Workbook

Sheet 2019 ALL N OLDER D95
A1: ACARA | B1: FROM DATE | C1: TO DATE | D1: DEPT | E1: WORLD | F1: DIVISION | G1: CLASS | H1: SUPPLIER | I1: BRAND | J1: SKU | K1: ARTICLE | L1: DESCRIPTION | M1: HARGA NORMAL | N1: DISKON | O1: HARGA PROMO | P1: DISCOUNT TYPE
A2: 2019 ALL ITEM & OLDER D95 | B2: 46121 | C2: 46127 | D2: 3260 | E2: 333 | F2: 3 | G2: 1 | H2: GRAHA CIPTA HARDIKA PT- 81455 | I2: AOS | J2: 19890836 | K2: TSH43RAS | L2: T-SHIRT ROCK & SOUL WORD 86:MISTY MEDIUM BROW:S | M2: 79900 | N2: 0.95 | O2: =M2-((95*M2)/100) -> 3995 | P2: PERCENTAGE
A3: =$A$2 -> 2019 ALL ITEM & OLDER D95 | B3: =$B$2 -> 46121 | C3: =$C$2 -> 46127 | D3: 3260 | E3: 333 | F3: 3 | G3: 1 | H3: GRAHA CIPTA HARDIKA PT- 81455 | I3: AOS | J3: 19892843 | K3: TSH43RST | L3: T-SHIRT ROCK STAR WORD 86:FROST GREY:M | M3: 79900 | N3: 0.95 | O3: =M3-((95*M3)/100) -> 3995 | P3: PERCENTAGE
A4: =$A$2 -> 2019 ALL ITEM & OLDER D95 | B4: =$B$2 -> 46121 | C4: =$C$2 -> 46127 | D4: 3260 | E4: 333 | F4: 3 | G4: 1 | H4: GRAHA CIPTA HARDIKA PT- 81455 | I4: AOS | J4: 20117973 | K4: TSH53IMA | L4: T-SHIRT IMAGINE WORD 86:MISTY MEDIUM BROWN:L | M4: 69900 | N4: 0.95 | O4: =M4-((95*M4)/100) -> 3495 | P4: PERCENTAGE
A5: =$A$2 -> 2019 ALL ITEM & OLDER D95 | B5: =$B$2 -> 46121 | C5: =$C$2 -> 46127 | D5: 3260 | E5: 333 | F5: 3 | G5: 1 | H5: GRAHA CIPTA HARDIKA PT- 81455 | I5: AOS | J5: 20124474 | K5: TSH53NOR | L5: T-SHIRT NO REGRET WORD 86:MISTY LIGHT BLUE:L | M5: 69900 | N5: 0.95 | O5: =M5-((95*M5)/100) -> 3495 | P5: PERCENTAGE
A6: =$A$2 -> 2019 ALL ITEM & OLDER D95 | B6: =$B$2 -> 46121 | C6: =$C$2 -> 46127 | D6: 3260 | E6: 333 | F6: 3 | G6: 1 | H6: GRAHA CIPTA HARDIKA PT- 81455 | I6: AOS | J6: 20547437 | K6: TSH83BER | L6: T-SHIRT BERLIN FLAG 86:MAROON:S | M6: 69900 | N6: 0.95 | O6: =M6-((95*M6)/100) -> 3495 | P6: PERCENTAGE
A7: =$A$2 -> 2019 ALL ITEM & OLDER D95 | B7: =$B$2 -> 46121 | C7: =$C$2 -> 46127 | D7: 3260 | E7: 333 | F7: 3 | G7: 1 | H7: GRAHA CIPTA HARDIKA PT- 81455 | I7: AOS | J7: 20547446 | K7: TSH83BER | L7: T-SHIRT BERLIN FLAG 86:MAROON:M | M7: 69900 | N7: 0.95 | O7: =M7-((95*M7)/100) -> 3495 | P7: PERCENTAGE
A8: =$A$2 -> 2019 ALL ITEM & OLDER D95 | B8: =$B$2 -> 46121 | C8: =$C$2 -> 46127 | D8: 3260 | E8: 333 | F8: 3 | G8: 1 | H8: GRAHA CIPTA HARDIKA PT- 81455 | I8: AOS | J8: 20547455 | K8: TSH83BER | L8: T-SHIRT BERLIN FLAG 86:MAROON:L | M8: 69900 | N8: 0.95 | O8: =M8-((95*M8)/100) -> 3495 | P8: PERCENTAGE
A9: =$A$2 -> 2019 ALL ITEM & OLDER D95 | B9: =$B$2 -> 46121 | C9: =$C$2 -> 46127 | D9: 3260 | E9: 333 | F9: 3 | G9: 1 | H9: GRAHA CIPTA HARDIKA PT- 81455 | I9: AOS | J9: 20564981 | K9: TSH83WIL | L9: T-SHIRT WILD LIFE ANIMAL LOGO 86:MISTY LIGHT BROW:M | M9: 69900 | N9: 0.95 | O9: =M9-((95*M9)/100) -> 3495 | P9: PERCENTAGE
A10: =$A$2 -> 2019 ALL ITEM & OLDER D95 | B10: =$B$2 -> 46121 | C10: =$C$2 -> 46127 | D10: 3260 | E10: 333 | F10: 3 | G10: 1 | H10: GRAHA CIPTA HARDIKA PT- 81455 | I10: AOS | J10: 20601001 | K10: CNS93ANO | L10: CUT N SEWN ANOMALI WORD 86:MAROON:M | M10: 79900 | N10: 0.95 | O10: =M10-((95*M10)/100) -> 3995 | P10: PERCENTAGE
A11: =$A$2 -> 2019 ALL ITEM & OLDER D95 | B11: =$B$2 -> 46121 | C11: =$C$2 -> 46127 | D11: 3260 | E11: 333 | F11: 3 | G11: 1 | H11: GRAHA CIPTA HARDIKA PT- 81455 | I11: AOS | J11: 20622060 | K11: TSH03DEN | L11: T-SHIRT DENIM ROCK WORDS 86:TURQUOISE:S | M11: 79900 | N11: 0.95 | O11: =M11-((95*M11)/100) -> 3995 | P11: PERCENTAGE
A12: =$A$2 -> 2019 ALL ITEM & OLDER D95 | B12: =$B$2 -> 46121 | C12: =$C$2 -> 46127 | D12: 3260 | E12: 333 | F12: 3 | G12: 1 | H12: GRAHA CIPTA HARDIKA PT- 81455 | I12: AOS | J12: 20622079 | K12: TSH03DEN | L12: T-SHIRT DENIM ROCK WORDS 86:TURQUOISE:M | M12: 79900 | N12: 0.95 | O12: =M12-((95*M12)/100) -> 3995 | P12: PERCENTAGE
A13: =$A$2 -> 2019 ALL ITEM & OLDER D95 | B13: =$B$2 -> 46121 | C13: =$C$2 -> 46127 | D13: 3260 | E13: 333 | F13: 3 | G13: 1 | H13: GRAHA CIPTA HARDIKA PT- 81455 | I13: AOS | J13: 20622382 | K13: TSH03COR | L13: T-SHIRT CORE DNM BIG FONT WORD 86:WINE:L | M13: 79900 | N13: 0.95 | O13: =M13-((95*M13)/100) -> 3995 | P13: PERCENTAGE
A14: =$A$2 -> 2019 ALL ITEM & OLDER D95 | B14: =$B$2 -> 46121 | C14: =$C$2 -> 46127 | D14: 3260 | E14: 333 | F14: 3 | G14: 1 | H14: GRAHA CIPTA HARDIKA PT- 81455 | I14: AOS | J14: 20622391 | K14: TSH03COR | L14: T-SHIRT CORE DNM BIG FONT WORD 86:WINE:XL | M14: 79900 | N14: 0.95 | O14: =M14-((95*M14)/100) -> 3995 | P14: PERCENTAGE
... A940: =$A$2 -> 2019 ALL ITEM & OLDER D95 | B940: =$B$2 -> 46121 | C940: =$C$2 -> 46127 | D940: 3260 | E940: 333 | F940: 3 | G940: 3 | H940: JAVA DESIGN SENTOSA CV. | I940: AOS | J940: 24925637 | K940: RSJ9M412 | L940: RAGLAN SHORT - HOME RUN 2 RSJ9 M412/BROWN:MISTY LIGHT BR:XL | M940: 99900 | N940: 0.95 | O940: =M940-((95*M940)/100) -> 4995 | P940: PERCENTAGE

Sheet 2020 ALL D85
A1: ACARA | B1: FROM DATE | C1: TO DATE | D1: DEPT | E1: WORLD | F1: DIVISION | G1: CLASS | H1: SUPPLIER | I1: BRAND | J1: SKU | K1: ARTICLE | L1: DESCRIPTION | M1: HARGA NORMAL | N1: DISKON | O1: HARGA PROMO | P1: DISCOUNT TYPE
A2: 2020 ALL D85 | B2: ='2019 ALL N OLDER D95'!$B$2 -> 46121 | C2: ='2019 ALL N OLDER D95'!$C$2 -> 46127 | D2: 3260 | E2: 333 | F2: 3 | G2: 2 | H2: 81461 | I2: AOS | J2: 26311662 | K2: LEB20-L3WH | L2: MUSLIM LONG SLEEVE 2020 - 3 LEB20-L3 WHITE:WHITE:S | M2: 159900 | N2: 0.85 | O2: =M2*(1-N2) -> 23985 | P2: PERCENTAGE
A3: =$A$2 -> 2020 ALL D85 | B3: ='2019 ALL N OLDER D95'!$B$2 -> 46121 | C3: ='2019 ALL N OLDER D95'!$C$2 -> 46127 | D3: 3260 | E3: 333 | F3: 3 | G3: 2 | H3: 81461 | I3: AOS | J3: 26311671 | K3: LEB20-L3WH | L3: MUSLIM LONG SLEEVE 2020 - 3 LEB20-L3 WHITE:WHITE:M | M3: 159900 | N3: =$N2 -> 0.85 | O3: =$O2 -> 23985 | P3: =$P2 -> PERCENTAGE
A4: =$A$2 -> 2020 ALL D85 | B4: ='2019 ALL N OLDER D95'!$B$2 -> 46121 | C4: ='2019 ALL N OLDER D95'!$C$2 -> 46127 | D4: 3260 | E4: 333 | F4: 3 | G4: 2 | H4: 81461 | I4: AOS | J4: 26311680 | K4: LEB20-L3WH | L4: MUSLIM LONG SLEEVE 2020 - 3 LEB20-L3 WHITE:WHITE:L | M4: 159900 | N4: =$N3 -> 0.85 | O4: =$O3 -> 23985 | P4: =$P3 -> PERCENTAGE
A5: =$A$2 -> 2020 ALL D85 | B5: ='2019 ALL N OLDER D95'!$B$2 -> 46121 | C5: ='2019 ALL N OLDER D95'!$C$2 -> 46127 | D5: 3260 | E5: 333 | F5: 3 | G5: 2 | H5: 81461 | I5: AOS | J5: 26311699 | K5: LEB20-L3WH | L5: MUSLIM LONG SLEEVE 2020 - 3 LEB20-L3 WHITE:WHITE:XL | M5: 159900 | N5: =$N4 -> 0.85 | O5: =$O4 -> 23985 | P5: =$P4 -> PERCENTAGE
A6: =$A$2 -> 2020 ALL D85 | B6: ='2019 ALL N OLDER D95'!$B$2 -> 46121 | C6: ='2019 ALL N OLDER D95'!$C$2 -> 46127 | D6: 3260 | E6: 333 | F6: 3 | G6: 2 | H6: 81461 | I6: AOS | J6: 26318923 | K6: LEB20-L4MDB | L6: MUSLIM LONG SLEEVE 2020 - 4 LEB20-L4 MDB:MISTY DARK BRO:S | M6: 159900 | N6: =$N5 -> 0.85 | O6: =$O5 -> 23985 | P6: =$P5 -> PERCENTAGE
A7: =$A$2 -> 2020 ALL D85 | B7: ='2019 ALL N OLDER D95'!$B$2 -> 46121 | C7: ='2019 ALL N OLDER D95'!$C$2 -> 46127 | D7: 3260 | E7: 333 | F7: 3 | G7: 2 | H7: 81461 | I7: AOS | J7: 26318932 | K7: LEB20-L4MDB | L7: MUSLIM LONG SLEEVE 2020 - 4 LEB20-L4 MDB:MISTY DARK BRO:M | M7: 159900 | N7: =$N6 -> 0.85 | O7: =$O6 -> 23985 | P7: =$P6 -> PERCENTAGE
A8: =$A$2 -> 2020 ALL D85 | B8: ='2019 ALL N OLDER D95'!$B$2 -> 46121 | C8: ='2019 ALL N OLDER D95'!$C$2 -> 46127 | D8: 3260 | E8: 333 | F8: 3 | G8: 2 | H8: 81461 | I8: AOS | J8: 26318941 | K8: LEB20-L4MDB | L8: MUSLIM LONG SLEEVE 2020 - 4 LEB20-L4 MDB:MISTY DARK BRO:L | M8: 159900 | N8: =$N7 -> 0.85 | O8: =$O7 -> 23985 | P8: =$P7 -> PERCENTAGE
A9: =$A$2 -> 2020 ALL D85 | B9: ='2019 ALL N OLDER D95'!$B$2 -> 46121 | C9: ='2019 ALL N OLDER D95'!$C$2 -> 46127 | D9: 3260 | E9: 333 | F9: 3 | G9: 2 | H9: 81461 | I9: AOS | J9: 26318950 | K9: LEB20-L4MDB | L9: MUSLIM LONG SLEEVE 2020 - 4 LEB20-L4 MDB:MISTY DARK BRO:XL | M9: 159900 | N9: =$N8 -> 0.85 | O9: =$O8 -> 23985 | P9: =$P8 -> PERCENTAGE
A10: =$A$2 -> 2020 ALL D85 | B10: ='2019 ALL N OLDER D95'!$B$2 -> 46121 | C10: ='2019 ALL N OLDER D95'!$C$2 -> 46127 | D10: 3260 | E10: 333 | F10: 3 | G10: 1 | H10: 81461 | I10: AOS | J10: 26321473 | K10: LEB20-S2WH | L10: MUSLIM SHORT SLEEVE 2020 - 2 LEB20-S2 WHITE:WHITE:S | M10: 149900 | N10: =$N9 -> 0.85 | O10: =$O9 -> 23985 | P10: =$P9 -> PERCENTAGE
A11: =$A$2 -> 2020 ALL D85 | B11: ='2019 ALL N OLDER D95'!$B$2 -> 46121 | C11: ='2019 ALL N OLDER D95'!$C$2 -> 46127 | D11: 3260 | E11: 333 | F11: 3 | G11: 1 | H11: 81461 | I11: AOS | J11: 26321482 | K11: LEB20-S2WH | L11: MUSLIM SHORT SLEEVE 2020 - 2 LEB20-S2 WHITE:WHITE:M | M11: 149900 | N11: =$N10 -> 0.85 | O11: =$O10 -> 23985 | P11: =$P10 -> PERCENTAGE
A12: =$A$2 -> 2020 ALL D85 | B12: ='2019 ALL N OLDER D95'!$B$2 -> 46121 | C12: ='2019 ALL N OLDER D95'!$C$2 -> 46127 | D12: 3260 | E12: 333 | F12: 3 | G12: 1 | H12: 81461 | I12: AOS | J12: 26321491 | K12: LEB20-S2WH | L12: MUSLIM SHORT SLEEVE 2020 - 2 LEB20-S2 WHITE:WHITE:L | M12: 149900 | N12: =$N11 -> 0.85 | O12: =$O11 -> 23985 | P12: =$P11 -> PERCENTAGE
A13: =$A$2 -> 2020 ALL D85 | B13: ='2019 ALL N OLDER D95'!$B$2 -> 46121 | C13: ='2019 ALL N OLDER D95'!$C$2 -> 46127 | D13: 3260 | E13: 333 | F13: 3 | G13: 1 | H13: 81461 | I13: AOS | J13: 26321508 | K13: LEB20-S2WH | L13: MUSLIM SHORT SLEEVE 2020 - 2 LEB20-S2 WHITE:WHITE:XL | M13: 149900 | N13: =$N12 -> 0.85 | O13: =$O12 -> 23985 | P13: =$P12 -> PERCENTAGE
A14: =$A$2 -> 2020 ALL D85 | B14: ='2019 ALL N OLDER D95'!$B$2 -> 46121 | C14: ='2019 ALL N OLDER D95'!$C$2 -> 46127 | D14: 3260 | E14: 333 | F14: 3 | G14: 1 | H14: 81461 | I14: AOS | J14: 26321759 | K14: LEB20-S4WH | L14: MUSLIM SHORT SLEEVE 2020 - 4 LEB20-S4 WHITE:WHITE:S | M14: 149900 | N14: =$N13 -> 0.85 | O14: =$O13 -> 23985 | P14: =$P13 -> PERCENTAGE
... A141: =$A$2 -> 2020 ALL D85 | B141: ='2019 ALL N OLDER D95'!$B$2 -> 46121 | C141: ='2019 ALL N OLDER D95'!$C$2 -> 46127 | D141: 3260 | E141: 333 | F141: 3 | G141: 4 | H141: 81323 | I141: AOS | J141: 27863403 | K141: CNY20-T2 | L141: SS T-SHIRT CNY 2021 - T-SHIRT CHINESE LETTERS CNY CO:CLASSIC RED:XL:GRAPHIC:SS T-SHIRT | M141: 89900 | N141: =$N140 -> 0.85 | O141: =$O140 -> 23985 | P141: =$P140 -> PERCENTAGE
A142: =$A$2 -> 2020 ALL D85 | B142: ='2019 ALL N OLDER D95'!$B$2 -> 46121 | C142: ='2019 ALL N OLDER D95'!$C$2 -> 46127 | D142: 3260 | E142: 333 | F142: 3 | G142: 1 | H142: PUTRA KREASINDO GARM | I142: AOS | J142: 26153208 | K142: STEP1BK | L142: TSHIRT PHOTOPRINT STE CALIFORNIA STEP1 BLACK | M142: 99900 | N142: =$N141 -> 0.85 | O142: =$O141 -> 23985 | P142: =$P141 -> PERCENTAGE
A143: =$A$2 -> 2020 ALL D85 | B143: ='2019 ALL N OLDER D95'!$B$2 -> 46121 | C143: ='2019 ALL N OLDER D95'!$C$2 -> 46127 | D143: 3260 | E143: 333 | F143: 3 | G143: 1 | H143: PUTRA KREASINDO GARM | I143: AOS | J143: 26153217 | K143: STEP1BK | L143: TSHIRT PHOTOPRINT STE CALIFORNIA STEP1 BLACK | M143: 99900 | N143: =$N142 -> 0.85 | O143: =$O142 -> 23985 | P143: =$P142 -> PERCENTAGE
A144: =$A$2 -> 2020 ALL D85 | B144: ='2019 ALL N OLDER D95'!$B$2 -> 46121 | C144: ='2019 ALL N OLDER D95'!$C$2 -> 46127 | D144: 3260 | E144: 333 | F144: 3 | G144: 1 | H144: PUTRA KREASINDO GARM | I144: AOS | J144: 26153226 | K144: STEP1BK | L144: TSHIRT PHOTOPRINT STE CALIFORNIA STEP1 BLACK | M144: 99900 | N144: =$N143 -> 0.85 | O144: =$O143 -> 23985 | P144: =$P143 -> PERCENTAGE
A145: =$A$2 -> 2020 ALL D85 | B145: ='2019 ALL N OLDER D95'!$B$2 -> 46121 | C145: ='2019 ALL N OLDER D95'!$C$2 -> 46127 | D145: 3260 | E145: 333 | F145: 3 | G145: 1 | H145: PUTRA KREASINDO GARM | I145: AOS | J145: 26153235 | K145: STEP1BK | L145: TSHIRT PHOTOPRINT STE CALIFORNIA STEP1 BLACK | M145: 99900 | N145: =$N144 -> 0.85 | O145: =$O144 -> 23985 | P145: =$P144 -> PERCENTAGE
A146: =$A$2 -> 2020 ALL D85 | B146: ='2019 ALL N OLDER D95'!$B$2 -> 46121 | C146: ='2019 ALL N OLDER D95'!$C$2 -> 46127 | D146: 3260 | E146: 333 | F146: 3 | G146: 1 | H146: PUTRA KREASINDO GARM | I146: AOS | J146: 26153244 | K146: STEP1NA | L146: TSHIRT PHOTOPRINT STE ENDLESS SUMMER STEP2 NAVY | M146: 99900 | N146: =$N145 -> 0.85 | O146: =$O145 -> 23985 | P146: =$P145 -> PERCENTAGE
A147: =$A$2 -> 2020 ALL D85 | B147: ='2019 ALL N OLDER D95'!$B$2 -> 46121 | C147: ='2019 ALL N OLDER D95'!$C$2 -> 46127 | D147: 3260 | E147: 333 | F147: 3 | G147: 1 | H147: PUTRA KREASINDO GARM | I147: AOS | J147: 26153253 | K147: STEP1NA | L147: TSHIRT PHOTOPRINT STE ENDLESS SUMMER STEP2 NAVY | M147: 99900 | N147: =$N146 -> 0.85 | O147: =$O146 -> 23985 | P147: =$P146 -> PERCENTAGE
A148: =$A$2 -> 2020 ALL D85 | B148: ='2019 ALL N OLDER D95'!$B$2 -> 46121 | C148: ='2019 ALL N OLDER D95'!$C$2 -> 46127 | D148: 3260 | E148: 333 | F148: 3 | G148: 1 | H148: PUTRA KREASINDO GARM | I148: AOS | J148: 26153262 | K148: STEP1NA | L148: TSHIRT PHOTOPRINT STE ENDLESS SUMMER STEP2 NAVY | M148: 99900 | N148: =$N147 -> 0.85 | O148: =$O147 -> 23985 | P148: =$P147 -> PERCENTAGE
A149: =$A$2 -> 2020 ALL D85 | B149: ='2019 ALL N OLDER D95'!$B$2 -> 46121 | C149: ='2019 ALL N OLDER D95'!$C$2 -> 46127 | D149: 3260 | E149: 333 | F149: 3 | G149: 1 | H149: PUTRA KREASINDO GARM | I149: AOS | J149: 26153271 | K149: STEP1NA | L149: TSHIRT PHOTOPRINT STE ENDLESS SUMMER STEP2 NAVY | M149: 99900 | N149: =$N148 -> 0.85 | O149: =$O148 -> 23985 | P149: =$P148 -> PERCENTAGE
A150: =$A$2 -> 2020 ALL D85 | B150: ='2019 ALL N OLDER D95'!$B$2 -> 46121 | C150: ='2019 ALL N OLDER D95'!$C$2 -> 46127 | D150: 3260 | E150: 333 | F150: 3 | G150: 1 | H150: PUTRA KREASINDO GARM | I150: AOS | J150: 26153280 | K150: STEP3NA | L150: TSHIRT PHOTOPRINT STE SUMMER STEP3 NAVY | M150: 99900 | N150: =$N149 -> 0.85 | O150: =$O149 -> 23985 | P150: =$P149 -> PERCENTAGE
A151: =$A$2 -> 2020 ALL D85 | B151: ='2019 ALL N OLDER D95'!$B$2 -> 46121 | C151: ='2019 ALL N OLDER D95'!$C$2 -> 46127 | D151: 3260 | E151: 333 | F151: 3 | G151: 1 | H151: PUTRA KREASINDO GARM | I151: AOS | J151: 26153299 | K151: STEP3NA | L151: TSHIRT PHOTOPRINT STE SUMMER STEP3 NAVY | M151: 99900 | N151: =$N150 -> 0.85 | O151: =$O150 -> 23985 | P151: =$P150 -> PERCENTAGE
A152: =$A$2 -> 2020 ALL D85 | B152: ='2019 ALL N OLDER D95'!$B$2 -> 46121 | C152: ='2019 ALL N OLDER D95'!$C$2 -> 46127 | D152: 3260 | E152: 333 | F152: 3 | G152: 1 | H152: PUTRA KREASINDO GARM | I152: AOS | J152: 26153306 | K152: STEP3NA | L152: TSHIRT PHOTOPRINT STE SUMMER STEP3 NAVY | M152: 99900 | N152: =$N151 -> 0.85 | O152: =$O151 -> 23985 | P152: =$P151 -> PERCENTAGE
A153: =$A$2 -> 2020 ALL D85 | B153: ='2019 ALL N OLDER D95'!$B$2 -> 46121 | C153: ='2019 ALL N OLDER D95'!$C$2 -> 46127 | D153: 3260 | E153: 333 | F153: 3 | G153: 1 | H153: PUTRA KREASINDO GARM | I153: AOS | J153: 26153315 | K153: STEP3NA | L153: TSHIRT PHOTOPRINT STE SUMMER STEP3 NAVY | M153: 99900 | N153: =$N152 -> 0.85 | O153: =$O152 -> 23985 | P153: =$P152 -> PERCENTAGE
... A1069: =$A$2 -> 2020 ALL D85 | B1069: ='2019 ALL N OLDER D95'!$B$2 -> 46121 | C1069: ='2019 ALL N OLDER D95'!$C$2 -> 46127 | D1069: 3260 | E1069: 333 | F1069: 3 | G1069: 3 | H1069: JAVA DESIGN SENTOSA | I1069: AOS | J1069: 26367531 | K1069: RSBM47 | L1069: RAGLAN SHORT BASIC RSBM47 M47/DARK BROWN 01-20:MISTY DARK BRO:XL | M1069: 89900 | N1069: =$N1068 -> 0.85 | O1069: =$O1068 -> 23985 | P1069: =$P1068 -> PERCENTAGE
A1070: =$A$2 -> 2020 ALL D85 | B1070: ='2019 ALL N OLDER D95'!$B$2 -> 46121 | C1070: ='2019 ALL N OLDER D95'!$C$2 -> 46127 | D1070: 3260 | E1070: 333 | F1070: 3 | G1070: 1 | J1070: 26133248 | K1070: BA-TDBK | L1070: TSHIRT FULLPRINT TIEDYE 1 BA-TDBK BLACK | M1070: 119900 | N1070: =$N1069 -> 0.85 | O1070: =$O1069 -> 23985 | P1070: =$P1069 -> PERCENTAGE
A1071: =$A$2 -> 2020 ALL D85 | B1071: ='2019 ALL N OLDER D95'!$B$2 -> 46121 | C1071: ='2019 ALL N OLDER D95'!$C$2 -> 46127 | D1071: 3260 | E1071: 333 | F1071: 3 | G1071: 1 | J1071: 26133257 | K1071: BA-TDBK | L1071: TSHIRT FULLPRINT TIEDYE 1 BA-TDBK BLACK | M1071: 119900 | N1071: =$N1070 -> 0.85 | O1071: =$O1070 -> 23985 | P1071: =$P1070 -> PERCENTAGE
A1072: =$A$2 -> 2020 ALL D85 | B1072: ='2019 ALL N OLDER D95'!$B$2 -> 46121 | C1072: ='2019 ALL N OLDER D95'!$C$2 -> 46127 | D1072: 3260 | E1072: 333 | F1072: 3 | G1072: 1 | J1072: 26133266 | K1072: BA-TDBK | L1072: TSHIRT FULLPRINT TIEDYE 1 BA-TDBK BLACK | M1072: 119900 | N1072: =$N1071 -> 0.85 | O1072: =$O1071 -> 23985 | P1072: =$P1071 -> PERCENTAGE
A1073: =$A$2 -> 2020 ALL D85 | B1073: ='2019 ALL N OLDER D95'!$B$2 -> 46121 | C1073: ='2019 ALL N OLDER D95'!$C$2 -> 46127 | D1073: 3260 | E1073: 333 | F1073: 3 | G1073: 1 | J1073: 26133275 | K1073: BA-TDBK | L1073: TSHIRT FULLPRINT TIEDYE 1 BA-TDBK BLACK | M1073: 119900 | N1073: =$N1072 -> 0.85 | O1073: =$O1072 -> 23985 | P1073: =$P1072 -> PERCENTAGE
A1074: =$A$2 -> 2020 ALL D85 | B1074: ='2019 ALL N OLDER D95'!$B$2 -> 46121 | C1074: ='2019 ALL N OLDER D95'!$C$2 -> 46127 | D1074: 3260 | E1074: 333 | F1074: 3 | G1074: 1 | J1074: 26133560 | K1074: BA-TDNA | L1074: TSHIRT FULLPRINT TIEDYE 2 BA-TDNA NAVY | M1074: 119900 | N1074: =$N1073 -> 0.85 | O1074: =$O1073 -> 23985 | P1074: =$P1073 -> PERCENTAGE
A1075: =$A$2 -> 2020 ALL D85 | B1075: ='2019 ALL N OLDER D95'!$B$2 -> 46121 | C1075: ='2019 ALL N OLDER D95'!$C$2 -> 46127 | D1075: 3260 | E1075: 333 | F1075: 3 | G1075: 1 | J1075: 26133579 | K1075: BA-TDNA | L1075: TSHIRT FULLPRINT TIEDYE 2 BA-TDNA NAVY | M1075: 119900 | N1075: =$N1074 -> 0.85 | O1075: =$O1074 -> 23985 | P1075: =$P1074 -> PERCENTAGE
A1076: =$A$2 -> 2020 ALL D85 | B1076: ='2019 ALL N OLDER D95'!$B$2 -> 46121 | C1076: ='2019 ALL N OLDER D95'!$C$2 -> 46127 | D1076: 3260 | E1076: 333 | F1076: 3 | G1076: 1 | J1076: 26133588 | K1076: BA-TDNA | L1076: TSHIRT FULLPRINT TIEDYE 2 BA-TDNA NAVY | M1076: 119900 | N1076: =$N1075 -> 0.85 | O1076: =$O1075 -> 23985 | P1076: =$P1075 -> PERCENTAGE
A1077: =$A$2 -> 2020 ALL D85 | B1077: ='2019 ALL N OLDER D95'!$B$2 -> 46121 | C1077: ='2019 ALL N OLDER D95'!$C$2 -> 46127 | D1077: 3260 | E1077: 333 | F1077: 3 | G1077: 1 | J1077: 26133597 | K1077: BA-TDNA | L1077: TSHIRT FULLPRINT TIEDYE 2 BA-TDNA NAVY | M1077: 119900 | N1077: =$N1076 -> 0.85 | O1077: =$O1076 -> 23985 | P1077: =$P1076 -> PERCENTAGE
A1078: =$A$2 -> 2020 ALL D85 | B1078: ='2019 ALL N OLDER D95'!$B$2 -> 46121 | C1078: ='2019 ALL N OLDER D95'!$C$2 -> 46127 | D1078: 3260 | E1078: 333 | F1078: 3 | G1078: 1 | J1078: 26133524 | K1078: BA-TDOL | L1078: TSHIRT FULLPRINT TIEDYE 2 BA-TDOL OLIVE | M1078: 119900 | N1078: =$N1077 -> 0.85 | O1078: =$O1077 -> 23985 | P1078: =$P1077 -> PERCENTAGE
A1079: =$A$2 -> 2020 ALL D85 | B1079: ='2019 ALL N OLDER D95'!$B$2 -> 46121 | C1079: ='2019 ALL N OLDER D95'!$C$2 -> 46127 | D1079: 3260 | E1079: 333 | F1079: 3 | G1079: 1 | J1079: 26133533 | K1079: BA-TDOL | L1079: TSHIRT FULLPRINT TIEDYE 2 BA-TDOL OLIVE | M1079: 119900 | N1079: =$N1078 -> 0.85 | O1079: =$O1078 -> 23985 | P1079: =$P1078 -> PERCENTAGE
A1080: =$A$2 -> 2020 ALL D85 | B1080: ='2019 ALL N OLDER D95'!$B$2 -> 46121 | C1080: ='2019 ALL N OLDER D95'!$C$2 -> 46127 | D1080: 3260 | E1080: 333 | F1080: 3 | G1080: 1 | J1080: 26133542 | K1080: BA-TDOL | L1080: TSHIRT FULLPRINT TIEDYE 2 BA-TDOL OLIVE | M1080: 119900 | N1080: =$N1079 -> 0.85 | O1080: =$O1079 -> 23985 | P1080: =$P1079 -> PERCENTAGE
A1081: =$A$2 -> 2020 ALL D85 | B1081: ='2019 ALL N OLDER D95'!$B$2 -> 46121 | C1081: ='2019 ALL N OLDER D95'!$C$2 -> 46127 | D1081: 3260 | E1081: 333 | F1081: 3 | G1081: 1 | J1081: 26133551 | K1081: BA-TDOL | L1081: TSHIRT FULLPRINT TIEDYE 2 BA-TDOL OLIVE | M1081: 119900 | N1081: =$N1080 -> 0.85 | O1081: =$O1080 -> 23985 | P1081: =$P1080 -> PERCENTAGE
... A1645: =$A$2 -> 2020 ALL D85 | B1645: ='2019 ALL N OLDER D95'!$B$2 -> 46121 | C1645: ='2019 ALL N OLDER D95'!$C$2 -> 46127 | D1645: 3260 | E1645: 333 | F1645: 3 | G1645: 3 | J1645: 26367611 | K1645: LRB-TO | L1645: RAGLAN LONG BASIC LRB-TO TOSCA/NAVY 02-20:TURQOUISE:XL | M1645: 109900 | N1645: =$N1644 -> 0.85 | O1645: =$O1644 -> 23985 | P1645: =$P1644 -> PERCENTAGE
A1646: =$A$2 -> 2020 ALL D85 | B1646: ='2019 ALL N OLDER D95'!$B$2 -> 46121 | C1646: ='2019 ALL N OLDER D95'!$C$2 -> 46127 | D1646: 3260 | E1646: 333 | F1646: 3 | G1646: 1 | H1646: 81328 | I1646: AOS | J1646: 27043683 | K1646: XMAS20T1 | L1646: SS T-SHIRT PRINT NEW SHAWL XMAS GREEN - XMAS COLLECT:CHRISTMAS G:S:GRAPHIC:SS T-SHIRT | M1646: 89900 | N1646: =$N1645 -> 0.85 | O1646: =$O1645 -> 23985 | P1646: =$P1645 -> PERCENTAGE
A1647: =$A$2 -> 2020 ALL D85 | B1647: ='2019 ALL N OLDER D95'!$B$2 -> 46121 | C1647: ='2019 ALL N OLDER D95'!$C$2 -> 46127 | D1647: 3260 | E1647: 333 | F1647: 3 | G1647: 1 | H1647: 81328 | I1647: AOS | J1647: 27043692 | K1647: XMAS20T1 | L1647: SS T-SHIRT PRINT NEW SHAWL XMAS GREEN - XMAS COLLECT:CHRISTMAS G:M:GRAPHIC:SS T-SHIRT | M1647: 89900 | N1647: =$N1646 -> 0.85 | O1647: =$O1646 -> 23985 | P1647: =$P1646 -> PERCENTAGE
A1648: =$A$2 -> 2020 ALL D85 | B1648: ='2019 ALL N OLDER D95'!$B$2 -> 46121 | C1648: ='2019 ALL N OLDER D95'!$C$2 -> 46127 | D1648: 3260 | E1648: 333 | F1648: 3 | G1648: 1 | H1648: 81328 | I1648: AOS | J1648: 27043709 | K1648: XMAS20T1 | L1648: SS T-SHIRT PRINT NEW SHAWL XMAS GREEN - XMAS COLLECT:CHRISTMAS G:L:GRAPHIC:SS T-SHIRT | M1648: 89900 | N1648: =$N1647 -> 0.85 | O1648: =$O1647 -> 23985 | P1648: =$P1647 -> PERCENTAGE
A1649: =$A$2 -> 2020 ALL D85 | B1649: ='2019 ALL N OLDER D95'!$B$2 -> 46121 | C1649: ='2019 ALL N OLDER D95'!$C$2 -> 46127 | D1649: 3260 | E1649: 333 | F1649: 3 | G1649: 1 | H1649: 81328 | I1649: AOS | J1649: 27043718 | K1649: XMAS20T1 | L1649: SS T-SHIRT PRINT NEW SHAWL XMAS GREEN - XMAS COLLECT:CHRISTMAS G:XL:GRAPHIC:SS T-SHIRT | M1649: 89900 | N1649: =$N1648 -> 0.85 | O1649: =$O1648 -> 23985 | P1649: =$P1648 -> PERCENTAGE
A1650: =$A$2 -> 2020 ALL D85 | B1650: ='2019 ALL N OLDER D95'!$B$2 -> 46121 | C1650: ='2019 ALL N OLDER D95'!$C$2 -> 46127 | D1650: 3260 | E1650: 333 | F1650: 3 | G1650: 1 | H1650: 81328 | I1650: AOS | J1650: 27043727 | K1650: XMAS20T1 | L1650: SS T-SHIRT PRINT NEW SHAWL XMAS MAROON - XMAS COLLECT:MAROON:S:GRAPHIC:SS T-SHIRT | M1650: 89900 | N1650: =$N1649 -> 0.85 | O1650: =$O1649 -> 23985 | P1650: =$P1649 -> PERCENTAGE
A1651: =$A$2 -> 2020 ALL D85 | B1651: ='2019 ALL N OLDER D95'!$B$2 -> 46121 | C1651: ='2019 ALL N OLDER D95'!$C$2 -> 46127 | D1651: 3260 | E1651: 333 | F1651: 3 | G1651: 1 | H1651: 81328 | I1651: AOS | J1651: 27043736 | K1651: XMAS20T1 | L1651: SS T-SHIRT PRINT NEW SHAWL XMAS MAROON - XMAS COLLECT:MAROON:M:GRAPHIC:SS T-SHIRT | M1651: 89900 | N1651: =$N1650 -> 0.85 | O1651: =$O1650 -> 23985 | P1651: =$P1650 -> PERCENTAGE
A1652: =$A$2 -> 2020 ALL D85 | B1652: ='2019 ALL N OLDER D95'!$B$2 -> 46121 | C1652: ='2019 ALL N OLDER D95'!$C$2 -> 46127 | D1652: 3260 | E1652: 333 | F1652: 3 | G1652: 1 | H1652: 81328 | I1652: AOS | J1652: 27043745 | K1652: XMAS20T1 | L1652: SS T-SHIRT PRINT NEW SHAWL XMAS MAROON - XMAS COLLECT:MAROON:L:GRAPHIC:SS T-SHIRT | M1652: 89900 | N1652: =$N1651 -> 0.85 | O1652: =$O1651 -> 23985 | P1652: =$P1651 -> PERCENTAGE
A1653: =$A$2 -> 2020 ALL D85 | B1653: ='2019 ALL N OLDER D95'!$B$2 -> 46121 | C1653: ='2019 ALL N OLDER D95'!$C$2 -> 46127 | D1653: 3260 | E1653: 333 | F1653: 3 | G1653: 1 | H1653: 81328 | I1653: AOS | J1653: 27043754 | K1653: XMAS20T1 | L1653: SS T-SHIRT PRINT NEW SHAWL XMAS MAROON - XMAS COLLECT:MAROON:XL:GRAPHIC:SS T-SHIRT | M1653: 89900 | N1653: =$N1652 -> 0.85 | O1653: =$O1652 -> 23985 | P1653: =$P1652 -> PERCENTAGE
A1654: =$A$2 -> 2020 ALL D85 | B1654: ='2019 ALL N OLDER D95'!$B$2 -> 46121 | C1654: ='2019 ALL N OLDER D95'!$C$2 -> 46127 | D1654: 3260 | E1654: 333 | F1654: 3 | G1654: 1 | H1654: 81328 | I1654: AOS | J1654: 27043807 | K1654: XMAS20T2 | L1654: SS T-SHIRT PRINT WONDERFUL TIME XMAS MAROON - XMAS C:MAROON:S:GRAPHIC:SS T-SHIRT | M1654: 89900 | N1654: =$N1653 -> 0.85 | O1654: =$O1653 -> 23985 | P1654: =$P1653 -> PERCENTAGE
A1655: =$A$2 -> 2020 ALL D85 | B1655: ='2019 ALL N OLDER D95'!$B$2 -> 46121 | C1655: ='2019 ALL N OLDER D95'!$C$2 -> 46127 | D1655: 3260 | E1655: 333 | F1655: 3 | G1655: 1 | H1655: 81328 | I1655: AOS | J1655: 27043816 | K1655: XMAS20T2 | L1655: SS T-SHIRT PRINT WONDERFUL TIME XMAS MAROON - XMAS C:MAROON:M:GRAPHIC:SS T-SHIRT | M1655: 89900 | N1655: =$N1654 -> 0.85 | O1655: =$O1654 -> 23985 | P1655: =$P1654 -> PERCENTAGE
A1656: =$A$2 -> 2020 ALL D85 | B1656: ='2019 ALL N OLDER D95'!$B$2 -> 46121 | C1656: ='2019 ALL N OLDER D95'!$C$2 -> 46127 | D1656: 3260 | E1656: 333 | F1656: 3 | G1656: 1 | H1656: 81328 | I1656: AOS | J1656: 27043825 | K1656: XMAS20T2 | L1656: SS T-SHIRT PRINT WONDERFUL TIME XMAS MAROON - XMAS C:MAROON:L:GRAPHIC:SS T-SHIRT | M1656: 89900 | N1656: =$N1655 -> 0.85 | O1656: =$O1655 -> 23985 | P1656: =$P1655 -> PERCENTAGE
A1657: =$A$2 -> 2020 ALL D85 | B1657: ='2019 ALL N OLDER D95'!$B$2 -> 46121 | C1657: ='2019 ALL N OLDER D95'!$C$2 -> 46127 | D1657: 3260 | E1657: 333 | F1657: 3 | G1657: 1 | H1657: 81328 | I1657: AOS | J1657: 27043834 | K1657: XMAS20T2 | L1657: SS T-SHIRT PRINT WONDERFUL TIME XMAS MAROON - XMAS C:MAROON:XL:GRAPHIC:SS T-SHIRT | M1657: 89900 | N1657: =$N1656 -> 0.85 | O1657: =$O1656 -> 23985 | P1657: =$P1656 -> PERCENTAGE
... A1693: =$A$2 -> 2020 ALL D85 | B1693: ='2019 ALL N OLDER D95'!$B$2 -> 46121 | C1693: ='2019 ALL N OLDER D95'!$C$2 -> 46127 | D1693: 3260 | E1693: 333 | F1693: 3 | G1693: 4 | H1693: 81328 | I1693: AOS | J1693: 27067023 | K1693: WBXMAS1 | L1693: SS T-SHIRT WB CHRISTMAS COLLECTION 2020 - LOONEY TUN:MAROON:XL:GRAPHIC:SS T-SHIRT | M1693: 99900 | N1693: =$N1692 -> 0.85 | O1693: =$O1692 -> 23985 | P1693: =$P1692 -> PERCENTAGE
A1694: =$A$2 -> 2020 ALL D85 | B1694: ='2019 ALL N OLDER D95'!$B$2 -> 46121 | C1694: ='2019 ALL N OLDER D95'!$C$2 -> 46127 | D1694: 3260 | E1694: 333 | F1694: 3 | G1694: 1 | H1694: GRAHA CIPTA HARDIKA | I1694: AOS | J1694: 27029878 | K1694: TG04-SC1 | L1694: SS T-SHIRT PRINT SUMMER COLLECTION -1 TG04-SC1:BLACK:S:GRAPHIC:SS T-SHIRT | M1694: 89900 | N1694: =$N1693 -> 0.85 | O1694: =$O1693 -> 23985 | P1694: =$P1693 -> PERCENTAGE
A1695: =$A$2 -> 2020 ALL D85 | B1695: ='2019 ALL N OLDER D95'!$B$2 -> 46121 | C1695: ='2019 ALL N OLDER D95'!$C$2 -> 46127 | D1695: 3260 | E1695: 333 | F1695: 3 | G1695: 1 | H1695: GRAHA CIPTA HARDIKA | I1695: AOS | J1695: 27029887 | K1695: TG04-SC1 | L1695: SS T-SHIRT PRINT SUMMER COLLECTION -1 TG04-SC1:BLACK:M:GRAPHIC:SS T-SHIRT | M1695: 89900 | N1695: =$N1694 -> 0.85 | O1695: =$O1694 -> 23985 | P1695: =$P1694 -> PERCENTAGE
A1696: =$A$2 -> 2020 ALL D85 | B1696: ='2019 ALL N OLDER D95'!$B$2 -> 46121 | C1696: ='2019 ALL N OLDER D95'!$C$2 -> 46127 | D1696: 3260 | E1696: 333 | F1696: 3 | G1696: 1 | H1696: GRAHA CIPTA HARDIKA | I1696: AOS | J1696: 27029896 | K1696: TG04-SC1 | L1696: SS T-SHIRT PRINT SUMMER COLLECTION -1 TG04-SC1:BLACK:L:GRAPHIC:SS T-SHIRT | M1696: 89900 | N1696: =$N1695 -> 0.85 | O1696: =$O1695 -> 23985 | P1696: =$P1695 -> PERCENTAGE
A1697: =$A$2 -> 2020 ALL D85 | B1697: ='2019 ALL N OLDER D95'!$B$2 -> 46121 | C1697: ='2019 ALL N OLDER D95'!$C$2 -> 46127 | D1697: 3260 | E1697: 333 | F1697: 3 | G1697: 1 | H1697: GRAHA CIPTA HARDIKA | I1697: AOS | J1697: 27029903 | K1697: TG04-SC1 | L1697: SS T-SHIRT PRINT SUMMER COLLECTION -1 TG04-SC1:BLACK:XL:GRAPHIC:SS T-SHIRT | M1697: 89900 | N1697: =$N1696 -> 0.85 | O1697: =$O1696 -> 23985 | P1697: =$P1696 -> PERCENTAGE
A1698: =$A$2 -> 2020 ALL D85 | B1698: ='2019 ALL N OLDER D95'!$B$2 -> 46121 | C1698: ='2019 ALL N OLDER D95'!$C$2 -> 46127 | D1698: 3260 | E1698: 333 | F1698: 3 | G1698: 1 | H1698: GRAHA CIPTA HARDIKA | I1698: AOS | J1698: 27029912 | K1698: TG04-SC2 | L1698: SS T-SHIRT PRINT SUMMER COLLECTION -2 TG04-SC2:MISTY MEDIUM:S:GRAPHIC:SS T-SHIRT | M1698: 89900 | N1698: =$N1697 -> 0.85 | O1698: =$O1697 -> 23985 | P1698: =$P1697 -> PERCENTAGE
A1699: =$A$2 -> 2020 ALL D85 | B1699: ='2019 ALL N OLDER D95'!$B$2 -> 46121 | C1699: ='2019 ALL N OLDER D95'!$C$2 -> 46127 | D1699: 3260 | E1699: 333 | F1699: 3 | G1699: 1 | H1699: GRAHA CIPTA HARDIKA | I1699: AOS | J1699: 27029921 | K1699: TG04-SC2 | L1699: SS T-SHIRT PRINT SUMMER COLLECTION -2 TG04-SC2:MISTY MEDIUM:M:GRAPHIC:SS T-SHIRT | M1699: 89900 | N1699: =$N1698 -> 0.85 | O1699: =$O1698 -> 23985 | P1699: =$P1698 -> PERCENTAGE
A1700: =$A$2 -> 2020 ALL D85 | B1700: ='2019 ALL N OLDER D95'!$B$2 -> 46121 | C1700: ='2019 ALL N OLDER D95'!$C$2 -> 46127 | D1700: 3260 | E1700: 333 | F1700: 3 | G1700: 1 | H1700: GRAHA CIPTA HARDIKA | I1700: AOS | J1700: 27029930 | K1700: TG04-SC2 | L1700: SS T-SHIRT PRINT SUMMER COLLECTION -2 TG04-SC2:MISTY MEDIUM:L:GRAPHIC:SS T-SHIRT | M1700: 89900 | N1700: =$N1699 -> 0.85 | O1700: =$O1699 -> 23985 | P1700: =$P1699 -> PERCENTAGE
A1701: =$A$2 -> 2020 ALL D85 | B1701: ='2019 ALL N OLDER D95'!$B$2 -> 46121 | C1701: ='2019 ALL N OLDER D95'!$C$2 -> 46127 | D1701: 3260 | E1701: 333 | F1701: 3 | G1701: 1 | H1701: GRAHA CIPTA HARDIKA | I1701: AOS | J1701: 27029949 | K1701: TG04-SC2 | L1701: SS T-SHIRT PRINT SUMMER COLLECTION -2 TG04-SC2:MISTY MEDIUM:XL:GRAPHIC:SS T-SHIRT | M1701: 89900 | N1701: =$N1700 -> 0.85 | O1701: =$O1700 -> 23985 | P1701: =$P1700 -> PERCENTAGE
A1702: =$A$2 -> 2020 ALL D85 | B1702: ='2019 ALL N OLDER D95'!$B$2 -> 46121 | C1702: ='2019 ALL N OLDER D95'!$C$2 -> 46127 | D1702: 3260 | E1702: 333 | F1702: 3 | G1702: 1 | H1702: GRAHA CIPTA HARDIKA | I1702: AOS | J1702: 27029958 | K1702: TG04-SC3 | L1702: SS T-SHIRT PRINT SUMMER COLLECTION -3 TG04-SC3:MISTY MEDIUM:S:GRAPHIC:SS T-SHIRT | M1702: 89900 | N1702: =$N1701 -> 0.85 | O1702: =$O1701 -> 23985 | P1702: =$P1701 -> PERCENTAGE
A1703: =$A$2 -> 2020 ALL D85 | B1703: ='2019 ALL N OLDER D95'!$B$2 -> 46121 | C1703: ='2019 ALL N OLDER D95'!$C$2 -> 46127 | D1703: 3260 | E1703: 333 | F1703: 3 | G1703: 1 | H1703: GRAHA CIPTA HARDIKA | I1703: AOS | J1703: 27029967 | K1703: TG04-SC3 | L1703: SS T-SHIRT PRINT SUMMER COLLECTION -3 TG04-SC3:MISTY MEDIUM:M:GRAPHIC:SS T-SHIRT | M1703: 89900 | N1703: =$N1702 -> 0.85 | O1703: =$O1702 -> 23985 | P1703: =$P1702 -> PERCENTAGE
A1704: =$A$2 -> 2020 ALL D85 | B1704: ='2019 ALL N OLDER D95'!$B$2 -> 46121 | C1704: ='2019 ALL N OLDER D95'!$C$2 -> 46127 | D1704: 3260 | E1704: 333 | F1704: 3 | G1704: 1 | H1704: GRAHA CIPTA HARDIKA | I1704: AOS | J1704: 27029976 | K1704: TG04-SC3 | L1704: SS T-SHIRT PRINT SUMMER COLLECTION -3 TG04-SC3:MISTY MEDIUM:L:GRAPHIC:SS T-SHIRT | M1704: 89900 | N1704: =$N1703 -> 0.85 | O1704: =$O1703 -> 23985 | P1704: =$P1703 -> PERCENTAGE
A1705: =$A$2 -> 2020 ALL D85 | B1705: ='2019 ALL N OLDER D95'!$B$2 -> 46121 | C1705: ='2019 ALL N OLDER D95'!$C$2 -> 46127 | D1705: 3260 | E1705: 333 | F1705: 3 | G1705: 1 | H1705: GRAHA CIPTA HARDIKA | I1705: AOS | J1705: 27029985 | K1705: TG04-SC3 | L1705: SS T-SHIRT PRINT SUMMER COLLECTION -3 TG04-SC3:MISTY MEDIUM:XL:GRAPHIC:SS T-SHIRT | M1705: 89900 | N1705: =$N1704 -> 0.85 | O1705: =$O1704 -> 23985 | P1705: =$P1704 -> PERCENTAGE
... A2005: =$A$2 -> 2020 ALL D85 | B2005: ='2019 ALL N OLDER D95'!$B$2 -> 46121 | C2005: ='2019 ALL N OLDER D95'!$C$2 -> 46127 | D2005: 3260 | E2005: 333 | F2005: 3 | G2005: 3 | H2005: JAVA DESIGN SENTOSA | I2005: AOS | J2005: 26968598 | K2005: ID20R3J2 | L2005: 3/4 RAGLAN T-SHIRT KITA INDONESIA - INDONESIA 2020 C:MISTY MEDIU:XL:TEXT:3/4 RAGLAN | M2005: 109900 | N2005: =$N2004 -> 0.85 | O2005: =$O2004 -> 23985 | P2005: =$P2004 -> PERCENTAGE
A2006: =$A$2 -> 2020 ALL D85 | B2006: ='2019 ALL N OLDER D95'!$B$2 -> 46121 | C2006: ='2019 ALL N OLDER D95'!$C$2 -> 46127 | D2006: 3260 | E2006: 333 | F2006: 3 | G2006: 1 | I2006: AOS | J2006: 26691949 | K2006: TJ04-ALBA1 | L2006: SS T-SHIRT PRINT SUMMER - ALOHA BAHAMAS 1 TJ04-ALBA1:BLACK:S:TEXT:SS T-SHIRT | M2006: 89900 | N2006: =$N2005 -> 0.85 | O2006: =$O2005 -> 23985 | P2006: =$P2005 -> PERCENTAGE
A2007: =$A$2 -> 2020 ALL D85 | B2007: ='2019 ALL N OLDER D95'!$B$2 -> 46121 | C2007: ='2019 ALL N OLDER D95'!$C$2 -> 46127 | D2007: 3260 | E2007: 333 | F2007: 3 | G2007: 1 | I2007: AOS | J2007: 26691958 | K2007: TJ04-ALBA1 | L2007: SS T-SHIRT PRINT SUMMER - ALOHA BAHAMAS 1 TJ04-ALBA1:BLACK:M:TEXT:SS T-SHIRT | M2007: 89900 | N2007: =$N2006 -> 0.85 | O2007: =$O2006 -> 23985 | P2007: =$P2006 -> PERCENTAGE
A2008: =$A$2 -> 2020 ALL D85 | B2008: ='2019 ALL N OLDER D95'!$B$2 -> 46121 | C2008: ='2019 ALL N OLDER D95'!$C$2 -> 46127 | D2008: 3260 | E2008: 333 | F2008: 3 | G2008: 1 | I2008: AOS | J2008: 26691967 | K2008: TJ04-ALBA1 | L2008: SS T-SHIRT PRINT SUMMER - ALOHA BAHAMAS 1 TJ04-ALBA1:BLACK:L:TEXT:SS T-SHIRT | M2008: 89900 | N2008: =$N2007 -> 0.85 | O2008: =$O2007 -> 23985 | P2008: =$P2007 -> PERCENTAGE
A2009: =$A$2 -> 2020 ALL D85 | B2009: ='2019 ALL N OLDER D95'!$B$2 -> 46121 | C2009: ='2019 ALL N OLDER D95'!$C$2 -> 46127 | D2009: 3260 | E2009: 333 | F2009: 3 | G2009: 1 | I2009: AOS | J2009: 26691976 | K2009: TJ04-ALBA1 | L2009: SS T-SHIRT PRINT SUMMER - ALOHA BAHAMAS 1 TJ04-ALBA1:BLACK:XL:TEXT:SS T-SHIRT | M2009: 89900 | N2009: =$N2008 -> 0.85 | O2009: =$O2008 -> 23985 | P2009: =$P2008 -> PERCENTAGE
A2010: =$A$2 -> 2020 ALL D85 | B2010: ='2019 ALL N OLDER D95'!$B$2 -> 46121 | C2010: ='2019 ALL N OLDER D95'!$C$2 -> 46127 | D2010: 3260 | E2010: 333 | F2010: 3 | G2010: 1 | I2010: AOS | J2010: 26692135 | K2010: TJ04-ALBA2 | L2010: SS T-SHIRT PRINT SUMMER - ALOHA BAHAMAS 2 TJ04-ALBA2:MISTY LIGHT:S:TEXT:SS T-SHIRT | M2010: 89900 | N2010: =$N2009 -> 0.85 | O2010: =$O2009 -> 23985 | P2010: =$P2009 -> PERCENTAGE
A2011: =$A$2 -> 2020 ALL D85 | B2011: ='2019 ALL N OLDER D95'!$B$2 -> 46121 | C2011: ='2019 ALL N OLDER D95'!$C$2 -> 46127 | D2011: 3260 | E2011: 333 | F2011: 3 | G2011: 1 | I2011: AOS | J2011: 26692144 | K2011: TJ04-ALBA2 | L2011: SS T-SHIRT PRINT SUMMER - ALOHA BAHAMAS 2 TJ04-ALBA2:MISTY LIGHT:M:TEXT:SS T-SHIRT | M2011: 89900 | N2011: =$N2010 -> 0.85 | O2011: =$O2010 -> 23985 | P2011: =$P2010 -> PERCENTAGE
A2012: =$A$2 -> 2020 ALL D85 | B2012: ='2019 ALL N OLDER D95'!$B$2 -> 46121 | C2012: ='2019 ALL N OLDER D95'!$C$2 -> 46127 | D2012: 3260 | E2012: 333 | F2012: 3 | G2012: 1 | I2012: AOS | J2012: 26692153 | K2012: TJ04-ALBA2 | L2012: SS T-SHIRT PRINT SUMMER - ALOHA BAHAMAS 2 TJ04-ALBA2:MISTY LIGHT:L:TEXT:SS T-SHIRT | M2012: 89900 | N2012: =$N2011 -> 0.85 | O2012: =$O2011 -> 23985 | P2012: =$P2011 -> PERCENTAGE
A2013: =$A$2 -> 2020 ALL D85 | B2013: ='2019 ALL N OLDER D95'!$B$2 -> 46121 | C2013: ='2019 ALL N OLDER D95'!$C$2 -> 46127 | D2013: 3260 | E2013: 333 | F2013: 3 | G2013: 1 | I2013: AOS | J2013: 26692162 | K2013: TJ04-ALBA2 | L2013: SS T-SHIRT PRINT SUMMER - ALOHA BAHAMAS 2 TJ04-ALBA2:MISTY LIGHT:XL:TEXT:SS T-SHIRT | M2013: 89900 | N2013: =$N2012 -> 0.85 | O2013: =$O2012 -> 23985 | P2013: =$P2012 -> PERCENTAGE
A2014: =$A$2 -> 2020 ALL D85 | B2014: ='2019 ALL N OLDER D95'!$B$2 -> 46121 | C2014: ='2019 ALL N OLDER D95'!$C$2 -> 46127 | D2014: 3260 | E2014: 333 | F2014: 3 | G2014: 1 | I2014: AOS | J2014: 26692171 | K2014: TJ04-ALHA1 | L2014: SS T-SHIRT PRINT SUMMER - ALOHA HAWAI 1 TJ04-ALHA1:NAVY BLUE:S:GRAPHIC:SS T-SHIRT | M2014: 89900 | N2014: =$N2013 -> 0.85 | O2014: =$O2013 -> 23985 | P2014: =$P2013 -> PERCENTAGE
A2015: =$A$2 -> 2020 ALL D85 | B2015: ='2019 ALL N OLDER D95'!$B$2 -> 46121 | C2015: ='2019 ALL N OLDER D95'!$C$2 -> 46127 | D2015: 3260 | E2015: 333 | F2015: 3 | G2015: 1 | I2015: AOS | J2015: 26692180 | K2015: TJ04-ALHA1 | L2015: SS T-SHIRT PRINT SUMMER - ALOHA HAWAI 1 TJ04-ALHA1:NAVY BLUE:M:GRAPHIC:SS T-SHIRT | M2015: 89900 | N2015: =$N2014 -> 0.85 | O2015: =$O2014 -> 23985 | P2015: =$P2014 -> PERCENTAGE
A2016: =$A$2 -> 2020 ALL D85 | B2016: ='2019 ALL N OLDER D95'!$B$2 -> 46121 | C2016: ='2019 ALL N OLDER D95'!$C$2 -> 46127 | D2016: 3260 | E2016: 333 | F2016: 3 | G2016: 1 | I2016: AOS | J2016: 26692199 | K2016: TJ04-ALHA1 | L2016: SS T-SHIRT PRINT SUMMER - ALOHA HAWAI 1 TJ04-ALHA1:NAVY BLUE:L:GRAPHIC:SS T-SHIRT | M2016: 89900 | N2016: =$N2015 -> 0.85 | O2016: =$O2015 -> 23985 | P2016: =$P2015 -> PERCENTAGE
A2017: =$A$2 -> 2020 ALL D85 | B2017: ='2019 ALL N OLDER D95'!$B$2 -> 46121 | C2017: ='2019 ALL N OLDER D95'!$C$2 -> 46127 | D2017: 3260 | E2017: 333 | F2017: 3 | G2017: 1 | I2017: AOS | J2017: 26692206 | K2017: TJ04-ALHA1 | L2017: SS T-SHIRT PRINT SUMMER - ALOHA HAWAI 1 TJ04-ALHA1:NAVY BLUE:XL:GRAPHIC:SS T-SHIRT | M2017: 89900 | N2017: =$N2016 -> 0.85 | O2017: =$O2016 -> 23985 | P2017: =$P2016 -> PERCENTAGE
... A2053: =$A$2 -> 2020 ALL D85 | B2053: ='2019 ALL N OLDER D95'!$B$2 -> 46121 | C2053: ='2019 ALL N OLDER D95'!$C$2 -> 46127 | D2053: 3260 | E2053: 333 | F2053: 3 | G2053: 1 | I2053: AOS | J2053: 26702954 | K2053: TS4-RR | L2053: SS T-SHIRT PHOTOPRINT RETRO: RELAX TS4-RR:BLACK:XL:GRAPHIC:SS T-SHIRT | M2053: 99900 | N2053: =$N2052 -> 0.85 | O2053: =$O2052 -> 23985 | P2053: =$P2052 -> PERCENTAGE
A2054: =$A$2 -> 2020 ALL D85 | B2054: ='2019 ALL N OLDER D95'!$B$2 -> 46121 | C2054: ='2019 ALL N OLDER D95'!$C$2 -> 46127 | D2054: 3260 | E2054: 333 | F2054: 3 | G2054: 1 | H2054: SAHABAT GARMINDO PT- | I2054: AOS | J2054: 24903151 | K2054: BSS30BMY | L2054: BIG SIZE PRINT - STREET STYLE BSS30 AQUA:AQUA:XL | M2054: 109900 | N2054: =$N2053 -> 0.85 | O2054: =$O2053 -> 23985 | P2054: =$P2053 -> PERCENTAGE
A2055: =$A$2 -> 2020 ALL D85 | B2055: ='2019 ALL N OLDER D95'!$B$2 -> 46121 | C2055: ='2019 ALL N OLDER D95'!$C$2 -> 46127 | D2055: 3260 | E2055: 333 | F2055: 3 | G2055: 1 | H2055: SAHABAT GARMINDO PT- | I2055: AOS | J2055: 24903160 | K2055: BSS30BMY | L2055: BIG SIZE PRINT - STREET STYLE BSS30 AQUA:AQUA:XXL | M2055: 109900 | N2055: =$N2054 -> 0.85 | O2055: =$O2054 -> 23985 | P2055: =$P2054 -> PERCENTAGE
A2056: =$A$2 -> 2020 ALL D85 | B2056: ='2019 ALL N OLDER D95'!$B$2 -> 46121 | C2056: ='2019 ALL N OLDER D95'!$C$2 -> 46127 | D2056: 3260 | E2056: 333 | F2056: 3 | G2056: 1 | H2056: SAHABAT GARMINDO PT- | I2056: AOS | J2056: 24903179 | K2056: BSS30BMY | L2056: BIG SIZE PRINT - STREET STYLE BSS30 AQUA:AQUA:XXXL | M2056: 109900 | N2056: =$N2055 -> 0.85 | O2056: =$O2055 -> 23985 | P2056: =$P2055 -> PERCENTAGE
A2057: =$A$2 -> 2020 ALL D85 | B2057: ='2019 ALL N OLDER D95'!$B$2 -> 46121 | C2057: ='2019 ALL N OLDER D95'!$C$2 -> 46127 | D2057: 3260 | E2057: 333 | F2057: 3 | G2057: 1 | H2057: SAHABAT GARMINDO PT- | I2057: AOS | J2057: 24903188 | K2057: BSS30BMY | L2057: BIG SIZE PRINT - STREET STYLE BSS30 AQUA:AQUA:4XL | M2057: 109900 | N2057: =$N2056 -> 0.85 | O2057: =$O2056 -> 23985 | P2057: =$P2056 -> PERCENTAGE
A2058: =$A$2 -> 2020 ALL D85 | B2058: ='2019 ALL N OLDER D95'!$B$2 -> 46121 | C2058: ='2019 ALL N OLDER D95'!$C$2 -> 46127 | D2058: 3260 | E2058: 333 | F2058: 3 | G2058: 1 | H2058: SAHABAT GARMINDO PT- | I2058: AOS | J2058: 24903268 | K2058: BSS31TE | L2058: BIG SIZE PRINT - SKATE ON ADVENTURE BSS31 TERA:RUSTIC ORANGE:XL | M2058: 109900 | N2058: =$N2057 -> 0.85 | O2058: =$O2057 -> 23985 | P2058: =$P2057 -> PERCENTAGE
A2059: =$A$2 -> 2020 ALL D85 | B2059: ='2019 ALL N OLDER D95'!$B$2 -> 46121 | C2059: ='2019 ALL N OLDER D95'!$C$2 -> 46127 | D2059: 3260 | E2059: 333 | F2059: 3 | G2059: 1 | H2059: SAHABAT GARMINDO PT- | I2059: AOS | J2059: 24903277 | K2059: BSS31TE | L2059: BIG SIZE PRINT - SKATE ON ADVENTURE BSS31 TERA:RUSTIC ORANGE:XXL | M2059: 109900 | N2059: =$N2058 -> 0.85 | O2059: =$O2058 -> 23985 | P2059: =$P2058 -> PERCENTAGE
A2060: =$A$2 -> 2020 ALL D85 | B2060: ='2019 ALL N OLDER D95'!$B$2 -> 46121 | C2060: ='2019 ALL N OLDER D95'!$C$2 -> 46127 | D2060: 3260 | E2060: 333 | F2060: 3 | G2060: 1 | H2060: SAHABAT GARMINDO PT- | I2060: AOS | J2060: 24903286 | K2060: BSS31TE | L2060: BIG SIZE PRINT - SKATE ON ADVENTURE BSS31 TERA:RUSTIC ORANGE:XXXL | M2060: 109900 | N2060: =$N2059 -> 0.85 | O2060: =$O2059 -> 23985 | P2060: =$P2059 -> PERCENTAGE
A2061: =$A$2 -> 2020 ALL D85 | B2061: ='2019 ALL N OLDER D95'!$B$2 -> 46121 | C2061: ='2019 ALL N OLDER D95'!$C$2 -> 46127 | D2061: 3260 | E2061: 333 | F2061: 3 | G2061: 1 | H2061: SAHABAT GARMINDO PT- | I2061: AOS | J2061: 24903295 | K2061: BSS31TE | L2061: BIG SIZE PRINT - SKATE ON ADVENTURE BSS31 TERA:RUSTIC ORANGE:4XL | M2061: 109900 | N2061: =$N2060 -> 0.85 | O2061: =$O2060 -> 23985 | P2061: =$P2060 -> PERCENTAGE
A2062: =$A$2 -> 2020 ALL D85 | B2062: ='2019 ALL N OLDER D95'!$B$2 -> 46121 | C2062: ='2019 ALL N OLDER D95'!$C$2 -> 46127 | D2062: 3260 | E2062: 333 | F2062: 3 | G2062: 1 | H2062: SAHABAT GARMINDO PT- | I2062: AOS | J2062: 24903508 | K2062: BSS33YE | L2062: BIG SIZE PRINT - LIFE IS SHORT BSS33 YELLOW:CLASSIC YELLO:XL | M2062: 109900 | N2062: =$N2061 -> 0.85 | O2062: =$O2061 -> 23985 | P2062: =$P2061 -> PERCENTAGE
A2063: =$A$2 -> 2020 ALL D85 | B2063: ='2019 ALL N OLDER D95'!$B$2 -> 46121 | C2063: ='2019 ALL N OLDER D95'!$C$2 -> 46127 | D2063: 3260 | E2063: 333 | F2063: 3 | G2063: 1 | H2063: SAHABAT GARMINDO PT- | I2063: AOS | J2063: 24903517 | K2063: BSS33YE | L2063: BIG SIZE PRINT - LIFE IS SHORT BSS33 YELLOW:CLASSIC YELLO:XXL | M2063: 109900 | N2063: =$N2062 -> 0.85 | O2063: =$O2062 -> 23985 | P2063: =$P2062 -> PERCENTAGE
A2064: =$A$2 -> 2020 ALL D85 | B2064: ='2019 ALL N OLDER D95'!$B$2 -> 46121 | C2064: ='2019 ALL N OLDER D95'!$C$2 -> 46127 | D2064: 3260 | E2064: 333 | F2064: 3 | G2064: 1 | H2064: SAHABAT GARMINDO PT- | I2064: AOS | J2064: 24903526 | K2064: BSS33YE | L2064: BIG SIZE PRINT - LIFE IS SHORT BSS33 YELLOW:CLASSIC YELLO:XXXL | M2064: 109900 | N2064: =$N2063 -> 0.85 | O2064: =$O2063 -> 23985 | P2064: =$P2063 -> PERCENTAGE
A2065: =$A$2 -> 2020 ALL D85 | B2065: ='2019 ALL N OLDER D95'!$B$2 -> 46121 | C2065: ='2019 ALL N OLDER D95'!$C$2 -> 46127 | D2065: 3260 | E2065: 333 | F2065: 3 | G2065: 1 | H2065: SAHABAT GARMINDO PT- | I2065: AOS | J2065: 24903535 | K2065: BSS33YE | L2065: BIG SIZE PRINT - LIFE IS SHORT BSS33 YELLOW:CLASSIC YELLO:4XL | M2065: 109900 | N2065: =$N2064 -> 0.85 | O2065: =$O2064 -> 23985 | P2065: =$P2064 -> PERCENTAGE
... A2241: =$A$2 -> 2020 ALL D85 | B2241: ='2019 ALL N OLDER D95'!$B$2 -> 46121 | C2241: ='2019 ALL N OLDER D95'!$C$2 -> 46127 | D2241: 3260 | E2241: 333 | F2241: 3 | G2241: 1 | H2241: JAVA DESIGN SENTOSA | I2241: AOS | J2241: 27069370 | K2241: TJ8-AMAC | L2241: SS T-SHIRT PRINT ANIMAL MACAW TJ8-AMAC:BLACK:XL:GRAPHIC:SS T-SHIRT | M2241: 109900 | N2241: =$N2240 -> 0.85 | O2241: =$O2240 -> 23985 | P2241: =$P2240 -> PERCENTAGE
A2242: =$A$2 -> 2020 ALL D85 | B2242: ='2019 ALL N OLDER D95'!$B$2 -> 46121 | C2242: ='2019 ALL N OLDER D95'!$C$2 -> 46127 | D2242: 3260 | E2242: 333 | F2242: 3 | G2242: 2 | I2242: AOS | J2242: 26857618 | K2242: LSG04-GS | L2242: LS T-SHIRT GEOMETRY: SPIRAL LSG04-GS:NAVY BLUE:S:GRAPHIC:LS T-SHIRT | M2242: 109900 | N2242: =$N2241 -> 0.85 | O2242: =$O2241 -> 23985 | P2242: =$P2241 -> PERCENTAGE
A2243: =$A$2 -> 2020 ALL D85 | B2243: ='2019 ALL N OLDER D95'!$B$2 -> 46121 | C2243: ='2019 ALL N OLDER D95'!$C$2 -> 46127 | D2243: 3260 | E2243: 333 | F2243: 3 | G2243: 2 | I2243: AOS | J2243: 26857627 | K2243: LSG04-GS | L2243: LS T-SHIRT GEOMETRY: SPIRAL LSG04-GS:NAVY BLUE:M:GRAPHIC:LS T-SHIRT | M2243: 109900 | N2243: =$N2242 -> 0.85 | O2243: =$O2242 -> 23985 | P2243: =$P2242 -> PERCENTAGE
A2244: =$A$2 -> 2020 ALL D85 | B2244: ='2019 ALL N OLDER D95'!$B$2 -> 46121 | C2244: ='2019 ALL N OLDER D95'!$C$2 -> 46127 | D2244: 3260 | E2244: 333 | F2244: 3 | G2244: 2 | I2244: AOS | J2244: 26857636 | K2244: LSG04-GS | L2244: LS T-SHIRT GEOMETRY: SPIRAL LSG04-GS:NAVY BLUE:L:GRAPHIC:LS T-SHIRT | M2244: 109900 | N2244: =$N2243 -> 0.85 | O2244: =$O2243 -> 23985 | P2244: =$P2243 -> PERCENTAGE
A2245: =$A$2 -> 2020 ALL D85 | B2245: ='2019 ALL N OLDER D95'!$B$2 -> 46121 | C2245: ='2019 ALL N OLDER D95'!$C$2 -> 46127 | D2245: 3260 | E2245: 333 | F2245: 3 | G2245: 2 | I2245: AOS | J2245: 26857645 | K2245: LSG04-GS | L2245: LS T-SHIRT GEOMETRY: SPIRAL LSG04-GS:NAVY BLUE:XL:GRAPHIC:LS T-SHIRT | M2245: 109900 | N2245: =$N2244 -> 0.85 | O2245: =$O2244 -> 23985 | P2245: =$P2244 -> PERCENTAGE
A2246: =$A$2 -> 2020 ALL D85 | B2246: ='2019 ALL N OLDER D95'!$B$2 -> 46121 | C2246: ='2019 ALL N OLDER D95'!$C$2 -> 46127 | D2246: 3260 | E2246: 333 | F2246: 3 | G2246: 2 | I2246: AOS | J2246: 26857574 | K2246: LSG04-GT | L2246: LS T-SHIRT GEOMETRY: TRIANGLE LSG04-GT:BLACK:S:GRAPHIC:LS T-SHIRT | M2246: 109900 | N2246: =$N2245 -> 0.85 | O2246: =$O2245 -> 23985 | P2246: =$P2245 -> PERCENTAGE
A2247: =$A$2 -> 2020 ALL D85 | B2247: ='2019 ALL N OLDER D95'!$B$2 -> 46121 | C2247: ='2019 ALL N OLDER D95'!$C$2 -> 46127 | D2247: 3260 | E2247: 333 | F2247: 3 | G2247: 2 | I2247: AOS | J2247: 26857583 | K2247: LSG04-GT | L2247: LS T-SHIRT GEOMETRY: TRIANGLE LSG04-GT:BLACK:M:GRAPHIC:LS T-SHIRT | M2247: 109900 | N2247: =$N2246 -> 0.85 | O2247: =$O2246 -> 23985 | P2247: =$P2246 -> PERCENTAGE
A2248: =$A$2 -> 2020 ALL D85 | B2248: ='2019 ALL N OLDER D95'!$B$2 -> 46121 | C2248: ='2019 ALL N OLDER D95'!$C$2 -> 46127 | D2248: 3260 | E2248: 333 | F2248: 3 | G2248: 2 | I2248: AOS | J2248: 26857592 | K2248: LSG04-GT | L2248: LS T-SHIRT GEOMETRY: TRIANGLE LSG04-GT:BLACK:L:GRAPHIC:LS T-SHIRT | M2248: 109900 | N2248: =$N2247 -> 0.85 | O2248: =$O2247 -> 23985 | P2248: =$P2247 -> PERCENTAGE
...

Sheet 2021 ALL D85
A1: ACARA | B1: FROM DATE | C1: TO DATE | D1: DEPT | E1: WORLD | F1: DIVISION | G1: CLASS | H1: SUPPLIER | I1: BRAND | J1: SKU | K1: ARTICLE | L1: DESCRIPTION | M1: HARGA NORMAL | N1: DISKON | O1: HARGA PROMO | P1: DISCOUNT TYPE
A2: 2021 ALL D85 | B2: ='2019 ALL N OLDER D95'!$B$2 -> 46121 | C2: ='2019 ALL N OLDER D95'!$C$2 -> 46127 | D2: 3260 | E2: 333 | F2: 3 | G2: 3 | H2: JAVA DESIGN SENTOSA CV. | I2: AOS | J2: 24398181 | K2: KIRSNA | L2: KI RAGLAN BASIC SHORT NAVY/M41 07-19:NAVY BLUE:S | M2: 89900 | N2: 0.85 | O2: =M2*(1-N2) -> 13485 | P2: PERCENTAGE
A3: =$A$2 -> 2021 ALL D85 | B3: ='2019 ALL N OLDER D95'!$B$2 -> 46121 | C3: ='2019 ALL N OLDER D95'!$C$2 -> 46127 | D3: 3260 | E3: 333 | F3: 3 | G3: 3 | H3: JAVA DESIGN SENTOSA CV. | I3: AOS | J3: 24398190 | K3: KIRSNA | L3: KI RAGLAN BASIC SHORT NAVY/M41 07-19:NAVY BLUE:M | M3: 89900 | N3: =$N2 -> 0.85 | O3: =$O2 -> 13485 | P3: =$P2 -> PERCENTAGE
A4: =$A$2 -> 2021 ALL D85 | B4: ='2019 ALL N OLDER D95'!$B$2 -> 46121 | C4: ='2019 ALL N OLDER D95'!$C$2 -> 46127 | D4: 3260 | E4: 333 | F4: 3 | G4: 3 | H4: JAVA DESIGN SENTOSA CV. | I4: AOS | J4: 24398207 | K4: KIRSNA | L4: KI RAGLAN BASIC SHORT NAVY/M41 07-19:NAVY BLUE:L | M4: 89900 | N4: =$N3 -> 0.85 | O4: =$O3 -> 13485 | P4: =$P3 -> PERCENTAGE
A5: =$A$2 -> 2021 ALL D85 | B5: ='2019 ALL N OLDER D95'!$B$2 -> 46121 | C5: ='2019 ALL N OLDER D95'!$C$2 -> 46127 | D5: 3260 | E5: 333 | F5: 3 | G5: 3 | H5: JAVA DESIGN SENTOSA CV. | I5: AOS | J5: 24398216 | K5: KIRSNA | L5: KI RAGLAN BASIC SHORT NAVY/M41 07-19:NAVY BLUE:XL | M5: 89900 | N5: =$N4 -> 0.85 | O5: =$O4 -> 13485 | P5: =$P4 -> PERCENTAGE
A6: =$A$2 -> 2021 ALL D85 | B6: ='2019 ALL N OLDER D95'!$B$2 -> 46121 | C6: ='2019 ALL N OLDER D95'!$C$2 -> 46127 | D6: 3260 | E6: 333 | F6: 3 | G6: 3 | H6: JAVA DESIGN SENTOSA CV. | I6: AOS | J6: 24398225 | K6: KIRSTO | L6: KI RAGLAN BASIC SHORT TOSCA/3T BLUE 07-19:TURQUOISE:S | M6: 89900 | N6: =$N5 -> 0.85 | O6: =$O5 -> 13485 | P6: =$P5 -> PERCENTAGE
A7: =$A$2 -> 2021 ALL D85 | B7: ='2019 ALL N OLDER D95'!$B$2 -> 46121 | C7: ='2019 ALL N OLDER D95'!$C$2 -> 46127 | D7: 3260 | E7: 333 | F7: 3 | G7: 3 | H7: JAVA DESIGN SENTOSA CV. | I7: AOS | J7: 24398234 | K7: KIRSTO | L7: KI RAGLAN BASIC SHORT TOSCA/3T BLUE 07-19:TURQUOISE:M | M7: 89900 | N7: =$N6 -> 0.85 | O7: =$O6 -> 13485 | P7: =$P6 -> PERCENTAGE
A8: =$A$2 -> 2021 ALL D85 | B8: ='2019 ALL N OLDER D95'!$B$2 -> 46121 | C8: ='2019 ALL N OLDER D95'!$C$2 -> 46127 | D8: 3260 | E8: 333 | F8: 3 | G8: 3 | H8: JAVA DESIGN SENTOSA CV. | I8: AOS | J8: 24398243 | K8: KIRSTO | L8: KI RAGLAN BASIC SHORT TOSCA/3T BLUE 07-19:TURQUOISE:L | M8: 89900 | N8: =$N7 -> 0.85 | O8: =$O7 -> 13485 | P8: =$P7 -> PERCENTAGE
A9: =$A$2 -> 2021 ALL D85 | B9: ='2019 ALL N OLDER D95'!$B$2 -> 46121 | C9: ='2019 ALL N OLDER D95'!$C$2 -> 46127 | D9: 3260 | E9: 333 | F9: 3 | G9: 3 | H9: JAVA DESIGN SENTOSA CV. | I9: AOS | J9: 24398252 | K9: KIRSTO | L9: KI RAGLAN BASIC SHORT TOSCA/3T BLUE 07-19:TURQUOISE:XL | M9: 89900 | N9: =$N8 -> 0.85 | O9: =$O8 -> 13485 | P9: =$P8 -> PERCENTAGE
A10: =$A$2 -> 2021 ALL D85 | B10: ='2019 ALL N OLDER D95'!$B$2 -> 46121 | C10: ='2019 ALL N OLDER D95'!$C$2 -> 46127 | D10: 3260 | E10: 333 | F10: 3 | G10: 3 | H10: JAVA DESIGN SENTOSA CV. | I10: AOS | J10: 24398305 | K10: KIRSYE | L10: KI RAGLAN BASIC SHORTYELLOW/CHARCOAL 07-19 :CLASSIC YELLOW:S | M10: 89900 | N10: =$N9 -> 0.85 | O10: =$O9 -> 13485 | P10: =$P9 -> PERCENTAGE
A11: =$A$2 -> 2021 ALL D85 | B11: ='2019 ALL N OLDER D95'!$B$2 -> 46121 | C11: ='2019 ALL N OLDER D95'!$C$2 -> 46127 | D11: 3260 | E11: 333 | F11: 3 | G11: 3 | H11: JAVA DESIGN SENTOSA CV. | I11: AOS | J11: 24398314 | K11: KIRSYE | L11: KI RAGLAN BASIC SHORTYELLOW/CHARCOAL 07-19:CLASSIC YELLOW:M | M11: 89900 | N11: =$N10 -> 0.85 | O11: =$O10 -> 13485 | P11: =$P10 -> PERCENTAGE
A12: =$A$2 -> 2021 ALL D85 | B12: ='2019 ALL N OLDER D95'!$B$2 -> 46121 | C12: ='2019 ALL N OLDER D95'!$C$2 -> 46127 | D12: 3260 | E12: 333 | F12: 3 | G12: 3 | H12: JAVA DESIGN SENTOSA CV. | I12: AOS | J12: 24398323 | K12: KIRSYE | L12: KI RAGLAN BASIC SHORTYELLOW/CHARCOAL 07-19:CLASSIC YELLOW:L | M12: 89900 | N12: =$N11 -> 0.85 | O12: =$O11 -> 13485 | P12: =$P11 -> PERCENTAGE
A13: =$A$2 -> 2021 ALL D85 | B13: ='2019 ALL N OLDER D95'!$B$2 -> 46121 | C13: ='2019 ALL N OLDER D95'!$C$2 -> 46127 | D13: 3260 | E13: 333 | F13: 3 | G13: 3 | H13: JAVA DESIGN SENTOSA CV. | I13: AOS | J13: 24398332 | K13: KIRSYE | L13: KI RAGLAN BASIC SHORTYELLOW/CHARCOAL 07-19:CLASSIC YELLOW:XL | M13: 89900 | N13: =$N12 -> 0.85 | O13: =$O12 -> 13485 | P13: =$P12 -> PERCENTAGE
A14: =$A$2 -> 2021 ALL D85 | B14: ='2019 ALL N OLDER D95'!$B$2 -> 46121 | C14: ='2019 ALL N OLDER D95'!$C$2 -> 46127 | D14: 3260 | E14: 333 | F14: 3 | G14: 5 | H14: JAVA DESIGN | I14: AOS | J14: 20140563 | K14: KI-R34PA | L14: KI RAGLAN BASIC 3/4 POCKET 05-17 105:WINE:XL | M14: 89900 | N14: =$N13 -> 0.85 | O14: =$O13 -> 13485 | P14: =$P13 -> PERCENTAGE
... A252: =$A$2 -> 2021 ALL D85 | B252: ='2019 ALL N OLDER D95'!$B$2 -> 46121 | C252: ='2019 ALL N OLDER D95'!$C$2 -> 46127 | D252: 3260 | E252: 333 | F252: 3 | G252: 1 | H252: JAVA DESIGN SENTOSA | I252: AOS | J252: 32639842 | K252: ID21TJ1 | L252: SS T-SHIRT INDONESIA COLL 2021 - IND ONESIAN MAP ID21TJ1:CLASSIC RE:S:GRAPHIC:SS T-SHIRT | M252: 99900 | N252: =$N251 -> 0.85 | O252: =$O251 -> 13485 | P252: =$P251 -> PERCENTAGE
A253: =$A$2 -> 2021 ALL D85 | B253: ='2019 ALL N OLDER D95'!$B$2 -> 46121 | C253: ='2019 ALL N OLDER D95'!$C$2 -> 46127 | D253: 3260 | E253: 333 | F253: 3 | G253: 1 | H253: JAVA DESIGN SENTOSA | I253: AOS | J253: 32639851 | K253: ID21TJ1 | L253: SS T-SHIRT INDONESIA COLL 2021 - IND ONESIAN MAP ID21TJ1:CLASSIC RE:M:GRAPHIC:SS T-SHIRT | M253: 99900 | N253: =$N252 -> 0.85 | O253: =$O252 -> 13485 | P253: =$P252 -> PERCENTAGE
A254: =$A$2 -> 2021 ALL D85 | B254: ='2019 ALL N OLDER D95'!$B$2 -> 46121 | C254: ='2019 ALL N OLDER D95'!$C$2 -> 46127 | D254: 3260 | E254: 333 | F254: 3 | G254: 1 | H254: JAVA DESIGN SENTOSA | I254: AOS | J254: 32639860 | K254: ID21TJ1 | L254: SS T-SHIRT INDONESIA COLL 2021 - IND ONESIAN MAP ID21TJ1:CLASSIC RE:L:GRAPHIC:SS T-SHIRT | M254: 99900 | N254: =$N253 -> 0.85 | O254: =$O253 -> 13485 | P254: =$P253 -> PERCENTAGE
A255: =$A$2 -> 2021 ALL D85 | B255: ='2019 ALL N OLDER D95'!$B$2 -> 46121 | C255: ='2019 ALL N OLDER D95'!$C$2 -> 46127 | D255: 3260 | E255: 333 | F255: 3 | G255: 1 | H255: JAVA DESIGN SENTOSA | I255: AOS | J255: 32639879 | K255: ID21TJ1 | L255: SS T-SHIRT INDONESIA COLL 2021 - IND ONESIAN MAP ID21TJ1:CLASSIC RE:XL:GRAPHIC:SS T-SHIRT | M255: 99900 | N255: =$N254 -> 0.85 | O255: =$O254 -> 13485 | P255: =$P254 -> PERCENTAGE
A256: =$A$2 -> 2021 ALL D85 | B256: ='2019 ALL N OLDER D95'!$B$2 -> 46121 | C256: ='2019 ALL N OLDER D95'!$C$2 -> 46127 | D256: 3260 | E256: 333 | F256: 3 | G256: 1 | H256: JAVA DESIGN SENTOSA | I256: AOS | J256: 32639922 | K256: ID21TJ2 | L256: SS T-SHIRT INDONESIA COLL 2021 - GOD BLESS INDONESIA:WHITE:S:TEXT:SS T-SHIRT | M256: 99900 | N256: =$N255 -> 0.85 | O256: =$O255 -> 13485 | P256: =$P255 -> PERCENTAGE
A257: =$A$2 -> 2021 ALL D85 | B257: ='2019 ALL N OLDER D95'!$B$2 -> 46121 | C257: ='2019 ALL N OLDER D95'!$C$2 -> 46127 | D257: 3260 | E257: 333 | F257: 3 | G257: 1 | H257: JAVA DESIGN SENTOSA | I257: AOS | J257: 32639931 | K257: ID21TJ2 | L257: SS T-SHIRT INDONESIA COLL 2021 - GOD BLESS INDONESIA:WHITE:M:TEXT:SS T-SHIRT | M257: 99900 | N257: =$N256 -> 0.85 | O257: =$O256 -> 13485 | P257: =$P256 -> PERCENTAGE
A258: =$A$2 -> 2021 ALL D85 | B258: ='2019 ALL N OLDER D95'!$B$2 -> 46121 | C258: ='2019 ALL N OLDER D95'!$C$2 -> 46127 | D258: 3260 | E258: 333 | F258: 3 | G258: 1 | H258: JAVA DESIGN SENTOSA | I258: AOS | J258: 32639940 | K258: ID21TJ2 | L258: SS T-SHIRT INDONESIA COLL 2021 - GOD BLESS INDONESIA:WHITE:L:TEXT:SS T-SHIRT | M258: 99900 | N258: =$N257 -> 0.85 | O258: =$O257 -> 13485 | P258: =$P257 -> PERCENTAGE
A259: =$A$2 -> 2021 ALL D85 | B259: ='2019 ALL N OLDER D95'!$B$2 -> 46121 | C259: ='2019 ALL N OLDER D95'!$C$2 -> 46127 | D259: 3260 | E259: 333 | F259: 3 | G259: 1 | H259: JAVA DESIGN SENTOSA | I259: AOS | J259: 32639959 | K259: ID21TJ2 | L259: SS T-SHIRT INDONESIA COLL 2021 - GOD BLESS INDONESIA:WHITE:XL:TEXT:SS T-SHIRT | M259: 99900 | N259: =$N258 -> 0.85 | O259: =$O258 -> 13485 | P259: =$P258 -> PERCENTAGE
A260: =$A$2 -> 2021 ALL D85 | B260: ='2019 ALL N OLDER D95'!$B$2 -> 46121 | C260: ='2019 ALL N OLDER D95'!$C$2 -> 46127 | D260: 3260 | E260: 333 | F260: 3 | G260: 1 | H260: JAVA DESIGN SENTOSA | I260: AOS | J260: 32640009 | K260: ID21TJ3 | L260: SS T-SHIRT INDONESIA COLL 2021 - PRINT BATIK 1 ID21TJ3:BLACK:S:GRAPHIC:SS T-SHIRT | M260: 99900 | N260: =$N259 -> 0.85 | O260: =$O259 -> 13485 | P260: =$P259 -> PERCENTAGE
A261: =$A$2 -> 2021 ALL D85 | B261: ='2019 ALL N OLDER D95'!$B$2 -> 46121 | C261: ='2019 ALL N OLDER D95'!$C$2 -> 46127 | D261: 3260 | E261: 333 | F261: 3 | G261: 1 | H261: JAVA DESIGN SENTOSA | I261: AOS | J261: 32640018 | K261: ID21TJ3 | L261: SS T-SHIRT INDONESIA COLL 2021 - PRINT BATIK 1 ID21TJ3:BLACK:M:GRAPHIC:SS T-SHIRT | M261: 99900 | N261: =$N260 -> 0.85 | O261: =$O260 -> 13485 | P261: =$P260 -> PERCENTAGE
A262: =$A$2 -> 2021 ALL D85 | B262: ='2019 ALL N OLDER D95'!$B$2 -> 46121 | C262: ='2019 ALL N OLDER D95'!$C$2 -> 46127 | D262: 3260 | E262: 333 | F262: 3 | G262: 1 | H262: JAVA DESIGN SENTOSA | I262: AOS | J262: 32640027 | K262: ID21TJ3 | L262: SS T-SHIRT INDONESIA COLL 2021 - PRINT BATIK 1 ID21TJ3:BLACK:L:GRAPHIC:SS T-SHIRT | M262: 99900 | N262: =$N261 -> 0.85 | O262: =$O261 -> 13485 | P262: =$P261 -> PERCENTAGE
A263: =$A$2 -> 2021 ALL D85 | B263: ='2019 ALL N OLDER D95'!$B$2 -> 46121 | C263: ='2019 ALL N OLDER D95'!$C$2 -> 46127 | D263: 3260 | E263: 333 | F263: 3 | G263: 1 | H263: JAVA DESIGN SENTOSA | I263: AOS | J263: 32640036 | K263: ID21TJ3 | L263: SS T-SHIRT INDONESIA COLL 2021 - PRINT BATIK 1 ID21TJ3:BLACK:XL:GRAPHIC:SS T-SHIRT | M263: 99900 | N263: =$N262 -> 0.85 | O263: =$O262 -> 13485 | P263: =$P262 -> PERCENTAGE
A264: =$A$2 -> 2021 ALL D85 | B264: ='2019 ALL N OLDER D95'!$B$2 -> 46121 | C264: ='2019 ALL N OLDER D95'!$C$2 -> 46127 | D264: 3260 | E264: 333 | F264: 3 | G264: 1 | H264: JAVA DESIGN SENTOSA | I264: AOS | J264: 32640045 | K264: ID21TJ3 | L264: SS T-SHIRT INDONESIA COLL 2021 - PRINT BATIK 1 ID21TJ3:CLASSIC RE:S:GRAPHIC:SS T-SHIRT | M264: 99900 | N264: =$N263 -> 0.85 | O264: =$O263 -> 13485 | P264: =$P263 -> PERCENTAGE
... A287: =$A$2 -> 2021 ALL D85 | B287: ='2019 ALL N OLDER D95'!$B$2 -> 46121 | C287: ='2019 ALL N OLDER D95'!$C$2 -> 46127 | D287: 3260 | E287: 333 | F287: 3 | G287: 2 | H287: JAVA DESIGN SENTOSA | I287: AOS | J287: 32641151 | K287: ID21LJ1 | L287: LS T-SHIRT INDONESIA COLL 2021 - INDONESIA IS AWESOM:MISTY LIGHT:XL:TEXT:LS T-SHIRT | M287: 109900 | N287: =$N286 -> 0.85 | O287: =$O286 -> 13485 | P287: =$P286 -> PERCENTAGE
A288: =$A$2 -> 2021 ALL D85 | B288: ='2019 ALL N OLDER D95'!B2 -> 46121 | C288: ='2019 ALL N OLDER D95'!C2 -> 46127 | D288: 3260 | E288: 333 | F288: 3 | G288: 1 | H288: 81461 | I288: AOS | J288: 28093485 | K288: LEB21-S3 | L288: SS KOKO MUSLIM SHORT SLEEVE 2021 - MISTY DARK BROWN:KHAKI:S:TEXTURE:SS KOKO | M288: 149900 | N288: =$N287 -> 0.85 | O288: =$O287 -> 13485 | P288: =$P287 -> PERCENTAGE
A289: =$A$2 -> 2021 ALL D85 | B289: ='2019 ALL N OLDER D95'!B3 -> 46121 | C289: ='2019 ALL N OLDER D95'!C3 -> 46127 | D289: 3260 | E289: 333 | F289: 3 | G289: 1 | H289: 81461 | I289: AOS | J289: 28093494 | K289: LEB21-S3 | L289: SS KOKO MUSLIM SHORT SLEEVE 2021 - MISTY DARK BROWN:KHAKI:M:TEXTURE:SS KOKO | M289: 149900 | N289: =$N288 -> 0.85 | O289: =$O288 -> 13485 | P289: =$P288 -> PERCENTAGE
A290: =$A$2 -> 2021 ALL D85 | B290: ='2019 ALL N OLDER D95'!B4 -> 46121 | C290: ='2019 ALL N OLDER D95'!C4 -> 46127 | D290: 3260 | E290: 333 | F290: 3 | G290: 1 | H290: 81461 | I290: AOS | J290: 28093501 | K290: LEB21-S3 | L290: SS KOKO MUSLIM SHORT SLEEVE 2021 - MISTY DARK BROWN:KHAKI:L:TEXTURE:SS KOKO | M290: 149900 | N290: =$N289 -> 0.85 | O290: =$O289 -> 13485 | P290: =$P289 -> PERCENTAGE
A291: =$A$2 -> 2021 ALL D85 | B291: ='2019 ALL N OLDER D95'!B5 -> 46121 | C291: ='2019 ALL N OLDER D95'!C5 -> 46127 | D291: 3260 | E291: 333 | F291: 3 | G291: 1 | H291: 81461 | I291: AOS | J291: 28093510 | K291: LEB21-S3 | L291: SS KOKO MUSLIM SHORT SLEEVE 2021 - MISTY DARK BROWN:KHAKI:XL:TEXTURE:SS KOKO | M291: 149900 | N291: =$N290 -> 0.85 | O291: =$O290 -> 13485 | P291: =$P290 -> PERCENTAGE
A292: =$A$2 -> 2021 ALL D85 | B292: ='2019 ALL N OLDER D95'!B6 -> 46121 | C292: ='2019 ALL N OLDER D95'!C6 -> 46127 | D292: 3260 | E292: 333 | F292: 3 | G292: 1 | H292: 81461 | I292: AOS | J292: 28093403 | K292: LEB21-S7 | L292: SS KOKO MUSLIM SHORT SLEEVE 2021 - WHITE LEB21-S7:WHITE:S:TEXTURE:SS KOKO | M292: 149900 | N292: =$N291 -> 0.85 | O292: =$O291 -> 13485 | P292: =$P291 -> PERCENTAGE
A293: =$A$2 -> 2021 ALL D85 | B293: ='2019 ALL N OLDER D95'!B7 -> 46121 | C293: ='2019 ALL N OLDER D95'!C7 -> 46127 | D293: 3260 | E293: 333 | F293: 3 | G293: 1 | H293: 81461 | I293: AOS | J293: 28093412 | K293: LEB21-S7 | L293: SS KOKO MUSLIM SHORT SLEEVE 2021 - WHITE LEB21-S7:WHITE:M:TEXTURE:SS KOKO | M293: 149900 | N293: =$N292 -> 0.85 | O293: =$O292 -> 13485 | P293: =$P292 -> PERCENTAGE
A294: =$A$2 -> 2021 ALL D85 | B294: ='2019 ALL N OLDER D95'!B8 -> 46121 | C294: ='2019 ALL N OLDER D95'!C8 -> 46127 | D294: 3260 | E294: 333 | F294: 3 | G294: 1 | H294: 81461 | I294: AOS | J294: 28093421 | K294: LEB21-S7 | L294: SS KOKO MUSLIM SHORT SLEEVE 2021 - WHITE LEB21-S7:WHITE:L:TEXTURE:SS KOKO | M294: 149900 | N294: =$N293 -> 0.85 | O294: =$O293 -> 13485 | P294: =$P293 -> PERCENTAGE
A295: =$A$2 -> 2021 ALL D85 | B295: ='2019 ALL N OLDER D95'!B9 -> 46121 | C295: ='2019 ALL N OLDER D95'!C9 -> 46127 | D295: 3260 | E295: 333 | F295: 3 | G295: 1 | H295: 81461 | I295: AOS | J295: 28093430 | K295: LEB21-S7 | L295: SS KOKO MUSLIM SHORT SLEEVE 2021 - WHITE LEB21-S7:WHITE:XL:TEXTURE:SS KOKO | M295: 149900 | N295: =$N294 -> 0.85 | O295: =$O294 -> 13485 | P295: =$P294 -> PERCENTAGE
A296: =$A$2 -> 2021 ALL D85 | B296: ='2019 ALL N OLDER D95'!B10 -> 46121 | C296: ='2019 ALL N OLDER D95'!C10 -> 46127 | D296: 3260 | E296: 333 | F296: 3 | G296: 1 | H296: 81461 | I296: AOS | J296: 28093645 | K296: LEB21-S11 | L296: SS KOKO MUSLIM SHORT SLEEVE 2021 - KHAKI LEB21-S11:KHAKI:S:TEXTURE:SS KOKO | M296: 149900 | N296: =$N295 -> 0.85 | O296: =$O295 -> 13485 | P296: =$P295 -> PERCENTAGE
A297: =$A$2 -> 2021 ALL D85 | B297: ='2019 ALL N OLDER D95'!B11 -> 46121 | C297: ='2019 ALL N OLDER D95'!C11 -> 46127 | D297: 3260 | E297: 333 | F297: 3 | G297: 1 | H297: 81461 | I297: AOS | J297: 28093654 | K297: LEB21-S11 | L297: SS KOKO MUSLIM SHORT SLEEVE 2021 - KHAKI LEB21-S11:KHAKI:M:TEXTURE:SS KOKO | M297: 149900 | N297: =$N296 -> 0.85 | O297: =$O296 -> 13485 | P297: =$P296 -> PERCENTAGE
A298: =$A$2 -> 2021 ALL D85 | B298: ='2019 ALL N OLDER D95'!B12 -> 46121 | C298: ='2019 ALL N OLDER D95'!C12 -> 46127 | D298: 3260 | E298: 333 | F298: 3 | G298: 1 | H298: 81461 | I298: AOS | J298: 28093663 | K298: LEB21-S11 | L298: SS KOKO MUSLIM SHORT SLEEVE 2021 - KHAKI LEB21-S11:KHAKI:L:TEXTURE:SS KOKO | M298: 149900 | N298: =$N297 -> 0.85 | O298: =$O297 -> 13485 | P298: =$P297 -> PERCENTAGE
A299: =$A$2 -> 2021 ALL D85 | B299: ='2019 ALL N OLDER D95'!B13 -> 46121 | C299: ='2019 ALL N OLDER D95'!C13 -> 46127 | D299: 3260 | E299: 333 | F299: 3 | G299: 1 | H299: 81461 | I299: AOS | J299: 28093672 | K299: LEB21-S11 | L299: SS KOKO MUSLIM SHORT SLEEVE 2021 - KHAKI LEB21-S11:KHAKI:XL:TEXTURE:SS KOKO | M299: 149900 | N299: =$N298 -> 0.85 | O299: =$O298 -> 13485 | P299: =$P298 -> PERCENTAGE
... A335: =$A$2 -> 2021 ALL D85 | B335: ='2019 ALL N OLDER D95'!B49 -> 46121 | C335: ='2019 ALL N OLDER D95'!C49 -> 46127 | D335: 3260 | E335: 333 | F335: 3 | G335: 2 | H335: 81461 | I335: AOS | J335: 28093190 | K335: LEB21-L1 | L335: LS KOKO MUSLIM LONG SLEEVE 2021 - LEB21-L1 WHITE LEB21-L1:WHITE:XL:SOLID:LS KOKO | M335: 159900 | N335: =$N334 -> 0.85 | O335: =$O334 -> 13485 | P335: =$P334 -> PERCENTAGE
A336: =$A$2 -> 2021 ALL D85 | B336: ='2019 ALL N OLDER D95'!$B$2 -> 46121 | C336: ='2019 ALL N OLDER D95'!$C$2 -> 46127 | D336: 3260 | E336: 333 | F336: 3 | G336: 1 | H336: JAVA DESIGN SENTOSA CV. | I336: AOS | J336: 33436710 | K336: XMAS21TJB | L336: SS T-SHIRT PRINT XMAS COLLECTION 2021 - BLESSED1 XMAS21TJB:BLACK:S:PRINT:SS T-SHIR | M336: 99900 | N336: =$N335 -> 0.85 | O336: =$O335 -> 13485 | P336: =$P335 -> PERCENTAGE
A337: =$A$2 -> 2021 ALL D85 | B337: ='2019 ALL N OLDER D95'!$B$2 -> 46121 | C337: ='2019 ALL N OLDER D95'!$C$2 -> 46127 | D337: 3260 | E337: 333 | F337: 3 | G337: 1 | H337: JAVA DESIGN SENTOSA CV. | I337: AOS | J337: 33436729 | K337: XMAS21TJB | L337: SS T-SHIRT PRINT XMAS COLLECTION 2021 - BLESSED1 XMAS21TJB:BLACK:M:PRINT:SS T-SHIR | M337: 99900 | N337: =$N336 -> 0.85 | O337: =$O336 -> 13485 | P337: =$P336 -> PERCENTAGE
A338: =$A$2 -> 2021 ALL D85 | B338: ='2019 ALL N OLDER D95'!$B$2 -> 46121 | C338: ='2019 ALL N OLDER D95'!$C$2 -> 46127 | D338: 3260 | E338: 333 | F338: 3 | G338: 1 | H338: JAVA DESIGN SENTOSA CV. | I338: AOS | J338: 33436738 | K338: XMAS21TJB | L338: SS T-SHIRT PRINT XMAS COLLECTION 2021 - BLESSED1 XMAS21TJB:BLACK:L:PRINT:SS T-SHIR | M338: 99900 | N338: =$N337 -> 0.85 | O338: =$O337 -> 13485 | P338: =$P337 -> PERCENTAGE
A339: =$A$2 -> 2021 ALL D85 | B339: ='2019 ALL N OLDER D95'!$B$2 -> 46121 | C339: ='2019 ALL N OLDER D95'!$C$2 -> 46127 | D339: 3260 | E339: 333 | F339: 3 | G339: 1 | H339: JAVA DESIGN SENTOSA CV. | I339: AOS | J339: 33436747 | K339: XMAS21TJB | L339: SS T-SHIRT PRINT XMAS COLLECTION 2021 - BLESSED1 XMAS21TJB:BLACK:XL:PRINT:SS T-SHIR | M339: 99900 | N339: =$N338 -> 0.85 | O339: =$O338 -> 13485 | P339: =$P338 -> PERCENTAGE
A340: =$A$2 -> 2021 ALL D85 | B340: ='2019 ALL N OLDER D95'!$B$2 -> 46121 | C340: ='2019 ALL N OLDER D95'!$C$2 -> 46127 | D340: 3260 | E340: 333 | F340: 3 | G340: 1 | H340: JAVA DESIGN SENTOSA CV. | I340: AOS | J340: 33436756 | K340: XMAS21TJB | L340: SS T-SHIRT PRINT XMAS COLLECTION 2021 - BLESSED1 XMAS21TJB:WHITE:S:PRINT:SS T-SHIR | M340: 99900 | N340: =$N339 -> 0.85 | O340: =$O339 -> 13485 | P340: =$P339 -> PERCENTAGE
A341: =$A$2 -> 2021 ALL D85 | B341: ='2019 ALL N OLDER D95'!$B$2 -> 46121 | C341: ='2019 ALL N OLDER D95'!$C$2 -> 46127 | D341: 3260 | E341: 333 | F341: 3 | G341: 1 | H341: JAVA DESIGN SENTOSA CV. | I341: AOS | J341: 33436765 | K341: XMAS21TJB | L341: SS T-SHIRT PRINT XMAS COLLECTION 2021 - BLESSED1 XMAS21TJB:WHITE:M:PRINT:SS T-SHIR | M341: 99900 | N341: =$N340 -> 0.85 | O341: =$O340 -> 13485 | P341: =$P340 -> PERCENTAGE
A342: =$A$2 -> 2021 ALL D85 | B342: ='2019 ALL N OLDER D95'!$B$2 -> 46121 | C342: ='2019 ALL N OLDER D95'!$C$2 -> 46127 | D342: 3260 | E342: 333 | F342: 3 | G342: 1 | H342: JAVA DESIGN SENTOSA CV. | I342: AOS | J342: 33436774 | K342: XMAS21TJB | L342: SS T-SHIRT PRINT XMAS COLLECTION 2021 - BLESSED1 XMAS21TJB:WHITE:L:PRINT:SS T-SHIR | M342: 99900 | N342: =$N341 -> 0.85 | O342: =$O341 -> 13485 | P342: =$P341 -> PERCENTAGE
A343: =$A$2 -> 2021 ALL D85 | B343: ='2019 ALL N OLDER D95'!$B$2 -> 46121 | C343: ='2019 ALL N OLDER D95'!$C$2 -> 46127 | D343: 3260 | E343: 333 | F343: 3 | G343: 1 | H343: JAVA DESIGN SENTOSA CV. | I343: AOS | J343: 33436783 | K343: XMAS21TJB | L343: SS T-SHIRT PRINT XMAS COLLECTION 2021 - BLESSED1 XMAS21TJB:WHITE:XL:PRINT:SS T-SHIR | M343: 99900 | N343: =$N342 -> 0.85 | O343: =$O342 -> 13485 | P343: =$P342 -> PERCENTAGE
A344: =$A$2 -> 2021 ALL D85 | B344: ='2019 ALL N OLDER D95'!$B$2 -> 46121 | C344: ='2019 ALL N OLDER D95'!$C$2 -> 46127 | D344: 3260 | E344: 333 | F344: 3 | G344: 1 | H344: JAVA DESIGN SENTOSA CV. | I344: AOS | J344: 33436792 | K344: XMAS21TJF | L344: SS T-SHIRT PRINT XMAS COLLECTION 2021 - FULLPRINT1 X:MISTY LIGHT:S:PRINT:SS T-SHIRT | M344: 99900 | N344: =$N343 -> 0.85 | O344: =$O343 -> 13485 | P344: =$P343 -> PERCENTAGE
A345: =$A$2 -> 2021 ALL D85 | B345: ='2019 ALL N OLDER D95'!$B$2 -> 46121 | C345: ='2019 ALL N OLDER D95'!$C$2 -> 46127 | D345: 3260 | E345: 333 | F345: 3 | G345: 1 | H345: JAVA DESIGN SENTOSA CV. | I345: AOS | J345: 33436809 | K345: XMAS21TJF | L345: SS T-SHIRT PRINT XMAS COLLECTION 2021 - FULLPRINT1 X:MISTY LIGHT:M:PRINT:SS T-SHIRT | M345: 99900 | N345: =$N344 -> 0.85 | O345: =$O344 -> 13485 | P345: =$P344 -> PERCENTAGE
A346: =$A$2 -> 2021 ALL D85 | B346: ='2019 ALL N OLDER D95'!$B$2 -> 46121 | C346: ='2019 ALL N OLDER D95'!$C$2 -> 46127 | D346: 3260 | E346: 333 | F346: 3 | G346: 1 | H346: JAVA DESIGN SENTOSA CV. | I346: AOS | J346: 33436818 | K346: XMAS21TJF | L346: SS T-SHIRT PRINT XMAS COLLECTION 2021 - FULLPRINT1 X:MISTY LIGHT:L:PRINT:SS T-SHIRT | M346: 99900 | N346: =$N345 -> 0.85 | O346: =$O345 -> 13485 | P346: =$P345 -> PERCENTAGE
A347: =$A$2 -> 2021 ALL D85 | B347: ='2019 ALL N OLDER D95'!$B$2 -> 46121 | C347: ='2019 ALL N OLDER D95'!$C$2 -> 46127 | D347: 3260 | E347: 333 | F347: 3 | G347: 1 | H347: JAVA DESIGN SENTOSA CV. | I347: AOS | J347: 33436827 | K347: XMAS21TJF | L347: SS T-SHIRT PRINT XMAS COLLECTION 2021 - FULLPRINT1 X:MISTY LIGHT:XL:PRINT:SS T-SHIRT | M347: 99900 | N347: =$N346 -> 0.85 | O347: =$O346 -> 13485 | P347: =$P346 -> PERCENTAGE
... A420: =$A$2 -> 2021 ALL D85 | B420: ='2019 ALL N OLDER D95'!$B$2 -> 46121 | C420: ='2019 ALL N OLDER D95'!$C$2 -> 46127 | D420: 3260 | E420: 333 | F420: 3 | G420: 4 | H420: JAVA DESIGN SENTOSA CV. | I420: AOS | J420: 33262461 | K420: WBTSS5 | L420: SS T-SHIRT WB SUICIDE SQUAD - THE SUICIDE SQUAD PHOT:WHITE:XL:GRAPHIC:SS T-SHIRT | M420: 119900 | N420: =$N419 -> 0.85 | O420: =$O419 -> 13485 | P420: =$P419 -> PERCENTAGE
A421: =$A$2 -> 2021 ALL D85 | B421: ='2019 ALL N OLDER D95'!$B$2 -> 46121 | C421: ='2019 ALL N OLDER D95'!$C$2 -> 46127 | D421: 3260 | E421: 333 | F421: 3 | G421: 3 | H421: JAVA DESIGN SENTOSA | I421: AOS | J421: 26366041 | K421: RSB551 | L421: RAGLAN SHORT BASIC RSBM551 M551/3TONE MAROON 02-20:MISTY LIGHT RE:S | M421: 89900 | N421: =$N420 -> 0.85 | O421: =$O420 -> 13485 | P421: =$P420 -> PERCENTAGE
A422: =$A$2 -> 2021 ALL D85 | B422: ='2019 ALL N OLDER D95'!$B$2 -> 46121 | C422: ='2019 ALL N OLDER D95'!$C$2 -> 46127 | D422: 3260 | E422: 333 | F422: 3 | G422: 3 | H422: JAVA DESIGN SENTOSA | I422: AOS | J422: 26366050 | K422: RSB551 | L422: RAGLAN SHORT BASIC RSBM551 M551/3TONE MAROON 02-20:MISTY LIGHT RE:M | M422: 89900 | N422: =$N421 -> 0.85 | O422: =$O421 -> 13485 | P422: =$P421 -> PERCENTAGE
A423: =$A$2 -> 2021 ALL D85 | B423: ='2019 ALL N OLDER D95'!$B$2 -> 46121 | C423: ='2019 ALL N OLDER D95'!$C$2 -> 46127 | D423: 3260 | E423: 333 | F423: 3 | G423: 3 | H423: JAVA DESIGN SENTOSA | I423: AOS | J423: 26366069 | K423: RSB551 | L423: RAGLAN SHORT BASIC RSBM551 M551/3TONE MAROON 02-20:MISTY LIGHT RE:L | M423: 89900 | N423: =$N422 -> 0.85 | O423: =$O422 -> 13485 | P423: =$P422 -> PERCENTAGE
A424: =$A$2 -> 2021 ALL D85 | B424: ='2019 ALL N OLDER D95'!$B$2 -> 46121 | C424: ='2019 ALL N OLDER D95'!$C$2 -> 46127 | D424: 3260 | E424: 333 | F424: 3 | G424: 3 | H424: JAVA DESIGN SENTOSA | I424: AOS | J424: 26366078 | K424: RSB551 | L424: RAGLAN SHORT BASIC RSBM551 M551/3TONE MAROON 02-20:MISTY LIGHT RE:XL | M424: 89900 | N424: =$N423 -> 0.85 | O424: =$O423 -> 13485 | P424: =$P423 -> PERCENTAGE
A425: =$A$2 -> 2021 ALL D85 | B425: ='2019 ALL N OLDER D95'!$B$2 -> 46121 | C425: ='2019 ALL N OLDER D95'!$C$2 -> 46127 | D425: 3260 | E425: 333 | F425: 3 | G425: 3 | H425: JAVA DESIGN SENTOSA | I425: AOS | J425: 26367540 | K425: RSBM41 | L425: RAGLAN SHORT BASIC RSBM41 M41/3TONE BLUE 01-20:MISTY MEDIUM B:S | M425: 89900 | N425: =$N424 -> 0.85 | O425: =$O424 -> 13485 | P425: =$P424 -> PERCENTAGE
A426: =$A$2 -> 2021 ALL D85 | B426: ='2019 ALL N OLDER D95'!$B$2 -> 46121 | C426: ='2019 ALL N OLDER D95'!$C$2 -> 46127 | D426: 3260 | E426: 333 | F426: 3 | G426: 3 | H426: JAVA DESIGN SENTOSA | I426: AOS | J426: 26367559 | K426: RSBM41 | L426: RAGLAN SHORT BASIC RSBM41 M41/3TONE BLUE 01-20:MISTY MEDIUM B:M | M426: 89900 | N426: =$N425 -> 0.85 | O426: =$O425 -> 13485 | P426: =$P425 -> PERCENTAGE
A427: =$A$2 -> 2021 ALL D85 | B427: ='2019 ALL N OLDER D95'!$B$2 -> 46121 | C427: ='2019 ALL N OLDER D95'!$C$2 -> 46127 | D427: 3260 | E427: 333 | F427: 3 | G427: 3 | H427: JAVA DESIGN SENTOSA | I427: AOS | J427: 26367568 | K427: RSBM41 | L427: RAGLAN SHORT BASIC RSBM41 M41/3TONE BLUE 01-20:MISTY MEDIUM B:L | M427: 89900 | N427: =$N426 -> 0.85 | O427: =$O426 -> 13485 | P427: =$P426 -> PERCENTAGE
A428: =$A$2 -> 2021 ALL D85 | B428: ='2019 ALL N OLDER D95'!$B$2 -> 46121 | C428: ='2019 ALL N OLDER D95'!$C$2 -> 46127 | D428: 3260 | E428: 333 | F428: 3 | G428: 3 | H428: JAVA DESIGN SENTOSA | I428: AOS | J428: 26367577 | K428: RSBM41 | L428: RAGLAN SHORT BASIC RSBM41 M41/3TONE BLUE 01-20:MISTY MEDIUM B:XL | M428: 89900 | N428: =$N427 -> 0.85 | O428: =$O427 -> 13485 | P428: =$P427 -> PERCENTAGE
A429: =$A$2 -> 2021 ALL D85 | B429: ='2019 ALL N OLDER D95'!$B$2 -> 46121 | C429: ='2019 ALL N OLDER D95'!$C$2 -> 46127 | D429: 3260 | E429: 333 | F429: 3 | G429: 1 | H429: SAHABAT GARMINDO PT- | I429: AOS | J429: 26703837 | K429: HDLS4-C | L429: LS T-SHIRT HOODIE TEXT NOTHING CHANGES CEST LA VIE HDLS4-C:BLACK:S:TEXT:LS T-SHIR | M429: 129900 | N429: =$N428 -> 0.85 | O429: =$O428 -> 13485 | P429: =$P428 -> PERCENTAGE
A430: =$A$2 -> 2021 ALL D85 | B430: ='2019 ALL N OLDER D95'!$B$2 -> 46121 | C430: ='2019 ALL N OLDER D95'!$C$2 -> 46127 | D430: 3260 | E430: 333 | F430: 3 | G430: 1 | H430: SAHABAT GARMINDO PT- | I430: AOS | J430: 26703846 | K430: HDLS4-C | L430: LS T-SHIRT HOODIE TEXT NOTHING CHANGES CEST LA VIE HDLS4-C:BLACK:M:TEXT:LS T-SHIR | M430: 129900 | N430: =$N429 -> 0.85 | O430: =$O429 -> 13485 | P430: =$P429 -> PERCENTAGE
A431: =$A$2 -> 2021 ALL D85 | B431: ='2019 ALL N OLDER D95'!$B$2 -> 46121 | C431: ='2019 ALL N OLDER D95'!$C$2 -> 46127 | D431: 3260 | E431: 333 | F431: 3 | G431: 1 | H431: SAHABAT GARMINDO PT- | I431: AOS | J431: 26703855 | K431: HDLS4-C | L431: LS T-SHIRT HOODIE TEXT NOTHING CHANGES CEST LA VIE HDLS4-C:BLACK:L:TEXT:LS T-SHIR | M431: 129900 | N431: =$N430 -> 0.85 | O431: =$O430 -> 13485 | P431: =$P430 -> PERCENTAGE
A432: =$A$2 -> 2021 ALL D85 | B432: ='2019 ALL N OLDER D95'!$B$2 -> 46121 | C432: ='2019 ALL N OLDER D95'!$C$2 -> 46127 | D432: 3260 | E432: 333 | F432: 3 | G432: 1 | H432: SAHABAT GARMINDO PT- | I432: AOS | J432: 26703864 | K432: HDLS4-C | L432: LS T-SHIRT HOODIE TEXT NOTHING CHANGES CEST LA VIE HDLS4-C:BLACK:XL:TEXT:LS T-SHIR | M432: 129900 | N432: =$N431 -> 0.85 | O432: =$O431 -> 13485 | P432: =$P431 -> PERCENTAGE
... A2430: =$A$2 -> 2021 ALL D85 | B2430: ='2019 ALL N OLDER D95'!$B$2 -> 46121 | C2430: ='2019 ALL N OLDER D95'!$C$2 -> 46127 | D2430: 3260 | E2430: 333 | F2430: 3 | G2430: 1 | H2430: JAVA DESIGN SENTOSA CV. | I2430: AOS | J2430: 46418493 | K2430: TJ9-OSIN | L2430: SS T-SHIRT PRINT OUTER SPACE AOP - I NEED MORE SPACE:WHITE:XL:TEXT:SS T-SHIRT | M2430: 99900 | N2430: =$N2429 -> 0.85 | O2430: =$O2429 -> 13485 | P2430: =$P2429 -> PERCENTAGE

Sheet 2022 ALL D85
A1: ACARA | B1: FROM DATE | C1: TO DATE | D1: DEPT | E1: WORLD | F1: DIVISION | G1: CLASS | H1: SUPPLIER | I1: BRAND | J1: SKU | K1: ARTICLE | L1: DESCRIPTION | M1: HARGA NORMAL | N1: DISKON | O1: HARGA PROMO | P1: DISCOUNT TYPE
A2: 2022 ALL D85 | B2: ='2019 ALL N OLDER D95'!$B$2 -> 46121 | C2: ='2019 ALL N OLDER D95'!$C$2 -> 46127 | D2: 3260 | E2: 333 | F2: 3 | G2: 1 | H2: FECEKRAN SANDANG JAYA PT.-81235 | I2: AOS | J2: 73433353 | K2: TFUF5-AB | L2: SS T-SHIRT FULLPRINT AOP THEME SUMMERTIME- LEAF TFUF5-AB:DUSTY PIN:XL:PRINT:SS T-SHIR | M2: 119900 | N2: 0.85 | O2: =M2*(1-N2) -> 17985 | P2: PERCENTAGE
A3: =$A$2 -> 2022 ALL D85 | B3: ='2019 ALL N OLDER D95'!$B$2 -> 46121 | C3: ='2019 ALL N OLDER D95'!$C$2 -> 46127 | D3: 3260 | E3: 333 | F3: 3 | G3: 1 | H3: FECEKRAN SANDANG JAYA PT.-81235 | I3: AOS | J3: 73433344 | K3: TFUF5-AB | L3: SS T-SHIRT FULLPRINT AOP THEME SUMMERTIME- LEAF TFUF5-AB:DUSTY PIN:L:PRINT:SS T-SHIR | M3: 119900 | N3: =$N$2 -> 0.85 | O3: =$O2 -> 17985 | P3: =$P$2 -> PERCENTAGE
A4: =$A$2 -> 2022 ALL D85 | B4: ='2019 ALL N OLDER D95'!$B$2 -> 46121 | C4: ='2019 ALL N OLDER D95'!$C$2 -> 46127 | D4: 3260 | E4: 333 | F4: 3 | G4: 1 | H4: FECEKRAN SANDANG JAYA PT.-81235 | I4: AOS | J4: 73433335 | K4: TFUF5-AB | L4: SS T-SHIRT FULLPRINT AOP THEME SUMMERTIME- LEAF TFUF5-AB:DUSTY PIN:M:PRINT:SS T-SHIR | M4: 119900 | N4: =$N$2 -> 0.85 | O4: =$O3 -> 17985 | P4: =$P$2 -> PERCENTAGE
A5: =$A$2 -> 2022 ALL D85 | B5: ='2019 ALL N OLDER D95'!$B$2 -> 46121 | C5: ='2019 ALL N OLDER D95'!$C$2 -> 46127 | D5: 3260 | E5: 333 | F5: 3 | G5: 1 | H5: FECEKRAN SANDANG JAYA PT.-81235 | I5: AOS | J5: 73433326 | K5: TFUF5-AB | L5: SS T-SHIRT FULLPRINT AOP THEME SUMMERTIME- LEAF TFUF5-AB:DUSTY PIN:S:PRINT:SS T-SHIR | M5: 119900 | N5: =$N$2 -> 0.85 | O5: =$O4 -> 17985 | P5: =$P$2 -> PERCENTAGE
A6: =$A$2 -> 2022 ALL D85 | B6: ='2019 ALL N OLDER D95'!$B$2 -> 46121 | C6: ='2019 ALL N OLDER D95'!$C$2 -> 46127 | D6: 3260 | E6: 333 | F6: 3 | G6: 1 | H6: FECEKRAN SANDANG JAYA PT.-81235 | I6: AOS | J6: 73433317 | K6: TFUF5-AB | L6: SS T-SHIRT FULLPRINT AOP THEME SUMMERTIME- LEAF TFUF5-AB:MUSTARD:XL:PRINT:SS T-SHIR | M6: 119900 | N6: =$N$2 -> 0.85 | O6: =$O5 -> 17985 | P6: =$P$2 -> PERCENTAGE
A7: =$A$2 -> 2022 ALL D85 | B7: ='2019 ALL N OLDER D95'!$B$2 -> 46121 | C7: ='2019 ALL N OLDER D95'!$C$2 -> 46127 | D7: 3260 | E7: 333 | F7: 3 | G7: 1 | H7: FECEKRAN SANDANG JAYA PT.-81235 | I7: AOS | J7: 73433308 | K7: TFUF5-AB | L7: SS T-SHIRT FULLPRINT AOP THEME SUMMERTIME- LEAF TFUF5-AB:MUSTARD:L:PRINT:SS T-SHIR | M7: 119900 | N7: =$N$2 -> 0.85 | O7: =$O6 -> 17985 | P7: =$P$2 -> PERCENTAGE
A8: =$A$2 -> 2022 ALL D85 | B8: ='2019 ALL N OLDER D95'!$B$2 -> 46121 | C8: ='2019 ALL N OLDER D95'!$C$2 -> 46127 | D8: 3260 | E8: 333 | F8: 3 | G8: 1 | H8: FECEKRAN SANDANG JAYA PT.-81235 | I8: AOS | J8: 73433291 | K8: TFUF5-AB | L8: SS T-SHIRT FULLPRINT AOP THEME SUMMERTIME- LEAF TFUF5-AB:MUSTARD:M:PRINT:SS T-SHIR | M8: 119900 | N8: =$N$2 -> 0.85 | O8: =$O7 -> 17985 | P8: =$P$2 -> PERCENTAGE
A9: =$A$2 -> 2022 ALL D85 | B9: ='2019 ALL N OLDER D95'!$B$2 -> 46121 | C9: ='2019 ALL N OLDER D95'!$C$2 -> 46127 | D9: 3260 | E9: 333 | F9: 3 | G9: 1 | H9: FECEKRAN SANDANG JAYA PT.-81235 | I9: AOS | J9: 73433282 | K9: TFUF5-AB | L9: SS T-SHIRT FULLPRINT AOP THEME SUMMERTIME- LEAF TFUF5-AB:MUSTARD:S:PRINT:SS T-SHIR | M9: 119900 | N9: =$N$2 -> 0.85 | O9: =$O8 -> 17985 | P9: =$P$2 -> PERCENTAGE
A10: =$A$2 -> 2022 ALL D85 | B10: ='2019 ALL N OLDER D95'!$B$2 -> 46121 | C10: ='2019 ALL N OLDER D95'!$C$2 -> 46127 | D10: 3260 | E10: 333 | F10: 3 | G10: 4 | H10: JAVA DESIGN SENTOSA CV. | I10: AOS | J10: 71529254 | K10: WBTF5-4 | L10: SS T-SHIRT WB FRIENDS - 4 WBTF5-4:WHITE:XL:GRAPHIC:SS T-SHIRT | M10: 129900 | N10: =$N$2 -> 0.85 | O10: =$O9 -> 17985 | P10: =$P$2 -> PERCENTAGE
A11: =$A$2 -> 2022 ALL D85 | B11: ='2019 ALL N OLDER D95'!$B$2 -> 46121 | C11: ='2019 ALL N OLDER D95'!$C$2 -> 46127 | D11: 3260 | E11: 333 | F11: 3 | G11: 4 | H11: JAVA DESIGN SENTOSA CV. | I11: AOS | J11: 71529245 | K11: WBTF5-4 | L11: SS T-SHIRT WB FRIENDS - 4 WBTF5-4:WHITE:L:GRAPHIC:SS T-SHIRT | M11: 129900 | N11: =$N$2 -> 0.85 | O11: =$O10 -> 17985 | P11: =$P$2 -> PERCENTAGE
A12: =$A$2 -> 2022 ALL D85 | B12: ='2019 ALL N OLDER D95'!$B$2 -> 46121 | C12: ='2019 ALL N OLDER D95'!$C$2 -> 46127 | D12: 3260 | E12: 333 | F12: 3 | G12: 4 | H12: JAVA DESIGN SENTOSA CV. | I12: AOS | J12: 71529236 | K12: WBTF5-4 | L12: SS T-SHIRT WB FRIENDS - 4 WBTF5-4:WHITE:M:GRAPHIC:SS T-SHIRT | M12: 129900 | N12: =$N$2 -> 0.85 | O12: =$O11 -> 17985 | P12: =$P$2 -> PERCENTAGE
A13: =$A$2 -> 2022 ALL D85 | B13: ='2019 ALL N OLDER D95'!$B$2 -> 46121 | C13: ='2019 ALL N OLDER D95'!$C$2 -> 46127 | D13: 3260 | E13: 333 | F13: 3 | G13: 4 | H13: JAVA DESIGN SENTOSA CV. | I13: AOS | J13: 71529227 | K13: WBTF5-4 | L13: SS T-SHIRT WB FRIENDS - 4 WBTF5-4:WHITE:S:GRAPHIC:SS T-SHIRT | M13: 129900 | N13: =$N$2 -> 0.85 | O13: =$O12 -> 17985 | P13: =$P$2 -> PERCENTAGE
A14: =$A$2 -> 2022 ALL D85 | B14: ='2019 ALL N OLDER D95'!$B$2 -> 46121 | C14: ='2019 ALL N OLDER D95'!$C$2 -> 46127 | D14: 3260 | E14: 333 | F14: 3 | G14: 4 | H14: JAVA DESIGN SENTOSA CV. | I14: AOS | J14: 71529218 | K14: WBTF5-3 | L14: SS T-SHIRT WB FRIENDS - 3 WBTF5-3:MUSTARD:XL:GRAPHIC:SS T-SHIRT | M14: 129900 | N14: =$N$2 -> 0.85 | O14: =$O13 -> 17985 | P14: =$P$2 -> PERCENTAGE
... A1131: =$A$2 -> 2022 ALL D85 | B1131: ='2019 ALL N OLDER D95'!$B$2 -> 46121 | C1131: ='2019 ALL N OLDER D95'!$C$2 -> 46127 | D1131: 3260 | E1131: 333 | F1131: 3 | G1131: 2 | H1131: JAVA DESIGN SENTOSA CV. | I1131: AOS | J1131: 32977432 | K1131: LSJ9-WIND | L1131: LS T-SHIRT PRINT - THE WIND IS CALLING LSJ9-WIND:CHARCOAL:S:TEXT:LS T-SHIRT | M1131: 109900 | N1131: =$N$2 -> 0.85 | O1131: =$O1130 -> 17985 | P1131: =$P$2 -> PERCENTAGE
A1132: =$A$2 -> 2022 ALL D85 | B1132: ='2019 ALL N OLDER D95'!$B$2 -> 46121 | C1132: ='2019 ALL N OLDER D95'!$C$2 -> 46127 | D1132: 3260 | E1132: 333 | F1132: 3 | G1132: 1 | H1132: SAHABAT GARMINDO PT- 81461 | I1132: AOS | J1132: 67146827 | K1132: OSFS3-C3 | L1132: SS T-SHIRT OVERSIZE PHOTOPRINT CITY - BOSTON OSFS3-C3:NAVY BLUE:L:GRAPHIC:SS T-SHIRT | M1132: 129900 | N1132: =$N$2 -> 0.85 | O1132: =$O1131 -> 17985 | P1132: =$P$2 -> PERCENTAGE
A1133: =$A$2 -> 2022 ALL D85 | B1133: ='2019 ALL N OLDER D95'!$B$2 -> 46121 | C1133: ='2019 ALL N OLDER D95'!$C$2 -> 46127 | D1133: 3260 | E1133: 333 | F1133: 3 | G1133: 1 | H1133: SAHABAT GARMINDO PT- 81461 | I1133: AOS | J1133: 67146783 | K1133: OSFS3-C1 | L1133: SS T-SHIRT OVERSIZE PHOTOPRINT CITY - URBAN CITY OSFS3-C1:BLACK:L:GRAPHIC:SS T-SHIRT | M1133: 129900 | N1133: =$N$2 -> 0.85 | O1133: =$O1132 -> 17985 | P1133: =$P$2 -> PERCENTAGE
A1134: =$A$2 -> 2022 ALL D85 | B1134: ='2019 ALL N OLDER D95'!$B$2 -> 46121 | C1134: ='2019 ALL N OLDER D95'!$C$2 -> 46127 | D1134: 3260 | E1134: 333 | F1134: 3 | G1134: 1 | H1134: SAHABAT GARMINDO PT- 81461 | I1134: AOS | J1134: 67146747 | K1134: OSFS3-C2 | L1134: SS T-SHIRT OVERSIZE PHOTOPRINT CITY - NYC CITY OSFS3-C2:WHITE:L:GRAPHIC:SS T-SHIRT | M1134: 129900 | N1134: =$N$2 -> 0.85 | O1134: =$O1133 -> 17985 | P1134: =$P$2 -> PERCENTAGE
A1135: =$A$2 -> 2022 ALL D85 | B1135: ='2019 ALL N OLDER D95'!$B$2 -> 46121 | C1135: ='2019 ALL N OLDER D95'!$C$2 -> 46127 | D1135: 3260 | E1135: 333 | F1135: 3 | G1135: 1 | H1135: PUTRA JAYA KREASI PT- 81602 | I1135: AOS | J1135: 66073103 | K1135: TK2N-96 | L1135: SS TSHIRT PRINT THEME NUMBER - AUTHENTIC 1996:OLIVE:L:TEXT:SS T-SHIRT | M1135: 119900 | N1135: =$N$2 -> 0.85 | O1135: =$O1134 -> 17985 | P1135: =$P$2 -> PERCENTAGE
A1136: =$A$2 -> 2022 ALL D85 | B1136: ='2019 ALL N OLDER D95'!$B$2 -> 46121 | C1136: ='2019 ALL N OLDER D95'!$C$2 -> 46127 | D1136: 3260 | E1136: 333 | F1136: 3 | G1136: 1 | H1136: PUTRA JAYA KREASI PT- 81602 | I1136: AOS | J1136: 66072864 | K1136: TK2N-86 | L1136: SS TSHIRT PRINT THEME NUMBER - 86 TYRANNOSAURUS:KHAKI:L:TEXT:SS T-SHIRT | M1136: 119900 | N1136: =$N$2 -> 0.85 | O1136: =$O1135 -> 17985 | P1136: =$P$2 -> PERCENTAGE
A1137: =$A$2 -> 2022 ALL D85 | B1137: ='2019 ALL N OLDER D95'!$B$2 -> 46121 | C1137: ='2019 ALL N OLDER D95'!$C$2 -> 46127 | D1137: 3260 | E1137: 333 | F1137: 3 | G1137: 1 | H1137: PUTRA JAYA KREASI PT- 81602 | I1137: AOS | J1137: 66072104 | K1137: TK2N-U8 | L1137: SS TSHIRT PRINT THEME - 8 URBAN TK2N-U8:MISTY LIGHT BL:L:TEXT:SS T-SHIRT | M1137: 119900 | N1137: =$N$2 -> 0.85 | O1137: =$O1136 -> 17985 | P1137: =$P$2 -> PERCENTAGE
A1138: =$A$2 -> 2022 ALL D85 | B1138: ='2019 ALL N OLDER D95'!$B$2 -> 46121 | C1138: ='2019 ALL N OLDER D95'!$C$2 -> 46127 | D1138: 3260 | E1138: 333 | F1138: 3 | G1138: 1 | H1138: PUTRA JAYA KREASI PT- 81602 | I1138: AOS | J1138: 66071249 | K1138: TK2N-99 | L1138: SS TSHIRT PRINT THEME NUMBER - 99 IGNORANCE:WHITE:L:TEXT:SS T-SHIRT | M1138: 119900 | N1138: =$N$2 -> 0.85 | O1138: =$O1137 -> 17985 | P1138: =$P$2 -> PERCENTAGE
A1139: =$A$2 -> 2022 ALL D85 | B1139: ='2019 ALL N OLDER D95'!$B$2 -> 46121 | C1139: ='2019 ALL N OLDER D95'!$C$2 -> 46127 | D1139: 3260 | E1139: 333 | F1139: 3 | G1139: 1 | H1139: PUTRA JAYA KREASI PT- 81602 | I1139: AOS | J1139: 66066997 | K1139: TK2N-L8 | L1139: SS TSHIRT PRINT THEME NUMBER - LUCKY EIGHT (8) TK2N-L8:BLACK:L:TEXT:SS T-SHIRT | M1139: 119900 | N1139: =$N$2 -> 0.85 | O1139: =$O1138 -> 17985 | P1139: =$P$2 -> PERCENTAGE
A1140: =$A$2 -> 2022 ALL D85 | B1140: ='2019 ALL N OLDER D95'!$B$2 -> 46121 | C1140: ='2019 ALL N OLDER D95'!$C$2 -> 46127 | D1140: 3260 | E1140: 333 | F1140: 3 | G1140: 1 | H1140: TRIKENCANA PUTRA GARMINDO CV-813 | I1140: AOS | J1140: 66065309 | K1140: TT2JS-JN | L1140: SS TSHIRT PRINT JAPAN STORY-JAPANESE NINJAKEN TT2JS-JN:BLACK:L:TEXT:SS T-SHIRT | M1140: 119900 | N1140: =$N$2 -> 0.85 | O1140: =$O1139 -> 17985 | P1140: =$P$2 -> PERCENTAGE
A1141: =$A$2 -> 2022 ALL D85 | B1141: ='2019 ALL N OLDER D95'!$B$2 -> 46121 | C1141: ='2019 ALL N OLDER D95'!$C$2 -> 46127 | D1141: 3260 | E1141: 333 | F1141: 3 | G1141: 1 | H1141: TRIKENCANA PUTRA GARMINDO CV-813 | I1141: AOS | J1141: 66040004 | K1141: TT2JS-TE | L1141: SS TSHIRT PRINT JAPAN STORY - TEMPLE 1 TT2JS-TE:KHAKI:L:GRAPHIC:SS T-SHIRT | M1141: 119900 | N1141: =$N$2 -> 0.85 | O1141: =$O1140 -> 17985 | P1141: =$P$2 -> PERCENTAGE
A1142: =$A$2 -> 2022 ALL D85 | B1142: ='2019 ALL N OLDER D95'!$B$2 -> 46121 | C1142: ='2019 ALL N OLDER D95'!$C$2 -> 46127 | D1142: 3260 | E1142: 333 | F1142: 3 | G1142: 1 | H1142: TRIKENCANA PUTRA GARMINDO CV-813 | I1142: AOS | J1142: 66039963 | K1142: TT2JS-TE | L1142: SS TSHIRT PRINT JAPAN STORY - TEMPLE 1 TT2JS-TE:CHARCOAL:L:GRAPHIC:SS T-SHIRT | M1142: 119900 | N1142: =$N$2 -> 0.85 | O1142: =$O1141 -> 17985 | P1142: =$P$2 -> PERCENTAGE
A1143: =$A$2 -> 2022 ALL D85 | B1143: ='2019 ALL N OLDER D95'!$B$2 -> 46121 | C1143: ='2019 ALL N OLDER D95'!$C$2 -> 46127 | D1143: 3260 | E1143: 333 | F1143: 3 | G1143: 1 | H1143: PUTRA JAYA KREASI PT- 81602 | I1143: AOS | J1143: 66038464 | K1143: TK2N-88 | L1143: PRINT THEME NUMBER - 88 TK2N-88:MISTY MEDIUM GRE:L:TEXT:SS T-SHIRT | M1143: 119900 | N1143: =$N$2 -> 0.85 | O1143: =$O1142 -> 17985 | P1143: =$P$2 -> PERCENTAGE
... A1159: =$A$2 -> 2022 ALL D85 | B1159: ='2019 ALL N OLDER D95'!$B$2 -> 46121 | C1159: ='2019 ALL N OLDER D95'!$C$2 -> 46127 | D1159: 3260 | E1159: 333 | F1159: 3 | G1159: 1 | H1159: INTAN DUA PT- 81337 | I1159: AOS | J1159: 65609376 | K1159: TI2IL-CR | L1159: SS T-SHIRT PRINT IMAGINERY LETTER - CIRCLE TI2IL-CR:WHITE:L:GRAPHIC:SS T-SHIRT | M1159: 119900 | N1159: =$N$2 -> 0.85 | O1159: =$O1158 -> 17985 | P1159: =$P$2 -> PERCENTAGE
A1160: =$A$2 -> 2022 ALL D85 | B1160: ='2019 ALL N OLDER D95'!$B$2 -> 46121 | C1160: ='2019 ALL N OLDER D95'!$C$2 -> 46127 | D1160: 3260 | E1160: 333 | F1160: 3 | G1160: 4 | H1160: JAVA DESIGN SENTOSA CV. | I1160: AOS | J1160: 66038606 | K1160: WBTB2-6 | L1160: SS T-SHIRT WB BATMAN MOVIE - 6 WBTB2-6:MISTY MEDIUM Y:XL:GRAPHIC:SS T-SHIRT | M1160: 129900 | N1160: =$N$2 -> 0.85 | O1160: =$O1159 -> 17985 | P1160: =$P$2 -> PERCENTAGE
A1161: =$A$2 -> 2022 ALL D85 | B1161: ='2019 ALL N OLDER D95'!$B$2 -> 46121 | C1161: ='2019 ALL N OLDER D95'!$C$2 -> 46127 | D1161: 3260 | E1161: 333 | F1161: 3 | G1161: 4 | H1161: JAVA DESIGN SENTOSA CV. | I1161: AOS | J1161: 66038599 | K1161: WBTB2-6 | L1161: SS T-SHIRT WB BATMAN MOVIE - 6 WBTB2-6:MISTY MEDIUM Y:L:GRAPHIC:SS T-SHIRT | M1161: 129900 | N1161: =$N$2 -> 0.85 | O1161: =$O1160 -> 17985 | P1161: =$P$2 -> PERCENTAGE
A1162: =$A$2 -> 2022 ALL D85 | B1162: ='2019 ALL N OLDER D95'!$B$2 -> 46121 | C1162: ='2019 ALL N OLDER D95'!$C$2 -> 46127 | D1162: 3260 | E1162: 333 | F1162: 3 | G1162: 4 | H1162: JAVA DESIGN SENTOSA CV. | I1162: AOS | J1162: 66038580 | K1162: WBTB2-6 | L1162: SS T-SHIRT WB BATMAN MOVIE - 6 WBTB2-6:MISTY MEDIUM Y:M:GRAPHIC:SS T-SHIRT | M1162: 129900 | N1162: =$N$2 -> 0.85 | O1162: =$O1161 -> 17985 | P1162: =$P$2 -> PERCENTAGE
A1163: =$A$2 -> 2022 ALL D85 | B1163: ='2019 ALL N OLDER D95'!$B$2 -> 46121 | C1163: ='2019 ALL N OLDER D95'!$C$2 -> 46127 | D1163: 3260 | E1163: 333 | F1163: 3 | G1163: 4 | H1163: JAVA DESIGN SENTOSA CV. | I1163: AOS | J1163: 66038571 | K1163: WBTB2-6 | L1163: SS T-SHIRT WB BATMAN MOVIE - 6 WBTB2-6:MISTY MEDIUM Y:S:GRAPHIC:SS T-SHIRT | M1163: 129900 | N1163: =$N$2 -> 0.85 | O1163: =$O1162 -> 17985 | P1163: =$P$2 -> PERCENTAGE
A1164: =$A$2 -> 2022 ALL D85 | B1164: ='2019 ALL N OLDER D95'!$B$2 -> 46121 | C1164: ='2019 ALL N OLDER D95'!$C$2 -> 46127 | D1164: 3260 | E1164: 333 | F1164: 3 | G1164: 4 | H1164: JAVA DESIGN SENTOSA CV. | I1164: AOS | J1164: 66038562 | K1164: WBTB2-5 | L1164: SS T-SHIRT WB BATMAN MOVIE - 5 WBTB2-5:NAVY BLUE:XL:GRAPHIC:SS T-SHIRT | M1164: 129900 | N1164: =$N$2 -> 0.85 | O1164: =$O1163 -> 17985 | P1164: =$P$2 -> PERCENTAGE
A1165: =$A$2 -> 2022 ALL D85 | B1165: ='2019 ALL N OLDER D95'!$B$2 -> 46121 | C1165: ='2019 ALL N OLDER D95'!$C$2 -> 46127 | D1165: 3260 | E1165: 333 | F1165: 3 | G1165: 4 | H1165: JAVA DESIGN SENTOSA CV. | I1165: AOS | J1165: 66038553 | K1165: WBTB2-5 | L1165: SS T-SHIRT WB BATMAN MOVIE - 5 WBTB2-5:NAVY BLUE:L:GRAPHIC:SS T-SHIRT | M1165: 129900 | N1165: =$N$2 -> 0.85 | O1165: =$O1164 -> 17985 | P1165: =$P$2 -> PERCENTAGE
A1166: =$A$2 -> 2022 ALL D85 | B1166: ='2019 ALL N OLDER D95'!$B$2 -> 46121 | C1166: ='2019 ALL N OLDER D95'!$C$2 -> 46127 | D1166: 3260 | E1166: 333 | F1166: 3 | G1166: 4 | H1166: JAVA DESIGN SENTOSA CV. | I1166: AOS | J1166: 66038544 | K1166: WBTB2-5 | L1166: SS T-SHIRT WB BATMAN MOVIE - 5 WBTB2-5:NAVY BLUE:M:GRAPHIC:SS T-SHIRT | M1166: 129900 | N1166: =$N$2 -> 0.85 | O1166: =$O1165 -> 17985 | P1166: =$P$2 -> PERCENTAGE
A1167: =$A$2 -> 2022 ALL D85 | B1167: ='2019 ALL N OLDER D95'!$B$2 -> 46121 | C1167: ='2019 ALL N OLDER D95'!$C$2 -> 46127 | D1167: 3260 | E1167: 333 | F1167: 3 | G1167: 4 | H1167: JAVA DESIGN SENTOSA CV. | I1167: AOS | J1167: 66038535 | K1167: WBTB2-5 | L1167: SS T-SHIRT WB BATMAN MOVIE - 5 WBTB2-5:NAVY BLUE:S:GRAPHIC:SS T-SHIRT | M1167: 129900 | N1167: =$N$2 -> 0.85 | O1167: =$O1166 -> 17985 | P1167: =$P$2 -> PERCENTAGE
A1168: =$A$2 -> 2022 ALL D85 | B1168: ='2019 ALL N OLDER D95'!$B$2 -> 46121 | C1168: ='2019 ALL N OLDER D95'!$C$2 -> 46127 | D1168: 3260 | E1168: 333 | F1168: 3 | G1168: 4 | H1168: JAVA DESIGN SENTOSA CV. | I1168: AOS | J1168: 66038526 | K1168: WBTB2-4 | L1168: SS T-SHIRT WB BATMAN MOVIE - 4 WBTB2-4:BLACK:XL:GRAPHIC:SS T-SHIRT | M1168: 129900 | N1168: =$N$2 -> 0.85 | O1168: =$O1167 -> 17985 | P1168: =$P$2 -> PERCENTAGE
A1169: =$A$2 -> 2022 ALL D85 | B1169: ='2019 ALL N OLDER D95'!$B$2 -> 46121 | C1169: ='2019 ALL N OLDER D95'!$C$2 -> 46127 | D1169: 3260 | E1169: 333 | F1169: 3 | G1169: 4 | H1169: JAVA DESIGN SENTOSA CV. | I1169: AOS | J1169: 66038517 | K1169: WBTB2-4 | L1169: SS T-SHIRT WB BATMAN MOVIE - 4 WBTB2-4:BLACK:L:GRAPHIC:SS T-SHIRT | M1169: 129900 | N1169: =$N$2 -> 0.85 | O1169: =$O1168 -> 17985 | P1169: =$P$2 -> PERCENTAGE
A1170: =$A$2 -> 2022 ALL D85 | B1170: ='2019 ALL N OLDER D95'!$B$2 -> 46121 | C1170: ='2019 ALL N OLDER D95'!$C$2 -> 46127 | D1170: 3260 | E1170: 333 | F1170: 3 | G1170: 4 | H1170: JAVA DESIGN SENTOSA CV. | I1170: AOS | J1170: 66038508 | K1170: WBTB2-4 | L1170: SS T-SHIRT WB BATMAN MOVIE - 4 WBTB2-4:BLACK:M:GRAPHIC:SS T-SHIRT | M1170: 129900 | N1170: =$N$2 -> 0.85 | O1170: =$O1169 -> 17985 | P1170: =$P$2 -> PERCENTAGE
A1171: =$A$2 -> 2022 ALL D85 | B1171: ='2019 ALL N OLDER D95'!$B$2 -> 46121 | C1171: ='2019 ALL N OLDER D95'!$C$2 -> 46127 | D1171: 3260 | E1171: 333 | F1171: 3 | G1171: 4 | H1171: JAVA DESIGN SENTOSA CV. | I1171: AOS | J1171: 66038491 | K1171: WBTB2-4 | L1171: SS T-SHIRT WB BATMAN MOVIE - 4 WBTB2-4:BLACK:S:GRAPHIC:SS T-SHIRT | M1171: 129900 | N1171: =$N$2 -> 0.85 | O1171: =$O1170 -> 17985 | P1171: =$P$2 -> PERCENTAGE
... A1327: =$A$2 -> 2022 ALL D85 | B1327: ='2019 ALL N OLDER D95'!$B$2 -> 46121 | C1327: ='2019 ALL N OLDER D95'!$C$2 -> 46127 | D1327: 3260 | E1327: 333 | F1327: 3 | G1327: 1 | H1327: JAVA DESIGN | I1327: AOS | J1327: 75740151 | K1327: XMAS22TJ-PR | L1327: SS T-SHIRT PRINT XMAS COLL 2022 - PRINT XMAS XMAS22TJ-PR:MISTY LIGH:XL:GRAPHIC:SS T-SHIRT | M1327: 119900 | N1327: =$N$2 -> 0.85 | O1327: =$O1326 -> 17985 | P1327: =$P$2 -> PERCENTAGE
A1328: =$A$2 -> 2022 ALL D85 | B1328: ='2019 ALL N OLDER D95'!$B$2 -> 46121 | C1328: ='2019 ALL N OLDER D95'!$C$2 -> 46127 | D1328: 3260 | E1328: 333 | F1328: 3 | G1328: 1 | H1328: JAVA DESIGN CV | I1328: AOS | J1328: 71528399 | K1328: ID22TJ-BA | L1328: SS T-SHIRT SEASONAL ID COLL 2022 - BATIK ID22TJ-BA:BLACK:S:GRAPHIC:SS T-SHIRT | M1328: 119900 | N1328: =$N$2 -> 0.85 | O1328: =$O1327 -> 17985 | P1328: =$P$2 -> PERCENTAGE
A1329: =$A$2 -> 2022 ALL D85 | B1329: ='2019 ALL N OLDER D95'!$B$2 -> 46121 | C1329: ='2019 ALL N OLDER D95'!$C$2 -> 46127 | D1329: 3260 | E1329: 333 | F1329: 3 | G1329: 1 | H1329: JAVA DESIGN CV | I1329: AOS | J1329: 71528406 | K1329: ID22TJ-BA | L1329: SS T-SHIRT SEASONAL ID COLL 2022 - BATIK ID22TJ-BA:BLACK:M:GRAPHIC:SS T-SHIRT | M1329: 119900 | N1329: =$N$2 -> 0.85 | O1329: =$O1328 -> 17985 | P1329: =$P$2 -> PERCENTAGE
A1330: =$A$2 -> 2022 ALL D85 | B1330: ='2019 ALL N OLDER D95'!$B$2 -> 46121 | C1330: ='2019 ALL N OLDER D95'!$C$2 -> 46127 | D1330: 3260 | E1330: 333 | F1330: 3 | G1330: 1 | H1330: JAVA DESIGN CV | I1330: AOS | J1330: 71528415 | K1330: ID22TJ-BA | L1330: SS T-SHIRT SEASONAL ID COLL 2022 - BATIK ID22TJ-BA:BLACK:L:GRAPHIC:SS T-SHIRT | M1330: 119900 | N1330: =$N$2 -> 0.85 | O1330: =$O1329 -> 17985 | P1330: =$P$2 -> PERCENTAGE
A1331: =$A$2 -> 2022 ALL D85 | B1331: ='2019 ALL N OLDER D95'!$B$2 -> 46121 | C1331: ='2019 ALL N OLDER D95'!$C$2 -> 46127 | D1331: 3260 | E1331: 333 | F1331: 3 | G1331: 1 | H1331: JAVA DESIGN CV | I1331: AOS | J1331: 71528424 | K1331: ID22TJ-BA | L1331: SS T-SHIRT SEASONAL ID COLL 2022 - BATIK ID22TJ-BA:BLACK:XL:GRAPHIC:SS T-SHIRT | M1331: 119900 | N1331: =$N$2 -> 0.85 | O1331: =$O1330 -> 17985 | P1331: =$P$2 -> PERCENTAGE
A1332: =$A$2 -> 2022 ALL D85 | B1332: ='2019 ALL N OLDER D95'!$B$2 -> 46121 | C1332: ='2019 ALL N OLDER D95'!$C$2 -> 46127 | D1332: 3260 | E1332: 333 | F1332: 3 | G1332: 1 | H1332: JAVA DESIGN CV | I1332: AOS | J1332: 71528479 | K1332: ID22TJ-IND | L1332: SS T-SHIRT SEASONAL ID COLL 2022 - INDONESIA ID22TJ-IND:WHITE:S:GRAPHIC:SS T-SHIRT | M1332: 119900 | N1332: =$N$2 -> 0.85 | O1332: =$O1331 -> 17985 | P1332: =$P$2 -> PERCENTAGE
A1333: =$A$2 -> 2022 ALL D85 | B1333: ='2019 ALL N OLDER D95'!$B$2 -> 46121 | C1333: ='2019 ALL N OLDER D95'!$C$2 -> 46127 | D1333: 3260 | E1333: 333 | F1333: 3 | G1333: 1 | H1333: JAVA DESIGN CV | I1333: AOS | J1333: 71528488 | K1333: ID22TJ-IND | L1333: SS T-SHIRT SEASONAL ID COLL 2022 - INDONESIA ID22TJ-IND:WHITE:M:GRAPHIC:SS T-SHIRT | M1333: 119900 | N1333: =$N$2 -> 0.85 | O1333: =$O1332 -> 17985 | P1333: =$P$2 -> PERCENTAGE
A1334: =$A$2 -> 2022 ALL D85 | B1334: ='2019 ALL N OLDER D95'!$B$2 -> 46121 | C1334: ='2019 ALL N OLDER D95'!$C$2 -> 46127 | D1334: 3260 | E1334: 333 | F1334: 3 | G1334: 1 | H1334: JAVA DESIGN CV | I1334: AOS | J1334: 71528497 | K1334: ID22TJ-IND | L1334: SS T-SHIRT SEASONAL ID COLL 2022 - INDONESIA ID22TJ-IND:WHITE:L:GRAPHIC:SS T-SHIRT | M1334: 119900 | N1334: =$N$2 -> 0.85 | O1334: =$O1333 -> 17985 | P1334: =$P$2 -> PERCENTAGE
A1335: =$A$2 -> 2022 ALL D85 | B1335: ='2019 ALL N OLDER D95'!$B$2 -> 46121 | C1335: ='2019 ALL N OLDER D95'!$C$2 -> 46127 | D1335: 3260 | E1335: 333 | F1335: 3 | G1335: 1 | H1335: JAVA DESIGN CV | I1335: AOS | J1335: 71528504 | K1335: ID22TJ-IND | L1335: SS T-SHIRT SEASONAL ID COLL 2022 - INDONESIA ID22TJ-IND:WHITE:XL:GRAPHIC:SS T-SHIRT | M1335: 119900 | N1335: =$N$2 -> 0.85 | O1335: =$O1334 -> 17985 | P1335: =$P$2 -> PERCENTAGE
A1336: =$A$2 -> 2022 ALL D85 | B1336: ='2019 ALL N OLDER D95'!$B$2 -> 46121 | C1336: ='2019 ALL N OLDER D95'!$C$2 -> 46127 | D1336: 3260 | E1336: 333 | F1336: 3 | G1336: 1 | H1336: JAVA DESIGN CV | I1336: AOS | J1336: 71528513 | K1336: ID22TJ-KR | L1336: SS T-SHIRT SEASONAL ID COLL 2022 - LOMBA KERUPUK ID22TJ-KR:MAROON:S:GRAPHIC:SS T-SHIR | M1336: 119900 | N1336: =$N$2 -> 0.85 | O1336: =$O1335 -> 17985 | P1336: =$P$2 -> PERCENTAGE
A1337: =$A$2 -> 2022 ALL D85 | B1337: ='2019 ALL N OLDER D95'!$B$2 -> 46121 | C1337: ='2019 ALL N OLDER D95'!$C$2 -> 46127 | D1337: 3260 | E1337: 333 | F1337: 3 | G1337: 1 | H1337: JAVA DESIGN CV | I1337: AOS | J1337: 71528522 | K1337: ID22TJ-KR | L1337: SS T-SHIRT SEASONAL ID COLL 2022 - LOMBA KERUPUK ID22TJ-KR:MAROON:M:GRAPHIC:SS T-SHIR | M1337: 119900 | N1337: =$N$2 -> 0.85 | O1337: =$O1336 -> 17985 | P1337: =$P$2 -> PERCENTAGE
A1338: =$A$2 -> 2022 ALL D85 | B1338: ='2019 ALL N OLDER D95'!$B$2 -> 46121 | C1338: ='2019 ALL N OLDER D95'!$C$2 -> 46127 | D1338: 3260 | E1338: 333 | F1338: 3 | G1338: 1 | H1338: JAVA DESIGN CV | I1338: AOS | J1338: 71528531 | K1338: ID22TJ-KR | L1338: SS T-SHIRT SEASONAL ID COLL 2022 - LOMBA KERUPUK ID22TJ-KR:MAROON:L:GRAPHIC:SS T-SHIR | M1338: 119900 | N1338: =$N$2 -> 0.85 | O1338: =$O1337 -> 17985 | P1338: =$P$2 -> PERCENTAGE
A1339: =$A$2 -> 2022 ALL D85 | B1339: ='2019 ALL N OLDER D95'!$B$2 -> 46121 | C1339: ='2019 ALL N OLDER D95'!$C$2 -> 46127 | D1339: 3260 | E1339: 333 | F1339: 3 | G1339: 1 | H1339: JAVA DESIGN CV | I1339: AOS | J1339: 71528540 | K1339: ID22TJ-KR | L1339: SS T-SHIRT SEASONAL ID COLL 2022 - LOMBA KERUPUK ID22TJ-KR:MAROON:XL:GRAPHIC:SS T-SHIR | M1339: 119900 | N1339: =$N$2 -> 0.85 | O1339: =$O1338 -> 17985 | P1339: =$P$2 -> PERCENTAGE
... A2159: =$A$2 -> 2022 ALL D85 | B2159: ='2019 ALL N OLDER D95'!$B$2 -> 46121 | C2159: ='2019 ALL N OLDER D95'!$C$2 -> 46127 | D2159: 3260 | E2159: 333 | F2159: 3 | G2159: 2 | H2159: SAHABAT GARMINDO PT- 81461 | I2159: AOS | J2159: 62061089 | K2159: LEB22-L01 | L2159: LS KOKO MUSLIM 2022 - LEB22-L01 LEB22-L01:WHITE:XL:GRAPHIC:LS KOKO | M2159: 169900 | N2159: =$N$2 -> 0.85 | O2159: =$O2158 -> 17985 | P2159: =$P$2 -> PERCENTAGE

Sheet 2023 ALL D90
A1: ACARA | B1: FROM DATE | C1: TO DATE | D1: DEPT | E1: WORLD | F1: DIVISION | G1: CLASS | H1: SUPPLIER | I1: BRAND | J1: SKU | K1: ARTICLE | L1: DESCRIPTION | M1: HARGA NORMAL | N1: DISKON | O1: HARGA PROMO | P1: DISCOUNT TYPE
A2: 2023 ALL TSHIRT D90 | B2: ='2019 ALL N OLDER D95'!$B$2 -> 46121 | C2: ='2019 ALL N OLDER D95'!$C$2 -> 46127 | D2: 3260 | E2: 333 | F2: 3 | G2: 1 | H2: TRIPUTRA | I2: AOS | J2: 76394202 | K2: TFUU11-PP | L2: SS T-SHIRT FULLPRINT THEME POP PUNK TFUU11-PP:MUSTARD:S:PRINT:SS T-SHIRT | M2: 129900 | N2: 0.9 | O2: =M2*(1-N2) -> 12990 | P2: PERCENTAGE
A3: =$A$2 -> 2023 ALL TSHIRT D90 | B3: ='2019 ALL N OLDER D95'!$B$2 -> 46121 | C3: ='2019 ALL N OLDER D95'!$C$2 -> 46127 | D3: 3260 | E3: 333 | F3: 3 | G3: 1 | H3: TRIPUTRA | I3: AOS | J3: 76394211 | K3: TFUU11-PP | L3: SS T-SHIRT FULLPRINT THEME POP PUNK TFUU11-PP:MUSTARD:M:PRINT:SS T-SHIRT | M3: 129900 | N3: =$N2 -> 0.9 | O3: =M3*(1-N3) -> 12990 | P3: =$P$2 -> PERCENTAGE
A4: =$A$2 -> 2023 ALL TSHIRT D90 | B4: ='2019 ALL N OLDER D95'!$B$2 -> 46121 | C4: ='2019 ALL N OLDER D95'!$C$2 -> 46127 | D4: 3260 | E4: 333 | F4: 3 | G4: 1 | H4: TRIPUTRA | I4: AOS | J4: 76394220 | K4: TFUU11-PP | L4: SS T-SHIRT FULLPRINT THEME POP PUNK TFUU11-PP:MUSTARD:L:PRINT:SS T-SHIRT | M4: 129900 | N4: =$N3 -> 0.9 | O4: =M4*(1-N4) -> 12990 | P4: =$P$2 -> PERCENTAGE
A5: =$A$2 -> 2023 ALL TSHIRT D90 | B5: ='2019 ALL N OLDER D95'!$B$2 -> 46121 | C5: ='2019 ALL N OLDER D95'!$C$2 -> 46127 | D5: 3260 | E5: 333 | F5: 3 | G5: 1 | H5: TRIPUTRA | I5: AOS | J5: 76394239 | K5: TFUU11-PP | L5: SS T-SHIRT FULLPRINT THEME POP PUNK TFUU11-PP:MUSTARD:XL:PRINT:SS T-SHIRT | M5: 129900 | N5: =$N4 -> 0.9 | O5: =M5*(1-N5) -> 12990 | P5: =$P$2 -> PERCENTAGE
A6: =$A$2 -> 2023 ALL TSHIRT D90 | B6: ='2019 ALL N OLDER D95'!$B$2 -> 46121 | C6: ='2019 ALL N OLDER D95'!$C$2 -> 46127 | D6: 3260 | E6: 333 | F6: 3 | G6: 1 | H6: PUTRA JAYA KREASI | I6: AOS | J6: 79077399 | K6: TK9UR-CO | L6: SS T-SHIRT PRINT THEME UNEVEN RELIEF - CONSISTENCY TK9UR-CO:BROWN SUGAR:S:GRAPHIC:SS T-SHIRT | M6: 119900 | N6: =$N5 -> 0.9 | O6: =M6*(1-N6) -> 11990 | P6: =$P$2 -> PERCENTAGE
A7: =$A$2 -> 2023 ALL TSHIRT D90 | B7: ='2019 ALL N OLDER D95'!$B$2 -> 46121 | C7: ='2019 ALL N OLDER D95'!$C$2 -> 46127 | D7: 3260 | E7: 333 | F7: 3 | G7: 1 | H7: PUTRA JAYA KREASI | I7: AOS | J7: 79077406 | K7: TK9UR-CO | L7: SS T-SHIRT PRINT THEME UNEVEN RELIEF - CONSISTENCY TK9UR-CO:BROWN SUGAR:M:GRAPHIC:SS T-SHIRT | M7: 119900 | N7: =$N6 -> 0.9 | O7: =M7*(1-N7) -> 11990 | P7: =$P$2 -> PERCENTAGE
A8: =$A$2 -> 2023 ALL TSHIRT D90 | B8: ='2019 ALL N OLDER D95'!$B$2 -> 46121 | C8: ='2019 ALL N OLDER D95'!$C$2 -> 46127 | D8: 3260 | E8: 333 | F8: 3 | G8: 1 | H8: PUTRA JAYA KREASI | I8: AOS | J8: 79077415 | K8: TK9UR-CO | L8: SS T-SHIRT PRINT THEME UNEVEN RELIEF - CONSISTENCY TK9UR-CO:BROWN SUGAR:L:GRAPHIC:SS T-SHIRT | M8: 119900 | N8: =$N7 -> 0.9 | O8: =M8*(1-N8) -> 11990 | P8: =$P$2 -> PERCENTAGE
A9: =$A$2 -> 2023 ALL TSHIRT D90 | B9: ='2019 ALL N OLDER D95'!$B$2 -> 46121 | C9: ='2019 ALL N OLDER D95'!$C$2 -> 46127 | D9: 3260 | E9: 333 | F9: 3 | G9: 1 | H9: PUTRA JAYA KREASI | I9: AOS | J9: 79077424 | K9: TK9UR-CO | L9: SS T-SHIRT PRINT THEME UNEVEN RELIEF - CONSISTENCY TK9UR-CO:BROWN SUGAR:XL:GRAPHIC:SS T-SHIRT | M9: 119900 | N9: =$N8 -> 0.9 | O9: =M9*(1-N9) -> 11990 | P9: =$P$2 -> PERCENTAGE
A10: =$A$2 -> 2023 ALL TSHIRT D90 | B10: ='2019 ALL N OLDER D95'!$B$2 -> 46121 | C10: ='2019 ALL N OLDER D95'!$C$2 -> 46127 | D10: 3260 | E10: 333 | F10: 3 | G10: 1 | H10: PUTRA JAYA KREASI | I10: AOS | J10: 79077433 | K10: TK9UR-NH | L10: SS T-SHIRT PRINT THEME UNEVEN RELIEF - NEW HABITS TK9UR-NH:MUSTARD:S:GRAPHIC:SS T-SHIRT | M10: 119900 | N10: =$N9 -> 0.9 | O10: =M10*(1-N10) -> 11990 | P10: =$P$2 -> PERCENTAGE
A11: =$A$2 -> 2023 ALL TSHIRT D90 | B11: ='2019 ALL N OLDER D95'!$B$2 -> 46121 | C11: ='2019 ALL N OLDER D95'!$C$2 -> 46127 | D11: 3260 | E11: 333 | F11: 3 | G11: 1 | H11: PUTRA JAYA KREASI | I11: AOS | J11: 79077442 | K11: TK9UR-NH | L11: SS T-SHIRT PRINT THEME UNEVEN RELIEF - NEW HABITS TK9UR-NH:MUSTARD:M:GRAPHIC:SS T-SHIRT | M11: 119900 | N11: =$N10 -> 0.9 | O11: =M11*(1-N11) -> 11990 | P11: =$P$2 -> PERCENTAGE
A12: =$A$2 -> 2023 ALL TSHIRT D90 | B12: ='2019 ALL N OLDER D95'!$B$2 -> 46121 | C12: ='2019 ALL N OLDER D95'!$C$2 -> 46127 | D12: 3260 | E12: 333 | F12: 3 | G12: 1 | H12: PUTRA JAYA KREASI | I12: AOS | J12: 79077451 | K12: TK9UR-NH | L12: SS T-SHIRT PRINT THEME UNEVEN RELIEF - NEW HABITS TK9UR-NH:MUSTARD:L:GRAPHIC:SS T-SHIRT | M12: 119900 | N12: =$N11 -> 0.9 | O12: =M12*(1-N12) -> 11990 | P12: =$P$2 -> PERCENTAGE
A13: =$A$2 -> 2023 ALL TSHIRT D90 | B13: ='2019 ALL N OLDER D95'!$B$2 -> 46121 | C13: ='2019 ALL N OLDER D95'!$C$2 -> 46127 | D13: 3260 | E13: 333 | F13: 3 | G13: 1 | H13: PUTRA JAYA KREASI | I13: AOS | J13: 79077460 | K13: TK9UR-NH | L13: SS T-SHIRT PRINT THEME UNEVEN RELIEF - NEW HABITS TK9UR-NH:MUSTARD:XL:GRAPHIC:SS T-SHIRT | M13: 119900 | N13: =$N12 -> 0.9 | O13: =M13*(1-N13) -> 11990 | P13: =$P$2 -> PERCENTAGE
A14: =$A$2 -> 2023 ALL TSHIRT D90 | B14: ='2019 ALL N OLDER D95'!$B$2 -> 46121 | C14: ='2019 ALL N OLDER D95'!$C$2 -> 46127 | D14: 3260 | E14: 333 | F14: 3 | G14: 1 | H14: PUTRA JAYA KREASI | I14: AOS | J14: 79077479 | K14: TK9UR-IT | L14: SS T-SHIRT PRINT THEME UNEVEN RELIEF - INTERSECTION TK9UR-IT:WINE:S:GRAPHIC:SS T-SHIRT | M14: 119900 | N14: =$N13 -> 0.9 | O14: =M14*(1-N14) -> 11990 | P14: =$P$2 -> PERCENTAGE
... A1835: =$A$2 -> 2023 ALL TSHIRT D90 | B1835: ='2019 ALL N OLDER D95'!$B$2 -> 46121 | C1835: ='2019 ALL N OLDER D95'!$C$2 -> 46127 | D1835: 3260 | E1835: 333 | F1835: 3 | G1835: 4 | H1835: JAVA DESIGN | I1835: AOS | J1835: 85495587 | K1835: WBXMAS23-MA | L1835: SS T-SHIRT WB XMAS COLL 2023 - THE MARTIAN WBXMAS23-MA:MAROON:XL:GRAPHIC:SS T-SHIRT | M1835: 129900 | N1835: =$N1834 -> 0.9 | O1835: =M1835*(1-N1835) -> 12990 | P1835: =$P$2 -> PERCENTAGE
A1836: =$A$2 -> 2023 ALL TSHIRT D90 | B1836: ='2019 ALL N OLDER D95'!$B$2 -> 46121 | C1836: ='2019 ALL N OLDER D95'!$C$2 -> 46127 | D1836: 3260 | E1836: 333 | F1836: 3 | G1836: 3 | H1836: JAVA DESIGN SENTOSA CV. | I1836: AOS | J1836: 14590937 | K1836: R3J8-FO | L1836: 3/4 RAGLAN T-SHIRT THEME VARSITY ICON - FOOTBALL R3J8-FO:MISTY DARK GREY:S:GRAPHIC:3/4 RAGLAN T-SHIR | M1836: 129900 | N1836: =$N1835 -> 0.9 | O1836: =M1836*(1-N1836) -> 12990 | P1836: =$P$2 -> PERCENTAGE
A1837: =$A$2 -> 2023 ALL TSHIRT D90 | B1837: ='2019 ALL N OLDER D95'!$B$2 -> 46121 | C1837: ='2019 ALL N OLDER D95'!$C$2 -> 46127 | D1837: 3260 | E1837: 333 | F1837: 3 | G1837: 3 | H1837: JAVA DESIGN SENTOSA CV. | I1837: AOS | J1837: 14590946 | K1837: R3J8-FO | L1837: 3/4 RAGLAN T-SHIRT THEME VARSITY ICON - FOOTBALL R3J8-FO:MISTY DARK GREY:M:GRAPHIC:3/4 RAGLAN T-SHIR | M1837: 129900 | N1837: =$N1836 -> 0.9 | O1837: =M1837*(1-N1837) -> 12990 | P1837: =$P$2 -> PERCENTAGE
A1838: =$A$2 -> 2023 ALL TSHIRT D90 | B1838: ='2019 ALL N OLDER D95'!$B$2 -> 46121 | C1838: ='2019 ALL N OLDER D95'!$C$2 -> 46127 | D1838: 3260 | E1838: 333 | F1838: 3 | G1838: 3 | H1838: JAVA DESIGN SENTOSA CV. | I1838: AOS | J1838: 14590955 | K1838: R3J8-FO | L1838: 3/4 RAGLAN T-SHIRT THEME VARSITY ICON - FOOTBALL R3J8-FO:MISTY DARK GREY:L:GRAPHIC:3/4 RAGLAN T-SHIR | M1838: 129900 | N1838: =$N1837 -> 0.9 | O1838: =M1838*(1-N1838) -> 12990 | P1838: =$P$2 -> PERCENTAGE
A1839: =$A$2 -> 2023 ALL TSHIRT D90 | B1839: ='2019 ALL N OLDER D95'!$B$2 -> 46121 | C1839: ='2019 ALL N OLDER D95'!$C$2 -> 46127 | D1839: 3260 | E1839: 333 | F1839: 3 | G1839: 3 | H1839: JAVA DESIGN SENTOSA CV. | I1839: AOS | J1839: 14590964 | K1839: R3J8-FO | L1839: 3/4 RAGLAN T-SHIRT THEME VARSITY ICON - FOOTBALL R3J8-FO:MISTY DARK GREY:XL:GRAPHIC:3/4 RAGLAN T-SHI | M1839: 129900 | N1839: =$N1838 -> 0.9 | O1839: =M1839*(1-N1839) -> 12990 | P1839: =$P$2 -> PERCENTAGE
A1840: =$A$2 -> 2023 ALL TSHIRT D90 | B1840: ='2019 ALL N OLDER D95'!$B$2 -> 46121 | C1840: ='2019 ALL N OLDER D95'!$C$2 -> 46127 | D1840: 3260 | E1840: 333 | F1840: 3 | G1840: 3 | H1840: JAVA DESIGN SENTOSA CV. | I1840: AOS | J1840: 14590973 | K1840: R3J8-FO | L1840: 3/4 RAGLAN T-SHIRT THEME VARSITY ICON - FOOTBALL R3J8-FO:DARK JADE:S:GRAPHIC:3/4 RAGLAN T-SHIRT | M1840: 129900 | N1840: =$N1839 -> 0.9 | O1840: =M1840*(1-N1840) -> 12990 | P1840: =$P$2 -> PERCENTAGE
A1841: =$A$2 -> 2023 ALL TSHIRT D90 | B1841: ='2019 ALL N OLDER D95'!$B$2 -> 46121 | C1841: ='2019 ALL N OLDER D95'!$C$2 -> 46127 | D1841: 3260 | E1841: 333 | F1841: 3 | G1841: 3 | H1841: JAVA DESIGN SENTOSA CV. | I1841: AOS | J1841: 14590982 | K1841: R3J8-FO | L1841: 3/4 RAGLAN T-SHIRT THEME VARSITY ICON - FOOTBALL R3J8-FO:DARK JADE:M:GRAPHIC:3/4 RAGLAN T-SHIRT | M1841: 129900 | N1841: =$N1840 -> 0.9 | O1841: =M1841*(1-N1841) -> 12990 | P1841: =$P$2 -> PERCENTAGE
A1842: =$A$2 -> 2023 ALL TSHIRT D90 | B1842: ='2019 ALL N OLDER D95'!$B$2 -> 46121 | C1842: ='2019 ALL N OLDER D95'!$C$2 -> 46127 | D1842: 3260 | E1842: 333 | F1842: 3 | G1842: 3 | H1842: JAVA DESIGN SENTOSA CV. | I1842: AOS | J1842: 14590991 | K1842: R3J8-FO | L1842: 3/4 RAGLAN T-SHIRT THEME VARSITY ICON - FOOTBALL R3J8-FO:DARK JADE:L:GRAPHIC:3/4 RAGLAN T-SHIRT | M1842: 129900 | N1842: =$N1841 -> 0.9 | O1842: =M1842*(1-N1842) -> 12990 | P1842: =$P$2 -> PERCENTAGE
A1843: =$A$2 -> 2023 ALL TSHIRT D90 | B1843: ='2019 ALL N OLDER D95'!$B$2 -> 46121 | C1843: ='2019 ALL N OLDER D95'!$C$2 -> 46127 | D1843: 3260 | E1843: 333 | F1843: 3 | G1843: 3 | H1843: JAVA DESIGN SENTOSA CV. | I1843: AOS | J1843: 14591007 | K1843: R3J8-FO | L1843: 3/4 RAGLAN T-SHIRT THEME VARSITY ICON - FOOTBALL R3J8-FO:DARK JADE:XL:GRAPHIC:3/4 RAGLAN T-SHIRT | M1843: 129900 | N1843: =$N1842 -> 0.9 | O1843: =M1843*(1-N1843) -> 12990 | P1843: =$P$2 -> PERCENTAGE
A1844: =$A$2 -> 2023 ALL TSHIRT D90 | B1844: ='2019 ALL N OLDER D95'!$B$2 -> 46121 | C1844: ='2019 ALL N OLDER D95'!$C$2 -> 46127 | D1844: 3260 | E1844: 333 | F1844: 3 | G1844: 3 | H1844: JAVA DESIGN SENTOSA CV. | I1844: AOS | J1844: 14591016 | K1844: R3J8-YE | L1844: 3/4 RAGLAN T-SHIRT THEME VARSITY ICON - YELLOWSTONE R3J8-YE:BLACK:S:GRAPHIC:3/4 RAGLAN T-SHIRT | M1844: 129900 | N1844: =$N1843 -> 0.9 | O1844: =M1844*(1-N1844) -> 12990 | P1844: =$P$2 -> PERCENTAGE
A1845: =$A$2 -> 2023 ALL TSHIRT D90 | B1845: ='2019 ALL N OLDER D95'!$B$2 -> 46121 | C1845: ='2019 ALL N OLDER D95'!$C$2 -> 46127 | D1845: 3260 | E1845: 333 | F1845: 3 | G1845: 3 | H1845: JAVA DESIGN SENTOSA CV. | I1845: AOS | J1845: 14591025 | K1845: R3J8-YE | L1845: 3/4 RAGLAN T-SHIRT THEME VARSITY ICON - YELLOWSTONE R3J8-YE:BLACK:M:GRAPHIC:3/4 RAGLAN T-SHIRT | M1845: 129900 | N1845: =$N1844 -> 0.9 | O1845: =M1845*(1-N1845) -> 12990 | P1845: =$P$2 -> PERCENTAGE
A1846: =$A$2 -> 2023 ALL TSHIRT D90 | B1846: ='2019 ALL N OLDER D95'!$B$2 -> 46121 | C1846: ='2019 ALL N OLDER D95'!$C$2 -> 46127 | D1846: 3260 | E1846: 333 | F1846: 3 | G1846: 3 | H1846: JAVA DESIGN SENTOSA CV. | I1846: AOS | J1846: 14591034 | K1846: R3J8-YE | L1846: 3/4 RAGLAN T-SHIRT THEME VARSITY ICON - YELLOWSTONE R3J8-YE:BLACK:L:GRAPHIC:3/4 RAGLAN T-SHIRT | M1846: 129900 | N1846: =$N1845 -> 0.9 | O1846: =M1846*(1-N1846) -> 12990 | P1846: =$P$2 -> PERCENTAGE
A1847: =$A$2 -> 2023 ALL TSHIRT D90 | B1847: ='2019 ALL N OLDER D95'!$B$2 -> 46121 | C1847: ='2019 ALL N OLDER D95'!$C$2 -> 46127 | D1847: 3260 | E1847: 333 | F1847: 3 | G1847: 3 | H1847: JAVA DESIGN SENTOSA CV. | I1847: AOS | J1847: 14591043 | K1847: R3J8-YE | L1847: 3/4 RAGLAN T-SHIRT THEME VARSITY ICON - YELLOWSTONE R3J8-YE:BLACK:XL:GRAPHIC:3/4 RAGLAN T-SHIRT | M1847: 129900 | N1847: =$N1846 -> 0.9 | O1847: =M1847*(1-N1847) -> 12990 | P1847: =$P$2 -> PERCENTAGE
... A1867: =$A$2 -> 2023 ALL TSHIRT D90 | B1867: ='2019 ALL N OLDER D95'!$B$2 -> 46121 | C1867: ='2019 ALL N OLDER D95'!$C$2 -> 46127 | D1867: 3260 | E1867: 333 | F1867: 3 | G1867: 3 | H1867: JAVA DESIGN SENTOSA CV. | I1867: AOS | J1867: 79318664 | K1867: R3J12-EX | L1867: 3/4 RAGLAN T-SHIRT THEME GEOMETRY - EXIST R3J12-EX:BROWN SUGAR:XL:GRAPHIC:3/4 RAGLAN T-SHIRT | M1867: 129900 | N1867: =$N1866 -> 0.9 | O1867: =M1867*(1-N1867) -> 12990 | P1867: =$P$2 -> PERCENTAGE
A1868: =$A$2 -> 2023 ALL TSHIRT D90 | B1868: ='2019 ALL N OLDER D95'!$B$2 -> 46121 | C1868: ='2019 ALL N OLDER D95'!$C$2 -> 46127 | D1868: 3260 | E1868: 333 | F1868: 3 | H1868: JAVA DESIGN SENTOSA CV. | I1868: AOS | J1868: 79318673 | K1868: R3J12-EX | L1868: 3/4 RAGLAN T-SHIRT THEME GEOMETRY - EXIST R3J12-EX:MISTY MEDIUM BROWN:S:GRAPHIC:3/4 RAGLAN T-SHIRT | M1868: 129900 | N1868: =$N1867 -> 0.9 | O1868: =M1868*(1-N1868) -> 12990 | P1868: =$P$2 -> PERCENTAGE
A1869: =$A$2 -> 2023 ALL TSHIRT D90 | B1869: ='2019 ALL N OLDER D95'!$B$2 -> 46121 | C1869: ='2019 ALL N OLDER D95'!$C$2 -> 46127 | D1869: 3260 | E1869: 333 | F1869: 3 | H1869: JAVA DESIGN SENTOSA CV. | I1869: AOS | J1869: 79318682 | K1869: R3J12-EX | L1869: 3/4 RAGLAN T-SHIRT THEME GEOMETRY - EXIST R3J12-EX:MISTY MEDIUM BROWN:M:GRAPHIC:3/4 RAGLAN T-SHIRT | M1869: 129900 | N1869: =$N1868 -> 0.9 | O1869: =M1869*(1-N1869) -> 12990 | P1869: =$P$2 -> PERCENTAGE
A1870: =$A$2 -> 2023 ALL TSHIRT D90 | B1870: ='2019 ALL N OLDER D95'!$B$2 -> 46121 | C1870: ='2019 ALL N OLDER D95'!$C$2 -> 46127 | D1870: 3260 | E1870: 333 | F1870: 3 | H1870: JAVA DESIGN SENTOSA CV. | I1870: AOS | J1870: 79318691 | K1870: R3J12-EX | L1870: 3/4 RAGLAN T-SHIRT THEME GEOMETRY - EXIST R3J12-EX:MISTY MEDIUM BROWN:L:GRAPHIC:3/4 RAGLAN T-SHIRT | M1870: 129900 | N1870: =$N1869 -> 0.9 | O1870: =M1870*(1-N1870) -> 12990 | P1870: =$P$2 -> PERCENTAGE
A1871: =$A$2 -> 2023 ALL TSHIRT D90 | B1871: ='2019 ALL N OLDER D95'!$B$2 -> 46121 | C1871: ='2019 ALL N OLDER D95'!$C$2 -> 46127 | D1871: 3260 | E1871: 333 | F1871: 3 | H1871: JAVA DESIGN SENTOSA CV. | I1871: AOS | J1871: 79318708 | K1871: R3J12-EX | L1871: 3/4 RAGLAN T-SHIRT THEME GEOMETRY - EXIST R3J12-EX:MISTY MEDIUM BROWN:XL:GRAPHIC:3/4 RAGLAN T-SHIRT | M1871: 129900 | N1871: =$N1870 -> 0.9 | O1871: =M1871*(1-N1871) -> 12990 | P1871: =$P$2 -> PERCENTAGE
A1872: =$A$2 -> 2023 ALL TSHIRT D90 | B1872: ='2019 ALL N OLDER D95'!$B$2 -> 46121 | C1872: ='2019 ALL N OLDER D95'!$C$2 -> 46127 | D1872: 3260 | E1872: 333 | F1872: 3 | H1872: JAVA DESIGN SENTOSA CV. | I1872: AOS | J1872: 79704317 | K1872: RSJ3-AP | L1872: SS RAGLAN T-SHIRT PRINT THEME EXPRESSION LETTER - ACTIVE PERFORM RSJ3-AP:WHITE:S:TEXT:SS RAGLAN T-SH | M1872: 129900 | N1872: =$N1871 -> 0.9 | O1872: =M1872*(1-N1872) -> 12990 | P1872: =$P$2 -> PERCENTAGE
A1873: =$A$2 -> 2023 ALL TSHIRT D90 | B1873: ='2019 ALL N OLDER D95'!$B$2 -> 46121 | C1873: ='2019 ALL N OLDER D95'!$C$2 -> 46127 | D1873: 3260 | E1873: 333 | F1873: 3 | H1873: JAVA DESIGN SENTOSA CV. | I1873: AOS | J1873: 79704326 | K1873: RSJ3-AP | L1873: SS RAGLAN T-SHIRT PRINT THEME EXPRESSION LETTER - ACTIVE PERFORM RSJ3-AP:WHITE:M:TEXT:SS RAGLAN T-SH | M1873: 129900 | N1873: =$N1872 -> 0.9 | O1873: =M1873*(1-N1873) -> 12990 | P1873: =$P$2 -> PERCENTAGE
A1874: =$A$2 -> 2023 ALL TSHIRT D90 | B1874: ='2019 ALL N OLDER D95'!$B$2 -> 46121 | C1874: ='2019 ALL N OLDER D95'!$C$2 -> 46127 | D1874: 3260 | E1874: 333 | F1874: 3 | H1874: JAVA DESIGN SENTOSA CV. | I1874: AOS | J1874: 79704335 | K1874: RSJ3-AP | L1874: SS RAGLAN T-SHIRT PRINT THEME EXPRESSION LETTER - ACTIVE PERFORM RSJ3-AP:WHITE:L:TEXT:SS RAGLAN T-SH | M1874: 129900 | N1874: =$N1873 -> 0.9 | O1874: =M1874*(1-N1874) -> 12990 | P1874: =$P$2 -> PERCENTAGE
A1875: =$A$2 -> 2023 ALL TSHIRT D90 | B1875: ='2019 ALL N OLDER D95'!$B$2 -> 46121 | C1875: ='2019 ALL N OLDER D95'!$C$2 -> 46127 | D1875: 3260 | E1875: 333 | F1875: 3 | H1875: JAVA DESIGN SENTOSA CV. | I1875: AOS | J1875: 79704344 | K1875: RSJ3-AP | L1875: SS RAGLAN T-SHIRT PRINT THEME EXPRESSION LETTER - ACTIVE PERFORM RSJ3-AP:WHITE:XL:TEXT:SS RAGLAN T-S | M1875: 129900 | N1875: =$N1874 -> 0.9 | O1875: =M1875*(1-N1875) -> 12990 | P1875: =$P$2 -> PERCENTAGE
A1876: =$A$2 -> 2023 ALL TSHIRT D90 | B1876: ='2019 ALL N OLDER D95'!$B$2 -> 46121 | C1876: ='2019 ALL N OLDER D95'!$C$2 -> 46127 | D1876: 3260 | E1876: 333 | F1876: 3 | H1876: JAVA DESIGN SENTOSA CV. | I1876: AOS | J1876: 79704353 | K1876: RSJ3-AP | L1876: SS RAGLAN T-SHIRT PRINT THEME EXPRESSION LETTER - ACTIVE PERFORM RSJ3-AP:MISTY LIGHT BLUE:S:TEXT:SS | M1876: 129900 | N1876: =$N1875 -> 0.9 | O1876: =M1876*(1-N1876) -> 12990 | P1876: =$P$2 -> PERCENTAGE
A1877: =$A$2 -> 2023 ALL TSHIRT D90 | B1877: ='2019 ALL N OLDER D95'!$B$2 -> 46121 | C1877: ='2019 ALL N OLDER D95'!$C$2 -> 46127 | D1877: 3260 | E1877: 333 | F1877: 3 | H1877: JAVA DESIGN SENTOSA CV. | I1877: AOS | J1877: 79704362 | K1877: RSJ3-AP | L1877: SS RAGLAN T-SHIRT PRINT THEME EXPRESSION LETTER - ACTIVE PERFORM RSJ3-AP:MISTY LIGHT BLUE:M:TEXT:SS | M1877: 129900 | N1877: =$N1876 -> 0.9 | O1877: =M1877*(1-N1877) -> 12990 | P1877: =$P$2 -> PERCENTAGE
A1878: =$A$2 -> 2023 ALL TSHIRT D90 | B1878: ='2019 ALL N OLDER D95'!$B$2 -> 46121 | C1878: ='2019 ALL N OLDER D95'!$C$2 -> 46127 | D1878: 3260 | E1878: 333 | F1878: 3 | H1878: JAVA DESIGN SENTOSA CV. | I1878: AOS | J1878: 79704371 | K1878: RSJ3-AP | L1878: SS RAGLAN T-SHIRT PRINT THEME EXPRESSION LETTER - ACTIVE PERFORM RSJ3-AP:MISTY LIGHT BLUE:L:TEXT:SS | M1878: 129900 | N1878: =$N1877 -> 0.9 | O1878: =M1878*(1-N1878) -> 12990 | P1878: =$P$2 -> PERCENTAGE
A1879: =$A$2 -> 2023 ALL TSHIRT D90 | B1879: ='2019 ALL N OLDER D95'!$B$2 -> 46121 | C1879: ='2019 ALL N OLDER D95'!$C$2 -> 46127 | D1879: 3260 | E1879: 333 | F1879: 3 | H1879: JAVA DESIGN SENTOSA CV. | I1879: AOS | J1879: 79704380 | K1879: RSJ3-AP | L1879: SS RAGLAN T-SHIRT PRINT THEME EXPRESSION LETTER - ACTIVE PERFORM RSJ3-AP:MISTY LIGHT BLUE:XL:TEXT:SS | M1879: 129900 | N1879: =$N1878 -> 0.9 | O1879: =M1879*(1-N1879) -> 12990 | P1879: =$P$2 -> PERCENTAGE
... A1926: =$A$2 -> 2023 ALL TSHIRT D90 | B1926: ='2019 ALL N OLDER D95'!$B$2 -> 46121 | C1926: ='2019 ALL N OLDER D95'!$C$2 -> 46127 | D1926: 3260 | E1926: 333 | F1926: 3 | H1926: JAVA DESIGN SENTOSA CV. | I1926: AOS | J1926: 15972504 | K1926: R3J2-BRO | L1926: 3/4 RAGLAN T-SHIRT THEME CITY - BROOKLYN R3J2-BRO:MISTY LIGHT BLUE:S:GRAPHIC:3/4 RAGLAN T-SHIRT | M1926: 129900 | N1926: =$N1925 -> 0.9 | O1926: =M1926*(1-N1926) -> 12990 | P1926: =$P$2 -> PERCENTAGE
A1927: =$A$2 -> 2023 ALL TSHIRT D90 | B1927: ='2019 ALL N OLDER D95'!$B$2 -> 46121 | C1927: ='2019 ALL N OLDER D95'!$C$2 -> 46127 | D1927: 3260 | E1927: 333 | F1927: 3 | H1927: JAVA DESIGN SENTOSA CV. | I1927: AOS | J1927: 15972513 | K1927: =K1926 -> R3J2-BRO | L1927: 3/4 RAGLAN T-SHIRT THEME CITY - BROOKLYN R3J2-BRO:MISTY LIGHT BLUE:M:GRAPHIC:3/4 RAGLAN T-SHIRT | M1927: 129900 | N1927: =$N1926 -> 0.9 | O1927: =M1927*(1-N1927) -> 12990 | P1927: =$P$2 -> PERCENTAGE
A1928: =$A$2 -> 2023 ALL TSHIRT D90 | B1928: ='2019 ALL N OLDER D95'!$B$2 -> 46121 | C1928: ='2019 ALL N OLDER D95'!$C$2 -> 46127 | D1928: 3260 | E1928: 333 | F1928: 3 | H1928: JAVA DESIGN SENTOSA CV. | I1928: AOS | J1928: 15972522 | K1928: =K1927 -> R3J2-BRO | L1928: 3/4 RAGLAN T-SHIRT THEME CITY - BROOKLYN R3J2-BRO:MISTY LIGHT BLUE:L:GRAPHIC:3/4 RAGLAN T-SHIRT | M1928: 129900 | N1928: =$N1927 -> 0.9 | O1928: =M1928*(1-N1928) -> 12990 | P1928: =$P$2 -> PERCENTAGE
A1929: =$A$2 -> 2023 ALL TSHIRT D90 | B1929: ='2019 ALL N OLDER D95'!$B$2 -> 46121 | C1929: ='2019 ALL N OLDER D95'!$C$2 -> 46127 | D1929: 3260 | E1929: 333 | F1929: 3 | H1929: JAVA DESIGN SENTOSA CV. | I1929: AOS | J1929: 15972531 | K1929: =K1928 -> R3J2-BRO | L1929: 3/4 RAGLAN T-SHIRT THEME CITY - BROOKLYN R3J2-BRO:MISTY LIGHT BLUE:XL:GRAPHIC:3/4 RAGLAN T-SHIRT | M1929: 129900 | N1929: =$N1928 -> 0.9 | O1929: =M1929*(1-N1929) -> 12990 | P1929: =$P$2 -> PERCENTAGE
A1930: =$A$2 -> 2023 ALL TSHIRT D90 | B1930: ='2019 ALL N OLDER D95'!$B$2 -> 46121 | C1930: ='2019 ALL N OLDER D95'!$C$2 -> 46127 | D1930: 3260 | E1930: 333 | F1930: 3 | H1930: JAVA DESIGN SENTOSA CV. | I1930: AOS | J1930: 15972540 | K1930: =K1929 -> R3J2-BRO | L1930: 3/4 RAGLAN T-SHIRT THEME CITY - BROOKLYN R3J2-BRO:NAVY BLUE:S:GRAPHIC:3/4 RAGLAN T-SHIRT | M1930: 129900 | N1930: =$N1929 -> 0.9 | O1930: =M1930*(1-N1930) -> 12990 | P1930: =$P$2 -> PERCENTAGE
A1931: =$A$2 -> 2023 ALL TSHIRT D90 | B1931: ='2019 ALL N OLDER D95'!$B$2 -> 46121 | C1931: ='2019 ALL N OLDER D95'!$C$2 -> 46127 | D1931: 3260 | E1931: 333 | F1931: 3 | H1931: JAVA DESIGN SENTOSA CV. | I1931: AOS | J1931: 15972559 | K1931: =K1930 -> R3J2-BRO | L1931: 3/4 RAGLAN T-SHIRT THEME CITY - BROOKLYN R3J2-BRO:NAVY BLUE:M:GRAPHIC:3/4 RAGLAN T-SHIRT | M1931: 129900 | N1931: =$N1930 -> 0.9 | O1931: =M1931*(1-N1931) -> 12990 | P1931: =$P$2 -> PERCENTAGE
A1932: =$A$2 -> 2023 ALL TSHIRT D90 | B1932: ='2019 ALL N OLDER D95'!$B$2 -> 46121 | C1932: ='2019 ALL N OLDER D95'!$C$2 -> 46127 | D1932: 3260 | E1932: 333 | F1932: 3 | H1932: JAVA DESIGN SENTOSA CV. | I1932: AOS | J1932: 15972568 | K1932: =K1931 -> R3J2-BRO | L1932: 3/4 RAGLAN T-SHIRT THEME CITY - BROOKLYN R3J2-BRO:NAVY BLUE:L:GRAPHIC:3/4 RAGLAN T-SHIRT | M1932: 129900 | N1932: =$N1931 -> 0.9 | O1932: =M1932*(1-N1932) -> 12990 | P1932: =$P$2 -> PERCENTAGE
A1933: =$A$2 -> 2023 ALL TSHIRT D90 | B1933: ='2019 ALL N OLDER D95'!$B$2 -> 46121 | C1933: ='2019 ALL N OLDER D95'!$C$2 -> 46127 | D1933: 3260 | E1933: 333 | F1933: 3 | H1933: JAVA DESIGN SENTOSA CV. | I1933: AOS | J1933: 15972577 | K1933: =K1932 -> R3J2-BRO | L1933: 3/4 RAGLAN T-SHIRT THEME CITY - BROOKLYN R3J2-BRO:NAVY BLUE:XL:GRAPHIC:3/4 RAGLAN T-SHIRT | M1933: 129900 | N1933: =$N1932 -> 0.9 | O1933: =M1933*(1-N1933) -> 12990 | P1933: =$P$2 -> PERCENTAGE
A1934: =$A$2 -> 2023 ALL TSHIRT D90 | B1934: ='2019 ALL N OLDER D95'!$B$2 -> 46121 | C1934: ='2019 ALL N OLDER D95'!$C$2 -> 46127 | D1934: 3260 | E1934: 333 | F1934: 3 | H1934: JAVA DESIGN SENTOSA CV. | I1934: AOS | J1934: 15972460 | K1934: R3J2-CHI | L1934: 3/4 RAGLAN T-SHIRT THEME CITY - CHICAGO R3J2-CHI:BLACK:S:GRAPHIC:3/4 RAGLAN T-SHIRT | M1934: 129900 | N1934: =$N1933 -> 0.9 | O1934: =M1934*(1-N1934) -> 12990 | P1934: =$P$2 -> PERCENTAGE
A1935: =$A$2 -> 2023 ALL TSHIRT D90 | B1935: ='2019 ALL N OLDER D95'!$B$2 -> 46121 | C1935: ='2019 ALL N OLDER D95'!$C$2 -> 46127 | D1935: 3260 | E1935: 333 | F1935: 3 | H1935: JAVA DESIGN SENTOSA CV. | I1935: AOS | J1935: 15972479 | K1935: =K1934 -> R3J2-CHI | L1935: 3/4 RAGLAN T-SHIRT THEME CITY - CHICAGO R3J2-CHI:BLACK:M:GRAPHIC:3/4 RAGLAN T-SHIRT | M1935: 129900 | N1935: =$N1934 -> 0.9 | O1935: =M1935*(1-N1935) -> 12990 | P1935: =$P$2 -> PERCENTAGE
A1936: =$A$2 -> 2023 ALL TSHIRT D90 | B1936: ='2019 ALL N OLDER D95'!$B$2 -> 46121 | C1936: ='2019 ALL N OLDER D95'!$C$2 -> 46127 | D1936: 3260 | E1936: 333 | F1936: 3 | H1936: JAVA DESIGN SENTOSA CV. | I1936: AOS | J1936: 15972488 | K1936: =K1935 -> R3J2-CHI | L1936: 3/4 RAGLAN T-SHIRT THEME CITY - CHICAGO R3J2-CHI:BLACK:L:GRAPHIC:3/4 RAGLAN T-SHIRT | M1936: 129900 | N1936: =$N1935 -> 0.9 | O1936: =M1936*(1-N1936) -> 12990 | P1936: =$P$2 -> PERCENTAGE
A1937: =$A$2 -> 2023 ALL TSHIRT D90 | B1937: ='2019 ALL N OLDER D95'!$B$2 -> 46121 | C1937: ='2019 ALL N OLDER D95'!$C$2 -> 46127 | D1937: 3260 | E1937: 333 | F1937: 3 | H1937: JAVA DESIGN SENTOSA CV. | I1937: AOS | J1937: 15972497 | K1937: =K1936 -> R3J2-CHI | L1937: 3/4 RAGLAN T-SHIRT THEME CITY - CHICAGO R3J2-CHI:BLACK:XL:GRAPHIC:3/4 RAGLAN T-SHIRT | M1937: 129900 | N1937: =$N1936 -> 0.9 | O1937: =M1937*(1-N1937) -> 12990 | P1937: =$P$2 -> PERCENTAGE
A1938: =$A$2 -> 2023 ALL TSHIRT D90 | B1938: ='2019 ALL N OLDER D95'!$B$2 -> 46121 | C1938: ='2019 ALL N OLDER D95'!$C$2 -> 46127 | D1938: 3260 | E1938: 333 | F1938: 3 | H1938: JAVA DESIGN SENTOSA CV. | I1938: AOS | J1938: 16241006 | K1938: R3J2-NYC | L1938: 3/4 RAGLAN T-SHIRT THEME CITY - NEW YORK R3J2-NYC:SAND:S:GRAPHIC:3/4 RAGLAN T-SHIRT | M1938: 129900 | N1938: =$N1937 -> 0.9 | O1938: =M1938*(1-N1938) -> 12990 | P1938: =$P$2 -> PERCENTAGE
A1939: =$A$2 -> 2023 ALL TSHIRT D90 | B1939: ='2019 ALL N OLDER D95'!$B$2 -> 46121 | C1939: ='2019 ALL N OLDER D95'!$C$2 -> 46127 | D1939: 3260 | E1939: 333 | F1939: 3 | H1939: JAVA DESIGN SENTOSA CV. | I1939: AOS | J1939: 16241015 | K1939: =K1938 -> R3J2-NYC | L1939: 3/4 RAGLAN T-SHIRT THEME CITY - NEW YORK R3J2-NYC:SAND:M:GRAPHIC:3/4 RAGLAN T-SHIRT | M1939: 129900 | N1939: =$N1938 -> 0.9 | O1939: =M1939*(1-N1939) -> 12990 | P1939: =$P$2 -> PERCENTAGE
A1940: =$A$2 -> 2023 ALL TSHIRT D90 | B1940: ='2019 ALL N OLDER D95'!$B$2 -> 46121 | C1940: ='2019 ALL N OLDER D95'!$C$2 -> 46127 | D1940: 3260 | E1940: 333 | F1940: 3 | H1940: JAVA DESIGN SENTOSA CV. | I1940: AOS | J1940: 80732178 | K1940: R3J2S-O | L1940: 3/4 RAGLAN T-SHIRT PRINT THEME SPACE TECHNO - ONE LIFE R3J2S-O:CHARCOAL:S:GRAPHIC:3/4 RAGLAN T-SHIRT | M1940: 129900 | N1940: =$N1939 -> 0.9 | O1940: =M1940*(1-N1940) -> 12990 | P1940: =$P$2 -> PERCENTAGE
A1941: =$A$2 -> 2023 ALL TSHIRT D90 | B1941: ='2019 ALL N OLDER D95'!$B$2 -> 46121 | C1941: ='2019 ALL N OLDER D95'!$C$2 -> 46127 | D1941: 3260 | E1941: 333 | F1941: 3 | H1941: JAVA DESIGN SENTOSA CV. | I1941: AOS | J1941: 80732187 | K1941: =K1940 -> R3J2S-O | L1941: 3/4 RAGLAN T-SHIRT PRINT THEME SPACE TECHNO - ONE LIFE R3J2S-O:CHARCOAL:M:GRAPHIC:3/4 RAGLAN T-SHIRT | M1941: 129900 | N1941: =$N1940 -> 0.9 | O1941: =M1941*(1-N1941) -> 12990 | P1941: =$P$2 -> PERCENTAGE
A1942: =$A$2 -> 2023 ALL TSHIRT D90 | B1942: ='2019 ALL N OLDER D95'!$B$2 -> 46121 | C1942: ='2019 ALL N OLDER D95'!$C$2 -> 46127 | D1942: 3260 | E1942: 333 | F1942: 3 | H1942: JAVA DESIGN SENTOSA CV. | I1942: AOS | J1942: 80732196 | K1942: =K1941 -> R3J2S-O | L1942: 3/4 RAGLAN T-SHIRT PRINT THEME SPACE TECHNO - ONE LIFE R3J2S-O:CHARCOAL:L:GRAPHIC:3/4 RAGLAN T-SHIRT | M1942: 129900 | N1942: =$N1941 -> 0.9 | O1942: =M1942*(1-N1942) -> 12990 | P1942: =$P$2 -> PERCENTAGE
A1943: =$A$2 -> 2023 ALL TSHIRT D90 | B1943: ='2019 ALL N OLDER D95'!$B$2 -> 46121 | C1943: ='2019 ALL N OLDER D95'!$C$2 -> 46127 | D1943: 3260 | E1943: 333 | F1943: 3 | H1943: JAVA DESIGN SENTOSA CV. | I1943: AOS | J1943: 80732203 | K1943: =K1942 -> R3J2S-O | L1943: 3/4 RAGLAN T-SHIRT PRINT THEME SPACE TECHNO - ONE LIFE R3J2S-O:CHARCOAL:XL:GRAPHIC:3/4 RAGLAN T-SHIR | M1943: 129900 | N1943: =$N1942 -> 0.9 | O1943: =M1943*(1-N1943) -> 12990 | P1943: =$P$2 -> PERCENTAGE
A1944: =$A$2 -> 2023 ALL TSHIRT D90 | B1944: ='2019 ALL N OLDER D95'!$B$2 -> 46121 | C1944: ='2019 ALL N OLDER D95'!$C$2 -> 46127 | D1944: 3260 | E1944: 333 | F1944: 3 | H1944: JAVA DESIGN SENTOSA CV. | I1944: AOS | J1944: 80732132 | K1944: =K1943 -> R3J2S-O | L1944: 3/4 RAGLAN T-SHIRT PRINT THEME SPACE TECHNO - ONE LIFE R3J2S-O:MUSTARD:S:GRAPHIC:3/4 RAGLAN T-SHIRT | M1944: 129900 | N1944: =$N1943 -> 0.9 | O1944: =M1944*(1-N1944) -> 12990 | P1944: =$P$2 -> PERCENTAGE
A1945: =$A$2 -> 2023 ALL TSHIRT D90 | B1945: ='2019 ALL N OLDER D95'!$B$2 -> 46121 | C1945: ='2019 ALL N OLDER D95'!$C$2 -> 46127 | D1945: 3260 | E1945: 333 | F1945: 3 | H1945: JAVA DESIGN SENTOSA CV. | I1945: AOS | J1945: 80732141 | K1945: =K1944 -> R3J2S-O | L1945: 3/4 RAGLAN T-SHIRT PRINT THEME SPACE TECHNO - ONE LIFE R3J2S-O:MUSTARD:M:GRAPHIC:3/4 RAGLAN T-SHIRT | M1945: 129900 | N1945: =$N1944 -> 0.9 | O1945: =M1945*(1-N1945) -> 12990 | P1945: =$P$2 -> PERCENTAGE
A1946: =$A$2 -> 2023 ALL TSHIRT D90 | B1946: ='2019 ALL N OLDER D95'!$B$2 -> 46121 | C1946: ='2019 ALL N OLDER D95'!$C$2 -> 46127 | D1946: 3260 | E1946: 333 | F1946: 3 | H1946: JAVA DESIGN SENTOSA CV. | I1946: AOS | J1946: 80732150 | K1946: =K1945 -> R3J2S-O | L1946: 3/4 RAGLAN T-SHIRT PRINT THEME SPACE TECHNO - ONE LIFE R3J2S-O:MUSTARD:L:GRAPHIC:3/4 RAGLAN T-SHIRT | M1946: 129900 | N1946: =$N1945 -> 0.9 | O1946: =M1946*(1-N1946) -> 12990 | P1946: =$P$2 -> PERCENTAGE
A1947: =$A$2 -> 2023 ALL TSHIRT D90 | B1947: ='2019 ALL N OLDER D95'!$B$2 -> 46121 | C1947: ='2019 ALL N OLDER D95'!$C$2 -> 46127 | D1947: 3260 | E1947: 333 | F1947: 3 | H1947: JAVA DESIGN SENTOSA CV. | I1947: AOS | J1947: 80732169 | K1947: =K1946 -> R3J2S-O | L1947: 3/4 RAGLAN T-SHIRT PRINT THEME SPACE TECHNO - ONE LIFE R3J2S-O:MUSTARD:XL:GRAPHIC:3/4 RAGLAN T-SHIRT | M1947: 129900 | N1947: =$N1946 -> 0.9 | O1947: =M1947*(1-N1947) -> 12990 | P1947: =$P$2 -> PERCENTAGE

Sheet 2023 2024 BL UT GWP MIN BUY 2 
A1: ACARA | B1: FROM DATE | C1: TO DATE | D1: DEPT | E1: WORLD | F1: DIVISION | G1: CLASS | H1: SUPPLIER | I1: BRAND | J1: SKU | K1: ARTICLE | L1: DESCRIPTION | M1: HARGA NORMAL | N1: DISKON | O1: HARGA PROMO | P1: DISCOUNT TYPE
A2: 2023 2024 BUMILANGIT/ULTRAMEN GWP MIN BUY 2 PCS T-SHIRT AOS | B2: ='2019 ALL N OLDER D95'!$B$2 -> 46121 | C2: ='2019 ALL N OLDER D95'!$C$2 -> 46127 | D2: 3260 | E2: 333 | F2: 3 | G2: 4 | H2: JAVA DESIGN | I2: AOS | J2: 83454053 | K2: BLTJ7-01 | L2: SS T-SHIRT BUMILANGIT - JAGOAN INDONESIA BLTJ7-01:MAROON:S:GRAPHIC:SS T-SHIRT | M2: 129900 | N2: GWP | O2: 1 | P2: GWP
A3: =$A$2 -> 2023 2024 BUMILANGIT/ULTRAMEN GWP MIN BUY 2 PCS T-SHIRT AOS | B3: ='2019 ALL N OLDER D95'!$B$2 -> 46121 | C3: ='2019 ALL N OLDER D95'!$C$2 -> 46127 | D3: 3260 | E3: 333 | F3: 3 | G3: 4 | H3: JAVA DESIGN | I3: AOS | J3: 83454062 | K3: BLTJ7-01 | L3: SS T-SHIRT BUMILANGIT - JAGOAN INDONESIA BLTJ7-01:MAROON:M:GRAPHIC:SS T-SHIRT | M3: 129900 | N3: =$N$2 -> GWP | O3: =$O$2 -> 1 | P3: =P2 -> GWP
A4: =$A$2 -> 2023 2024 BUMILANGIT/ULTRAMEN GWP MIN BUY 2 PCS T-SHIRT AOS | B4: ='2019 ALL N OLDER D95'!$B$2 -> 46121 | C4: ='2019 ALL N OLDER D95'!$C$2 -> 46127 | D4: 3260 | E4: 333 | F4: 3 | G4: 4 | H4: JAVA DESIGN | I4: AOS | J4: 83454071 | K4: BLTJ7-01 | L4: SS T-SHIRT BUMILANGIT - JAGOAN INDONESIA BLTJ7-01:MAROON:L:GRAPHIC:SS T-SHIRT | M4: 129900 | N4: =$N$2 -> GWP | O4: =$O$2 -> 1 | P4: =P3 -> GWP
A5: =$A$2 -> 2023 2024 BUMILANGIT/ULTRAMEN GWP MIN BUY 2 PCS T-SHIRT AOS | B5: ='2019 ALL N OLDER D95'!$B$2 -> 46121 | C5: ='2019 ALL N OLDER D95'!$C$2 -> 46127 | D5: 3260 | E5: 333 | F5: 3 | G5: 4 | H5: JAVA DESIGN | I5: AOS | J5: 83454080 | K5: BLTJ7-01 | L5: SS T-SHIRT BUMILANGIT - JAGOAN INDONESIA BLTJ7-01:MAROON:XL:GRAPHIC:SS T-SHIRT | M5: 129900 | N5: =$N$2 -> GWP | O5: =$O$2 -> 1 | P5: =P4 -> GWP
A6: =$A$2 -> 2023 2024 BUMILANGIT/ULTRAMEN GWP MIN BUY 2 PCS T-SHIRT AOS | B6: ='2019 ALL N OLDER D95'!$B$2 -> 46121 | C6: ='2019 ALL N OLDER D95'!$C$2 -> 46127 | D6: 3260 | E6: 333 | F6: 3 | G6: 4 | H6: JAVA DESIGN | I6: AOS | J6: 83454099 | K6: BLTJ7-02 | L6: SS T-SHIRT BUMILANGIT - PATRIOT INDONESIA BLTJ7-02:NAVY BLUE:S:GRAPHIC:SS T-SHIRT | M6: 129900 | N6: =$N$2 -> GWP | O6: =$O$2 -> 1 | P6: =P5 -> GWP
A7: =$A$2 -> 2023 2024 BUMILANGIT/ULTRAMEN GWP MIN BUY 2 PCS T-SHIRT AOS | B7: ='2019 ALL N OLDER D95'!$B$2 -> 46121 | C7: ='2019 ALL N OLDER D95'!$C$2 -> 46127 | D7: 3260 | E7: 333 | F7: 3 | G7: 4 | H7: JAVA DESIGN | I7: AOS | J7: 83454106 | K7: BLTJ7-02 | L7: SS T-SHIRT BUMILANGIT - PATRIOT INDONESIA BLTJ7-02:NAVY BLUE:M:GRAPHIC:SS T-SHIRT | M7: 129900 | N7: =$N$2 -> GWP | O7: =$O$2 -> 1 | P7: =P6 -> GWP
A8: =$A$2 -> 2023 2024 BUMILANGIT/ULTRAMEN GWP MIN BUY 2 PCS T-SHIRT AOS | B8: ='2019 ALL N OLDER D95'!$B$2 -> 46121 | C8: ='2019 ALL N OLDER D95'!$C$2 -> 46127 | D8: 3260 | E8: 333 | F8: 3 | G8: 4 | H8: JAVA DESIGN | I8: AOS | J8: 83454115 | K8: BLTJ7-02 | L8: SS T-SHIRT BUMILANGIT - PATRIOT INDONESIA BLTJ7-02:NAVY BLUE:L:GRAPHIC:SS T-SHIRT | M8: 129900 | N8: =$N$2 -> GWP | O8: =$O$2 -> 1 | P8: =P7 -> GWP
A9: =$A$2 -> 2023 2024 BUMILANGIT/ULTRAMEN GWP MIN BUY 2 PCS T-SHIRT AOS | B9: ='2019 ALL N OLDER D95'!$B$2 -> 46121 | C9: ='2019 ALL N OLDER D95'!$C$2 -> 46127 | D9: 3260 | E9: 333 | F9: 3 | G9: 4 | H9: JAVA DESIGN | I9: AOS | J9: 83454124 | K9: BLTJ7-02 | L9: SS T-SHIRT BUMILANGIT - PATRIOT INDONESIA BLTJ7-02:NAVY BLUE:XL:GRAPHIC:SS T-SHIRT | M9: 129900 | N9: =$N$2 -> GWP | O9: =$O$2 -> 1 | P9: =P8 -> GWP
A10: =$A$2 -> 2023 2024 BUMILANGIT/ULTRAMEN GWP MIN BUY 2 PCS T-SHIRT AOS | B10: ='2019 ALL N OLDER D95'!$B$2 -> 46121 | C10: ='2019 ALL N OLDER D95'!$C$2 -> 46127 | D10: 3260 | E10: 333 | F10: 3 | G10: 4 | H10: JAVA DESIGN | I10: AOS | J10: 83454133 | K10: BLTJ7-03 | L10: SS T-SHIRT BUMILANGIT - 3 PATRIOT BLTJ7-03:WHITE:S:GRAPHIC:SS T-SHIRT | M10: 129900 | N10: =$N$2 -> GWP | O10: =$O$2 -> 1 | P10: =P9 -> GWP
A11: =$A$2 -> 2023 2024 BUMILANGIT/ULTRAMEN GWP MIN BUY 2 PCS T-SHIRT AOS | B11: ='2019 ALL N OLDER D95'!$B$2 -> 46121 | C11: ='2019 ALL N OLDER D95'!$C$2 -> 46127 | D11: 3260 | E11: 333 | F11: 3 | G11: 4 | H11: JAVA DESIGN | I11: AOS | J11: 83454142 | K11: BLTJ7-03 | L11: SS T-SHIRT BUMILANGIT - 3 PATRIOT BLTJ7-03:WHITE:M:GRAPHIC:SS T-SHIRT | M11: 129900 | N11: =$N$2 -> GWP | O11: =$O$2 -> 1 | P11: =P10 -> GWP
A12: =$A$2 -> 2023 2024 BUMILANGIT/ULTRAMEN GWP MIN BUY 2 PCS T-SHIRT AOS | B12: ='2019 ALL N OLDER D95'!$B$2 -> 46121 | C12: ='2019 ALL N OLDER D95'!$C$2 -> 46127 | D12: 3260 | E12: 333 | F12: 3 | G12: 4 | H12: JAVA DESIGN | I12: AOS | J12: 83454151 | K12: BLTJ7-03 | L12: SS T-SHIRT BUMILANGIT - 3 PATRIOT BLTJ7-03:WHITE:L:GRAPHIC:SS T-SHIRT | M12: 129900 | N12: =$N$2 -> GWP | O12: =$O$2 -> 1 | P12: =P11 -> GWP
A13: =$A$2 -> 2023 2024 BUMILANGIT/ULTRAMEN GWP MIN BUY 2 PCS T-SHIRT AOS | B13: ='2019 ALL N OLDER D95'!$B$2 -> 46121 | C13: ='2019 ALL N OLDER D95'!$C$2 -> 46127 | D13: 3260 | E13: 333 | F13: 3 | G13: 4 | H13: JAVA DESIGN | I13: AOS | J13: 83454160 | K13: BLTJ7-03 | L13: SS T-SHIRT BUMILANGIT - 3 PATRIOT BLTJ7-03:WHITE:XL:GRAPHIC:SS T-SHIRT | M13: 129900 | N13: =$N$2 -> GWP | O13: =$O$2 -> 1 | P13: =P12 -> GWP
A14: =$A$2 -> 2023 2024 BUMILANGIT/ULTRAMEN GWP MIN BUY 2 PCS T-SHIRT AOS | B14: ='2019 ALL N OLDER D95'!$B$2 -> 46121 | C14: ='2019 ALL N OLDER D95'!$C$2 -> 46127 | D14: 3260 | E14: 333 | F14: 3 | G14: 4 | H14: JAVA DESIGN | I14: AOS | J14: 83454179 | K14: BLTJ7-04 | L14: SS T-SHIRT BUMILANGIT - GARUDA PATRIOT BLTJ7-04:WHITE:S:GRAPHIC:SS T-SHIRT | M14: 129900 | N14: =$N$2 -> GWP | O14: =$O$2 -> 1 | P14: =P13 -> GWP
... A50: =$A$2 -> 2023 2024 BUMILANGIT/ULTRAMEN GWP MIN BUY 2 PCS T-SHIRT AOS | B50: ='2019 ALL N OLDER D95'!$B$2 -> 46121 | C50: ='2019 ALL N OLDER D95'!$C$2 -> 46127 | D50: 3260 | E50: 333 | F50: 3 | G50: 4 | H50: INTAN DUA | I50: AOS | J50: 81926707 | K50: UMTI5-5 | L50: SS T-SHIRT ULTRAMAN BATCH 2 - 5 PRINT 10 COLORS UMTI5-5:NAVY BLUE:S:GRAPHIC:SS T-SHIRT | M50: 129900 | N50: =$N$2 -> GWP | O50: =$O$2 -> 1 | P50: =P49 -> GWP
A51: =$A$2 -> 2023 2024 BUMILANGIT/ULTRAMEN GWP MIN BUY 2 PCS T-SHIRT AOS | B51: ='2019 ALL N OLDER D95'!B3 -> 46121 | C51: ='2019 ALL N OLDER D95'!C3 -> 46127 | D51: 3260 | E51: 333 | F51: 3 | G51: 4 | H51: INTAN DUA | I51: AOS | J51: 81926716 | K51: UMTI5-5 | L51: SS T-SHIRT ULTRAMAN BATCH 2 - 5 PRINT 10 COLORS UMTI5-5:NAVY BLUE:M:GRAPHIC:SS T-SHIRT | M51: 129900 | N51: =$N$2 -> GWP | O51: =$O$2 -> 1 | P51: =P50 -> GWP
A52: =$A$2 -> 2023 2024 BUMILANGIT/ULTRAMEN GWP MIN BUY 2 PCS T-SHIRT AOS | B52: ='2019 ALL N OLDER D95'!B4 -> 46121 | C52: ='2019 ALL N OLDER D95'!C4 -> 46127 | D52: 3260 | E52: 333 | F52: 3 | G52: 4 | H52: INTAN DUA | I52: AOS | J52: 81926725 | K52: UMTI5-5 | L52: SS T-SHIRT ULTRAMAN BATCH 2 - 5 PRINT 10 COLORS UMTI5-5:NAVY BLUE:L:GRAPHIC:SS T-SHIRT | M52: 129900 | N52: =$N$2 -> GWP | O52: =$O$2 -> 1 | P52: =P51 -> GWP
A53: =$A$2 -> 2023 2024 BUMILANGIT/ULTRAMEN GWP MIN BUY 2 PCS T-SHIRT AOS | B53: ='2019 ALL N OLDER D95'!B5 -> 46121 | C53: ='2019 ALL N OLDER D95'!C5 -> 46127 | D53: 3260 | E53: 333 | F53: 3 | G53: 4 | H53: INTAN DUA | I53: AOS | J53: 81926734 | K53: UMTI5-5 | L53: SS T-SHIRT ULTRAMAN BATCH 2 - 5 PRINT 10 COLORS UMTI5-5:NAVY BLUE:XL:GRAPHIC:SS T-SHIRT | M53: 129900 | N53: =$N$2 -> GWP | O53: =$O$2 -> 1 | P53: =P52 -> GWP
A54: =$A$2 -> 2023 2024 BUMILANGIT/ULTRAMEN GWP MIN BUY 2 PCS T-SHIRT AOS | B54: ='2019 ALL N OLDER D95'!B6 -> 46121 | C54: ='2019 ALL N OLDER D95'!C6 -> 46127 | D54: 3260 | E54: 333 | F54: 3 | G54: 4 | H54: INTAN DUA | I54: AOS | J54: 81926743 | K54: UMTI5-6 | L54: SS T-SHIRT ULTRAMAN BATCH 2 - 6 FULLPRINT UMTI5-6:PASTEL GREY:S:PRINT:SS T-SHIRT | M54: 129900 | N54: =$N$2 -> GWP | O54: =$O$2 -> 1 | P54: =P53 -> GWP
A55: =$A$2 -> 2023 2024 BUMILANGIT/ULTRAMEN GWP MIN BUY 2 PCS T-SHIRT AOS | B55: ='2019 ALL N OLDER D95'!B7 -> 46121 | C55: ='2019 ALL N OLDER D95'!C7 -> 46127 | D55: 3260 | E55: 333 | F55: 3 | G55: 4 | H55: INTAN DUA | I55: AOS | J55: 81926752 | K55: UMTI5-6 | L55: SS T-SHIRT ULTRAMAN BATCH 2 - 6 FULLPRINT UMTI5-6:PASTEL GREY:M:PRINT:SS T-SHIRT | M55: 129900 | N55: =$N$2 -> GWP | O55: =$O$2 -> 1 | P55: =P54 -> GWP
A56: =$A$2 -> 2023 2024 BUMILANGIT/ULTRAMEN GWP MIN BUY 2 PCS T-SHIRT AOS | B56: ='2019 ALL N OLDER D95'!B8 -> 46121 | C56: ='2019 ALL N OLDER D95'!C8 -> 46127 | D56: 3260 | E56: 333 | F56: 3 | G56: 4 | H56: INTAN DUA | I56: AOS | J56: 81926761 | K56: UMTI5-6 | L56: SS T-SHIRT ULTRAMAN BATCH 2 - 6 FULLPRINT UMTI5-6:PASTEL GREY:L:PRINT:SS T-SHIRT | M56: 129900 | N56: =$N$2 -> GWP | O56: =$O$2 -> 1 | P56: =P55 -> GWP
A57: =$A$2 -> 2023 2024 BUMILANGIT/ULTRAMEN GWP MIN BUY 2 PCS T-SHIRT AOS | B57: ='2019 ALL N OLDER D95'!B9 -> 46121 | C57: ='2019 ALL N OLDER D95'!C9 -> 46127 | D57: 3260 | E57: 333 | F57: 3 | G57: 4 | H57: INTAN DUA | I57: AOS | J57: 81926770 | K57: UMTI5-6 | L57: SS T-SHIRT ULTRAMAN BATCH 2 - 6 FULLPRINT UMTI5-6:PASTEL GREY:XL:PRINT:SS T-SHIRT | M57: 129900 | N57: =$N$2 -> GWP | O57: =$O$2 -> 1 | P57: =P56 -> GWP
A58: =$A$2 -> 2023 2024 BUMILANGIT/ULTRAMEN GWP MIN BUY 2 PCS T-SHIRT AOS | B58: ='2019 ALL N OLDER D95'!B10 -> 46121 | C58: ='2019 ALL N OLDER D95'!C10 -> 46127 | D58: 3260 | E58: 333 | F58: 3 | G58: 4 | H58: TRIKENCANA | I58: AOS | J58: 81926547 | K58: UMTT5-1 | L58: SS T-SHIRT ULTRAMAN BATCH 2 - 1 BACKPRINT UMTT5-1:BLACK:S:GRAPHIC:SS T-SHIRT | M58: 129900 | N58: =$N$2 -> GWP | O58: =$O$2 -> 1 | P58: =P57 -> GWP
A59: =$A$2 -> 2023 2024 BUMILANGIT/ULTRAMEN GWP MIN BUY 2 PCS T-SHIRT AOS | B59: ='2019 ALL N OLDER D95'!B11 -> 46121 | C59: ='2019 ALL N OLDER D95'!C11 -> 46127 | D59: 3260 | E59: 333 | F59: 3 | G59: 4 | H59: TRIKENCANA | I59: AOS | J59: 81926556 | K59: UMTT5-1 | L59: SS T-SHIRT ULTRAMAN BATCH 2 - 1 BACKPRINT UMTT5-1:BLACK:M:GRAPHIC:SS T-SHIRT | M59: 129900 | N59: =$N$2 -> GWP | O59: =$O$2 -> 1 | P59: =P58 -> GWP
A60: =$A$2 -> 2023 2024 BUMILANGIT/ULTRAMEN GWP MIN BUY 2 PCS T-SHIRT AOS | B60: ='2019 ALL N OLDER D95'!B12 -> 46121 | C60: ='2019 ALL N OLDER D95'!C12 -> 46127 | D60: 3260 | E60: 333 | F60: 3 | G60: 4 | H60: TRIKENCANA | I60: AOS | J60: 81926565 | K60: UMTT5-1 | L60: SS T-SHIRT ULTRAMAN BATCH 2 - 1 BACKPRINT UMTT5-1:BLACK:L:GRAPHIC:SS T-SHIRT | M60: 129900 | N60: =$N$2 -> GWP | O60: =$O$2 -> 1 | P60: =P59 -> GWP
A61: =$A$2 -> 2023 2024 BUMILANGIT/ULTRAMEN GWP MIN BUY 2 PCS T-SHIRT AOS | B61: ='2019 ALL N OLDER D95'!B13 -> 46121 | C61: ='2019 ALL N OLDER D95'!C13 -> 46127 | D61: 3260 | E61: 333 | F61: 3 | G61: 4 | H61: TRIKENCANA | I61: AOS | J61: 81926574 | K61: UMTT5-1 | L61: SS T-SHIRT ULTRAMAN BATCH 2 - 1 BACKPRINT UMTT5-1:BLACK:XL:GRAPHIC:SS T-SHIRT | M61: 129900 | N61: =$N$2 -> GWP | O61: =$O$2 -> 1 | P61: =P60 -> GWP
A62: =$A$2 -> 2023 2024 BUMILANGIT/ULTRAMEN GWP MIN BUY 2 PCS T-SHIRT AOS | B62: ='2019 ALL N OLDER D95'!B14 -> 46121 | C62: ='2019 ALL N OLDER D95'!C14 -> 46127 | D62: 3260 | E62: 333 | F62: 3 | G62: 4 | H62: TRIKENCANA | I62: AOS | J62: 81926627 | K62: UMTT5-3 | L62: SS T-SHIRT ULTRAMAN BATCH 2 - 3 BACKPRINT UMTT5-3:GOLDEN BROWN:S:GRAPHIC:SS T-SHIRT | M62: 129900 | N62: =$N$2 -> GWP | O62: =$O$2 -> 1 | P62: =P61 -> GWP
... A73: =$A$2 -> 2023 2024 BUMILANGIT/ULTRAMEN GWP MIN BUY 2 PCS T-SHIRT AOS | B73: ='2019 ALL N OLDER D95'!B25 -> 46121 | C73: ='2019 ALL N OLDER D95'!C25 -> 46127 | D73: 3260 | E73: 333 | F73: 3 | G73: 4 | H73: TRIKENCANA | I73: AOS | J73: 81926690 | K73: UMTT5-4 | L73: SS T-SHIRT ULTRAMAN BATCH 2 - 4 PRINT DTF UMTT5-4:BLACK:XL:GRAPHIC:SS T-SHIRT | M73: 129900 | N73: =$N$2 -> GWP | O73: =$O$2 -> 1 | P73: =P72 -> GWP
A74: =$A$2 -> 2023 2024 BUMILANGIT/ULTRAMEN GWP MIN BUY 2 PCS T-SHIRT AOS | B74: ='2019 ALL N OLDER D95'!$B$2 -> 46121 | C74: ='2019 ALL N OLDER D95'!$C$2 -> 46127 | D74: 3260 | E74: 333 | F74: 3 | G74: 4 | H74: PUTRA KREASINDO GARMENT PT.-8092 | I74: AOS | J74: 15508373 | K74: BLTP2-1 | L74: SS T-SHIRT BUMILANGIT - 1 JAPAN STYLE BLTP2-1:WHITE:S:GRAPHIC:SS T-SHIRT | M74: 129900 | N74: =$N$2 -> GWP | O74: =$O$2 -> 1 | P74: =P73 -> GWP
A75: =$A$2 -> 2023 2024 BUMILANGIT/ULTRAMEN GWP MIN BUY 2 PCS T-SHIRT AOS | B75: ='2019 ALL N OLDER D95'!$B$2 -> 46121 | C75: ='2019 ALL N OLDER D95'!$C$2 -> 46127 | D75: 3260 | E75: 333 | F75: 3 | G75: 4 | H75: PUTRA KREASINDO GARMENT PT.-8092 | I75: AOS | J75: 15508382 | K75: BLTP2-1 | L75: SS T-SHIRT BUMILANGIT - 1 JAPAN STYLE BLTP2-1:WHITE:M:GRAPHIC:SS T-SHIRT | M75: 129900 | N75: =$N$2 -> GWP | O75: =$O$2 -> 1 | P75: =P74 -> GWP
A76: =$A$2 -> 2023 2024 BUMILANGIT/ULTRAMEN GWP MIN BUY 2 PCS T-SHIRT AOS | B76: ='2019 ALL N OLDER D95'!$B$2 -> 46121 | C76: ='2019 ALL N OLDER D95'!$C$2 -> 46127 | D76: 3260 | E76: 333 | F76: 3 | G76: 4 | H76: PUTRA KREASINDO GARMENT PT.-8092 | I76: AOS | J76: 15508391 | K76: BLTP2-1 | L76: SS T-SHIRT BUMILANGIT - 1 JAPAN STYLE BLTP2-1:WHITE:L:GRAPHIC:SS T-SHIRT | M76: 129900 | N76: =$N$2 -> GWP | O76: =$O$2 -> 1 | P76: =P75 -> GWP
A77: =$A$2 -> 2023 2024 BUMILANGIT/ULTRAMEN GWP MIN BUY 2 PCS T-SHIRT AOS | B77: ='2019 ALL N OLDER D95'!$B$2 -> 46121 | C77: ='2019 ALL N OLDER D95'!$C$2 -> 46127 | D77: 3260 | E77: 333 | F77: 3 | G77: 4 | H77: PUTRA KREASINDO GARMENT PT.-8092 | I77: AOS | J77: 15508408 | K77: BLTP2-1 | L77: SS T-SHIRT BUMILANGIT - 1 JAPAN STYLE BLTP2-1:WHITE:XL:GRAPHIC:SS T-SHIRT | M77: 129900 | N77: =$N$2 -> GWP | O77: =$O$2 -> 1 | P77: =P76 -> GWP
A78: =$A$2 -> 2023 2024 BUMILANGIT/ULTRAMEN GWP MIN BUY 2 PCS T-SHIRT AOS | B78: ='2019 ALL N OLDER D95'!$B$2 -> 46121 | C78: ='2019 ALL N OLDER D95'!$C$2 -> 46127 | D78: 3260 | E78: 333 | F78: 3 | G78: 4 | H78: PUTRA KREASINDO GARMENT PT.-8092 | I78: AOS | J78: 15508417 | K78: BLTP2-2 | L78: SS T-SHIRT BUMILANGIT - 2 GODAM SUPERHERO BLTP2-2:CHARCOAL:S:GRAPHIC:SS T-SHIRT | M78: 129900 | N78: =$N$2 -> GWP | O78: =$O$2 -> 1 | P78: =P77 -> GWP
A79: =$A$2 -> 2023 2024 BUMILANGIT/ULTRAMEN GWP MIN BUY 2 PCS T-SHIRT AOS | B79: ='2019 ALL N OLDER D95'!$B$2 -> 46121 | C79: ='2019 ALL N OLDER D95'!$C$2 -> 46127 | D79: 3260 | E79: 333 | F79: 3 | G79: 4 | H79: PUTRA KREASINDO GARMENT PT.-8092 | I79: AOS | J79: 15508426 | K79: BLTP2-2 | L79: SS T-SHIRT BUMILANGIT - 2 GODAM SUPERHERO BLTP2-2:CHARCOAL:M:GRAPHIC:SS T-SHIRT | M79: 129900 | N79: =$N$2 -> GWP | O79: =$O$2 -> 1 | P79: =P78 -> GWP
A80: =$A$2 -> 2023 2024 BUMILANGIT/ULTRAMEN GWP MIN BUY 2 PCS T-SHIRT AOS | B80: ='2019 ALL N OLDER D95'!$B$2 -> 46121 | C80: ='2019 ALL N OLDER D95'!$C$2 -> 46127 | D80: 3260 | E80: 333 | F80: 3 | G80: 4 | H80: PUTRA KREASINDO GARMENT PT.-8093 | I80: AOS | J80: 15508435 | K80: BLTP2-2 | L80: SS T-SHIRT BUMILANGIT - 2 GODAM SUPERHERO BLTP2-2:CHARCOAL:L:GRAPHIC:SS T-SHIRT | M80: 129900 | N80: =$N$2 -> GWP | O80: =$O$2 -> 1 | P80: =P79 -> GWP
A81: =$A$2 -> 2023 2024 BUMILANGIT/ULTRAMEN GWP MIN BUY 2 PCS T-SHIRT AOS | B81: ='2019 ALL N OLDER D95'!$B$2 -> 46121 | C81: ='2019 ALL N OLDER D95'!$C$2 -> 46127 | D81: 3260 | E81: 333 | F81: 3 | G81: 4 | H81: PUTRA KREASINDO GARMENT PT.-8094 | I81: AOS | J81: 15508444 | K81: BLTP2-2 | L81: SS T-SHIRT BUMILANGIT - 2 GODAM SUPERHERO BLTP2-2:CHARCOAL:XL:GRAPHIC:SS T-SHIRT | M81: 129900 | N81: =$N$2 -> GWP | O81: =$O$2 -> 1 | P81: =P80 -> GWP
A82: =$A$2 -> 2023 2024 BUMILANGIT/ULTRAMEN GWP MIN BUY 2 PCS T-SHIRT AOS | B82: ='2019 ALL N OLDER D95'!$B$2 -> 46121 | C82: ='2019 ALL N OLDER D95'!$C$2 -> 46127 | D82: 3260 | E82: 333 | F82: 3 | G82: 4 | H82: PUTRA KREASINDO GARMENT PT.-8095 | I82: AOS | J82: 15508453 | K82: BLTP2-3 | L82: SS T-SHIRT BUMILANGIT - 3 GODAM BLACK AND WHITE BLTP2-3:BLACK:S:GRAPHIC:SS T-SHIRT | M82: 129900 | N82: =$N$2 -> GWP | O82: =$O$2 -> 1 | P82: =P81 -> GWP
A83: =$A$2 -> 2023 2024 BUMILANGIT/ULTRAMEN GWP MIN BUY 2 PCS T-SHIRT AOS | B83: ='2019 ALL N OLDER D95'!$B$2 -> 46121 | C83: ='2019 ALL N OLDER D95'!$C$2 -> 46127 | D83: 3260 | E83: 333 | F83: 3 | G83: 4 | H83: PUTRA KREASINDO GARMENT PT.-8096 | I83: AOS | J83: 15508462 | K83: BLTP2-3 | L83: SS T-SHIRT BUMILANGIT - 3 GODAM BLACK AND WHITE BLTP2-3:BLACK:M:GRAPHIC:SS T-SHIRT | M83: 129900 | N83: =$N$2 -> GWP | O83: =$O$2 -> 1 | P83: =P82 -> GWP
A84: =$A$2 -> 2023 2024 BUMILANGIT/ULTRAMEN GWP MIN BUY 2 PCS T-SHIRT AOS | B84: ='2019 ALL N OLDER D95'!$B$2 -> 46121 | C84: ='2019 ALL N OLDER D95'!$C$2 -> 46127 | D84: 3260 | E84: 333 | F84: 3 | G84: 4 | H84: PUTRA KREASINDO GARMENT PT.-8097 | I84: AOS | J84: 15508471 | K84: BLTP2-3 | L84: SS T-SHIRT BUMILANGIT - 3 GODAM BLACK AND WHITE BLTP2-3:BLACK:L:GRAPHIC:SS T-SHIRT | M84: 129900 | N84: =$N$2 -> GWP | O84: =$O$2 -> 1 | P84: =P83 -> GWP
A85: =$A$2 -> 2023 2024 BUMILANGIT/ULTRAMEN GWP MIN BUY 2 PCS T-SHIRT AOS | B85: ='2019 ALL N OLDER D95'!$B$2 -> 46121 | C85: ='2019 ALL N OLDER D95'!$C$2 -> 46127 | D85: 3260 | E85: 333 | F85: 3 | G85: 4 | H85: PUTRA KREASINDO GARMENT PT.-8098 | I85: AOS | J85: 15508480 | K85: BLTP2-3 | L85: SS T-SHIRT BUMILANGIT - 3 GODAM BLACK AND WHITE BLTP2-3:BLACK:XL:GRAPHIC:SS T-SHIRT | M85: 129900 | N85: =$N$2 -> GWP | O85: =$O$2 -> 1 | P85: =P84 -> GWP
... A97: =$A$2 -> 2023 2024 BUMILANGIT/ULTRAMEN GWP MIN BUY 2 PCS T-SHIRT AOS | B97: ='2019 ALL N OLDER D95'!$B$2 -> 46121 | C97: ='2019 ALL N OLDER D95'!$C$2 -> 46127 | D97: 3260 | E97: 333 | F97: 3 | G97: 4 | H97: PUTRA KREASINDO GARMENT PT.-8110 | I97: AOS | J97: 15508604 | K97: BLTP2-6 | L97: SS T-SHIRT BUMILANGIT - 6 GODAM LOGO BLTP2-6:BLACK:XL:GRAPHIC:SS T-SHIRT | M97: 129900 | N97: =$N$2 -> GWP | O97: =$O$2 -> 1 | P97: =P96 -> GWP

Sheet 2024 RAGLAN D85
A1: ACARA | B1: FROM DATE | C1: TO DATE | D1: DEPT | E1: WORLD | F1: DIVISION | G1: CLASS | H1: SUPPLIER | I1: BRAND | J1: SKU | K1: ARTICLE | L1: DESCRIPTION | M1: HARGA NORMAL | N1: DISKON | O1: HARGA PROMO | P1: DISCOUNT TYPE
A2: 2024 RAGLAN D85 | B2: ='2019 ALL N OLDER D95'!$B$2 -> 46121 | C2: ='2019 ALL N OLDER D95'!$C$2 -> 46127 | D2: 3260 | E2: 333 | F2: 3 | G2: 3 | H2: JAVA DESIGN SENTOSA CV. | I2: AOS | J2: 15520377 | K2: R3J11-CO | L2: 3/4 RAGLAN T-SHIRT THEME CAMOU - COURAGE R3J11-CO:BROWN SUGAR:S:GRAPHIC:3/4 RAGLAN T-SHIRT | M2: 129900 | N2: 0.85 | O2: =M2*(1-N2) -> 19485 | P2: PERCENTAGE
A3: =$A$2 -> 2024 RAGLAN D85 | B3: ='2019 ALL N OLDER D95'!$B$2 -> 46121 | C3: ='2019 ALL N OLDER D95'!$C$2 -> 46127 | D3: 3260 | E3: 333 | F3: 3 | G3: 3 | H3: JAVA DESIGN SENTOSA CV. | I3: AOS | J3: 15520386 | K3: R3J11-CO | L3: 3/4 RAGLAN T-SHIRT THEME CAMOU - COURAGE R3J11-CO:BROWN SUGAR:M:GRAPHIC:3/4 RAGLAN T-SHIRT | M3: 129900 | N3: =$N$2 -> 0.85 | O3: =O2 -> 19485 | P3: =$P$2 -> PERCENTAGE
A4: =$A$2 -> 2024 RAGLAN D85 | B4: ='2019 ALL N OLDER D95'!$B$2 -> 46121 | C4: ='2019 ALL N OLDER D95'!$C$2 -> 46127 | D4: 3260 | E4: 333 | F4: 3 | G4: 3 | H4: JAVA DESIGN SENTOSA CV. | I4: AOS | J4: 15520395 | K4: R3J11-CO | L4: 3/4 RAGLAN T-SHIRT THEME CAMOU - COURAGE R3J11-CO:BROWN SUGAR:L:GRAPHIC:3/4 RAGLAN T-SHIRT | M4: 129900 | N4: =$N$2 -> 0.85 | O4: =O3 -> 19485 | P4: =$P$2 -> PERCENTAGE
A5: =$A$2 -> 2024 RAGLAN D85 | B5: ='2019 ALL N OLDER D95'!$B$2 -> 46121 | C5: ='2019 ALL N OLDER D95'!$C$2 -> 46127 | D5: 3260 | E5: 333 | F5: 3 | G5: 3 | H5: JAVA DESIGN SENTOSA CV. | I5: AOS | J5: 15520402 | K5: R3J11-CO | L5: 3/4 RAGLAN T-SHIRT THEME CAMOU - COURAGE R3J11-CO:BROWN SUGAR:XL:GRAPHIC:3/4 RAGLAN T-SHIRT | M5: 129900 | N5: =$N$2 -> 0.85 | O5: =O4 -> 19485 | P5: =$P$2 -> PERCENTAGE
A6: =$A$2 -> 2024 RAGLAN D85 | B6: ='2019 ALL N OLDER D95'!$B$2 -> 46121 | C6: ='2019 ALL N OLDER D95'!$C$2 -> 46127 | D6: 3260 | E6: 333 | F6: 3 | G6: 3 | H6: JAVA DESIGN SENTOSA CV. | I6: AOS | J6: 15520411 | K6: R3J11-CO | L6: 3/4 RAGLAN T-SHIRT THEME CAMOU - COURAGE R3J11-CO:KHAKI:S:GRAPHIC:3/4 RAGLAN T-SHIRT | M6: 129900 | N6: =$N$2 -> 0.85 | O6: =O5 -> 19485 | P6: =$P$2 -> PERCENTAGE
A7: =$A$2 -> 2024 RAGLAN D85 | B7: ='2019 ALL N OLDER D95'!$B$2 -> 46121 | C7: ='2019 ALL N OLDER D95'!$C$2 -> 46127 | D7: 3260 | E7: 333 | F7: 3 | G7: 3 | H7: JAVA DESIGN SENTOSA CV. | I7: AOS | J7: 15520420 | K7: R3J11-CO | L7: 3/4 RAGLAN T-SHIRT THEME CAMOU - COURAGE R3J11-CO:KHAKI:M:GRAPHIC:3/4 RAGLAN T-SHIRT | M7: 129900 | N7: =$N$2 -> 0.85 | O7: =O6 -> 19485 | P7: =$P$2 -> PERCENTAGE
A8: =$A$2 -> 2024 RAGLAN D85 | B8: ='2019 ALL N OLDER D95'!$B$2 -> 46121 | C8: ='2019 ALL N OLDER D95'!$C$2 -> 46127 | D8: 3260 | E8: 333 | F8: 3 | G8: 3 | H8: JAVA DESIGN SENTOSA CV. | I8: AOS | J8: 15520439 | K8: R3J11-CO | L8: 3/4 RAGLAN T-SHIRT THEME CAMOU - COURAGE R3J11-CO:KHAKI:L:GRAPHIC:3/4 RAGLAN T-SHIRT | M8: 129900 | N8: =$N$2 -> 0.85 | O8: =O7 -> 19485 | P8: =$P$2 -> PERCENTAGE
A9: =$A$2 -> 2024 RAGLAN D85 | B9: ='2019 ALL N OLDER D95'!$B$2 -> 46121 | C9: ='2019 ALL N OLDER D95'!$C$2 -> 46127 | D9: 3260 | E9: 333 | F9: 3 | G9: 3 | H9: JAVA DESIGN SENTOSA CV. | I9: AOS | J9: 15520448 | K9: R3J11-CO | L9: 3/4 RAGLAN T-SHIRT THEME CAMOU - COURAGE R3J11-CO:KHAKI:XL:GRAPHIC:3/4 RAGLAN T-SHIRT | M9: 129900 | N9: =$N$2 -> 0.85 | O9: =O8 -> 19485 | P9: =$P$2 -> PERCENTAGE
A10: =$A$2 -> 2024 RAGLAN D85 | B10: ='2019 ALL N OLDER D95'!$B$2 -> 46121 | C10: ='2019 ALL N OLDER D95'!$C$2 -> 46127 | D10: 3260 | E10: 333 | F10: 3 | G10: 3 | H10: JAVA DESIGN SENTOSA CV. | I10: AOS | J10: 15520457 | K10: R3J11-SC | L10: 3/4 RAGLAN T-SHIRT THEME CAMOU - STAY COOL R3J11-SC:CACTUS GREEN:S:GRAPHIC:3/4 RAGLAN T-SHIRT | M10: 129900 | N10: =$N$2 -> 0.85 | O10: =O9 -> 19485 | P10: =$P$2 -> PERCENTAGE
A11: =$A$2 -> 2024 RAGLAN D85 | B11: ='2019 ALL N OLDER D95'!$B$2 -> 46121 | C11: ='2019 ALL N OLDER D95'!$C$2 -> 46127 | D11: 3260 | E11: 333 | F11: 3 | G11: 3 | H11: JAVA DESIGN SENTOSA CV. | I11: AOS | J11: 15520475 | K11: R3J11-SC | L11: 3/4 RAGLAN T-SHIRT THEME CAMOU - STAY COOL R3J11-SC:CACTUS GREEN:M:GRAPHIC:3/4 RAGLAN T-SHIRT | M11: 129900 | N11: =$N$2 -> 0.85 | O11: =O10 -> 19485 | P11: =$P$2 -> PERCENTAGE
A12: =$A$2 -> 2024 RAGLAN D85 | B12: ='2019 ALL N OLDER D95'!$B$2 -> 46121 | C12: ='2019 ALL N OLDER D95'!$C$2 -> 46127 | D12: 3260 | E12: 333 | F12: 3 | G12: 3 | H12: JAVA DESIGN SENTOSA CV. | I12: AOS | J12: 15520484 | K12: R3J11-SC | L12: 3/4 RAGLAN T-SHIRT THEME CAMOU - STAY COOL R3J11-SC:CACTUS GREEN:L:GRAPHIC:3/4 RAGLAN T-SHIRT | M12: 129900 | N12: =$N$2 -> 0.85 | O12: =O11 -> 19485 | P12: =$P$2 -> PERCENTAGE
A13: =$A$2 -> 2024 RAGLAN D85 | B13: ='2019 ALL N OLDER D95'!$B$2 -> 46121 | C13: ='2019 ALL N OLDER D95'!$C$2 -> 46127 | D13: 3260 | E13: 333 | F13: 3 | G13: 3 | H13: JAVA DESIGN SENTOSA CV. | I13: AOS | J13: 15520493 | K13: R3J11-SC | L13: 3/4 RAGLAN T-SHIRT THEME CAMOU - STAY COOL R3J11-SC:CACTUS GREEN:XL:GRAPHIC:3/4 RAGLAN T-SHIRT | M13: 129900 | N13: =$N$2 -> 0.85 | O13: =O12 -> 19485 | P13: =$P$2 -> PERCENTAGE
A14: =$A$2 -> 2024 RAGLAN D85 | B14: ='2019 ALL N OLDER D95'!$B$2 -> 46121 | C14: ='2019 ALL N OLDER D95'!$C$2 -> 46127 | D14: 3260 | E14: 333 | F14: 3 | G14: 3 | H14: JAVA DESIGN SENTOSA CV. | I14: AOS | J14: 15520500 | K14: R3J11-SC | L14: 3/4 RAGLAN T-SHIRT THEME CAMOU - STAY COOL R3J11-SC:TAUPE GREY:S:GRAPHIC:3/4 RAGLAN T-SHIRT | M14: 129900 | N14: =$N$2 -> 0.85 | O14: =O13 -> 19485 | P14: =$P$2 -> PERCENTAGE
... A31: =$A$2 -> 2024 RAGLAN D85 | B31: ='2019 ALL N OLDER D95'!$B$2 -> 46121 | C31: ='2019 ALL N OLDER D95'!$C$2 -> 46127 | D31: 3260 | E31: 333 | F31: 3 | G31: 3 | H31: JAVA DESIGN SENTOSA CV. | I31: AOS | J31: 16241033 | K31: R3J2-NYC | L31: 3/4 RAGLAN T-SHIRT THEME CITY - NEW YORK R3J2-NYC:SAND:XL:GRAPHIC:3/4 RAGLAN T-SHIRT | M31: 129900 | N31: =$N$2 -> 0.85 | O31: =O30 -> 19485 | P31: =$P$2 -> PERCENTAGE

Sheet 2024 ALL EXC KI RAGLAN D80
A1: ACARA | B1: FROM DATE | C1: TO DATE | D1: DEPT | E1: WORLD | F1: DIVISION | G1: CLASS | H1: SUPPLIER | I1: BRAND | J1: SKU | K1: ARTICLE | L1: DESCRIPTION | M1: HARGA NORMAL | N1: DISKON | O1: HARGA PROMO | P1: DISCOUNT TYPE
A2: 2024 ALL T-SHIRT EXC KI & RAGLAN D80 | B2: ='2019 ALL N OLDER D95'!$B$2 -> 46121 | C2: ='2019 ALL N OLDER D95'!$C$2 -> 46127 | D2: 3260 | E2: 333 | F2: 3 | G2: 1 | H2: FECEKRAN SANDANG JAYA PT.-81235 | I2: AOS | J2: 15020505 | K2: TF1FT-BD | L2: SS T-SHIRT PRINT THEME FUN PICT AND TEXT - BETTER DAYS TF1FT-BD:KHAKI:S:GRAPHIC:SS T-SHIRT | M2: 109900 | N2: 0.8 | O2: =M2*(1-N2) -> 21980 | P2: PERCENTAGE
A3: =$A$2 -> 2024 ALL T-SHIRT EXC KI & RAGLAN D80 | B3: ='2019 ALL N OLDER D95'!$B$2 -> 46121 | C3: ='2019 ALL N OLDER D95'!$C$2 -> 46127 | D3: 3260 | E3: 333 | F3: 3 | G3: 1 | H3: FECEKRAN SANDANG JAYA PT.-81235 | I3: AOS | J3: 15020514 | K3: TF1FT-BD | L3: SS T-SHIRT PRINT THEME FUN PICT AND TEXT - BETTER DAYS TF1FT-BD:KHAKI:M:GRAPHIC:SS T-SHIRT | M3: 109900 | N3: =$N$2 -> 0.8 | O3: =$O$2 -> 21980 | P3: =$P$2 -> PERCENTAGE
A4: =$A$2 -> 2024 ALL T-SHIRT EXC KI & RAGLAN D80 | B4: ='2019 ALL N OLDER D95'!$B$2 -> 46121 | C4: ='2019 ALL N OLDER D95'!$C$2 -> 46127 | D4: 3260 | E4: 333 | F4: 3 | G4: 1 | H4: FECEKRAN SANDANG JAYA PT.-81235 | I4: AOS | J4: 15020523 | K4: TF1FT-BD | L4: SS T-SHIRT PRINT THEME FUN PICT AND TEXT - BETTER DAYS TF1FT-BD:KHAKI:L:GRAPHIC:SS T-SHIRT | M4: 109900 | N4: =$N$2 -> 0.8 | O4: =$O$2 -> 21980 | P4: =$P$2 -> PERCENTAGE
A5: =$A$2 -> 2024 ALL T-SHIRT EXC KI & RAGLAN D80 | B5: ='2019 ALL N OLDER D95'!$B$2 -> 46121 | C5: ='2019 ALL N OLDER D95'!$C$2 -> 46127 | D5: 3260 | E5: 333 | F5: 3 | G5: 1 | H5: FECEKRAN SANDANG JAYA PT.-81235 | I5: AOS | J5: 15020532 | K5: TF1FT-BD | L5: SS T-SHIRT PRINT THEME FUN PICT AND TEXT - BETTER DAYS TF1FT-BD:KHAKI:XL:GRAPHIC:SS T-SHIRT | M5: 109900 | N5: =$N$2 -> 0.8 | O5: =$O$2 -> 21980 | P5: =$P$2 -> PERCENTAGE
A6: =$A$2 -> 2024 ALL T-SHIRT EXC KI & RAGLAN D80 | B6: ='2019 ALL N OLDER D95'!$B$2 -> 46121 | C6: ='2019 ALL N OLDER D95'!$C$2 -> 46127 | D6: 3260 | E6: 333 | F6: 3 | G6: 1 | H6: FECEKRAN SANDANG JAYA PT.-81235 | I6: AOS | J6: 15020541 | K6: TF1FT-NO | L6: SS T-SHIRT PRINT THEME FUN PICT AND TEXT - NO JUSTICE NO PEACE TF1FT-NO:WHITE:S:GRAPHIC:SS T-SHIRT | M6: 109900 | N6: =$N$2 -> 0.8 | O6: =$O$2 -> 21980 | P6: =$P$2 -> PERCENTAGE
A7: =$A$2 -> 2024 ALL T-SHIRT EXC KI & RAGLAN D80 | B7: ='2019 ALL N OLDER D95'!$B$2 -> 46121 | C7: ='2019 ALL N OLDER D95'!$C$2 -> 46127 | D7: 3260 | E7: 333 | F7: 3 | G7: 1 | H7: FECEKRAN SANDANG JAYA PT.-81235 | I7: AOS | J7: 15020550 | K7: TF1FT-NO | L7: SS T-SHIRT PRINT THEME FUN PICT AND TEXT - NO JUSTICE NO PEACE TF1FT-NO:WHITE:M:GRAPHIC:SS T-SHIRT | M7: 109900 | N7: =$N$2 -> 0.8 | O7: =$O$2 -> 21980 | P7: =$P$2 -> PERCENTAGE
A8: =$A$2 -> 2024 ALL T-SHIRT EXC KI & RAGLAN D80 | B8: ='2019 ALL N OLDER D95'!$B$2 -> 46121 | C8: ='2019 ALL N OLDER D95'!$C$2 -> 46127 | D8: 3260 | E8: 333 | F8: 3 | G8: 1 | H8: FECEKRAN SANDANG JAYA PT.-81235 | I8: AOS | J8: 15020569 | K8: TF1FT-NO | L8: SS T-SHIRT PRINT THEME FUN PICT AND TEXT - NO JUSTICE NO PEACE TF1FT-NO:WHITE:L:GRAPHIC:SS T-SHIRT | M8: 109900 | N8: =$N$2 -> 0.8 | O8: =$O$2 -> 21980 | P8: =$P$2 -> PERCENTAGE
A9: =$A$2 -> 2024 ALL T-SHIRT EXC KI & RAGLAN D80 | B9: ='2019 ALL N OLDER D95'!$B$2 -> 46121 | C9: ='2019 ALL N OLDER D95'!$C$2 -> 46127 | D9: 3260 | E9: 333 | F9: 3 | G9: 1 | H9: FECEKRAN SANDANG JAYA PT.-81235 | I9: AOS | J9: 15020578 | K9: TF1FT-NO | L9: SS T-SHIRT PRINT THEME FUN PICT AND TEXT - NO JUSTICE NO PEACE TF1FT-NO:WHITE:XL:GRAPHIC:SS T-SHIRT | M9: 109900 | N9: =$N$2 -> 0.8 | O9: =$O$2 -> 21980 | P9: =$P$2 -> PERCENTAGE
A10: =$A$2 -> 2024 ALL T-SHIRT EXC KI & RAGLAN D80 | B10: ='2019 ALL N OLDER D95'!$B$2 -> 46121 | C10: ='2019 ALL N OLDER D95'!$C$2 -> 46127 | D10: 3260 | E10: 333 | F10: 3 | G10: 1 | H10: FECEKRAN SANDANG JAYA PT.-81235 | I10: AOS | J10: 15020587 | K10: TF1FT-DO | L10: SS T-SHIRT PRINT THEME FUN PICT AND TEXT - DO ANYTHING TF1FT-DO:BLACK:S:GRAPHIC:SS T-SHIRT | M10: 109900 | N10: =$N$2 -> 0.8 | O10: =$O$2 -> 21980 | P10: =$P$2 -> PERCENTAGE
A11: =$A$2 -> 2024 ALL T-SHIRT EXC KI & RAGLAN D80 | B11: ='2019 ALL N OLDER D95'!$B$2 -> 46121 | C11: ='2019 ALL N OLDER D95'!$C$2 -> 46127 | D11: 3260 | E11: 333 | F11: 3 | G11: 1 | H11: FECEKRAN SANDANG JAYA PT.-81235 | I11: AOS | J11: 15020596 | K11: TF1FT-DO | L11: SS T-SHIRT PRINT THEME FUN PICT AND TEXT - DO ANYTHING TF1FT-DO:BLACK:M:GRAPHIC:SS T-SHIRT | M11: 109900 | N11: =$N$2 -> 0.8 | O11: =$O$2 -> 21980 | P11: =$P$2 -> PERCENTAGE
A12: =$A$2 -> 2024 ALL T-SHIRT EXC KI & RAGLAN D80 | B12: ='2019 ALL N OLDER D95'!$B$2 -> 46121 | C12: ='2019 ALL N OLDER D95'!$C$2 -> 46127 | D12: 3260 | E12: 333 | F12: 3 | G12: 1 | H12: FECEKRAN SANDANG JAYA PT.-81235 | I12: AOS | J12: 15020603 | K12: TF1FT-DO | L12: SS T-SHIRT PRINT THEME FUN PICT AND TEXT - DO ANYTHING TF1FT-DO:BLACK:L:GRAPHIC:SS T-SHIRT | M12: 109900 | N12: =$N$2 -> 0.8 | O12: =$O$2 -> 21980 | P12: =$P$2 -> PERCENTAGE
A13: =$A$2 -> 2024 ALL T-SHIRT EXC KI & RAGLAN D80 | B13: ='2019 ALL N OLDER D95'!$B$2 -> 46121 | C13: ='2019 ALL N OLDER D95'!$C$2 -> 46127 | D13: 3260 | E13: 333 | F13: 3 | G13: 1 | H13: FECEKRAN SANDANG JAYA PT.-81235 | I13: AOS | J13: 15020612 | K13: TF1FT-DO | L13: SS T-SHIRT PRINT THEME FUN PICT AND TEXT - DO ANYTHING TF1FT-DO:BLACK:XL:GRAPHIC:SS T-SHIRT | M13: 109900 | N13: =$N$2 -> 0.8 | O13: =$O$2 -> 21980 | P13: =$P$2 -> PERCENTAGE
A14: =$A$2 -> 2024 ALL T-SHIRT EXC KI & RAGLAN D80 | B14: ='2019 ALL N OLDER D95'!$B$2 -> 46121 | C14: ='2019 ALL N OLDER D95'!$C$2 -> 46127 | D14: 3260 | E14: 333 | F14: 3 | G14: 1 | H14: FECEKRAN SANDANG JAYA PT.-81235 | I14: AOS | J14: 15020621 | K14: TFPFAN-1 | L14: SS T-SHIRT PHOTOPRINT THEME ANIME FECEKRAN - 1 TFPFAN-1:BLACK:S:GRAPHIC:SS T-SHIRT | M14: 109900 | N14: =$N$2 -> 0.8 | O14: =$O$2 -> 21980 | P14: =$P$2 -> PERCENTAGE
... A759: =$A$2 -> 2024 ALL T-SHIRT EXC KI & RAGLAN D80 | B759: ='2019 ALL N OLDER D95'!$B$2 -> 46121 | C759: ='2019 ALL N OLDER D95'!$C$2 -> 46127 | D759: 3260 | E759: 333 | F759: 3 | G759: 4 | H759: JAVA DESIGN SENTOSA CV. | I759: AOS | J759: 16182900 | K759: WBTB224-6 | L759: SS T-SHIRT WB BATMAN ANNIVERSARY - 6 WBTB224-6:BLACK:XL:GRAPHIC:SS T-SHIRT | M759: 129900 | N759: =$N$2 -> 0.8 | O759: =$O$2 -> 21980 | P759: =$P$2 -> PERCENTAGE
A760: =$A$2 -> 2024 ALL T-SHIRT EXC KI & RAGLAN D80 | B760: ='2019 ALL N OLDER D95'!$B$2 -> 46121 | C760: ='2019 ALL N OLDER D95'!$C$2 -> 46127 | D760: 3260 | E760: 333 | F760: 3 | G760: 1 | H760: JAVA DESIGN SENTOSA CV. | I760: AOS | J760: 16961023 | K760: TJ4SU-SV | L760: SS T-SHIRT PRINT THEME SUMMER - SURF VIBES TJ4SU-SV:TEAL:S:GRAPHIC:SS T-SHIRT | M760: 109900 | N760: =$N$2 -> 0.8 | O760: =$O$2 -> 21980 | P760: =$P$2 -> PERCENTAGE
A761: =$A$2 -> 2024 ALL T-SHIRT EXC KI & RAGLAN D80 | B761: ='2019 ALL N OLDER D95'!$B$2 -> 46121 | C761: ='2019 ALL N OLDER D95'!$C$2 -> 46127 | D761: 3260 | E761: 333 | F761: 3 | G761: 1 | H761: JAVA DESIGN SENTOSA CV. | I761: AOS | J761: 16961032 | K761: TJ4SU-SV | L761: SS T-SHIRT PRINT THEME SUMMER - SURF VIBES TJ4SU-SV:TEAL:M:GRAPHIC:SS T-SHIRT | M761: 109900 | N761: =$N$2 -> 0.8 | O761: =$O$2 -> 21980 | P761: =$P$2 -> PERCENTAGE
A762: =$A$2 -> 2024 ALL T-SHIRT EXC KI & RAGLAN D80 | B762: ='2019 ALL N OLDER D95'!$B$2 -> 46121 | C762: ='2019 ALL N OLDER D95'!$C$2 -> 46127 | D762: 3260 | E762: 333 | F762: 3 | G762: 1 | H762: JAVA DESIGN SENTOSA CV. | I762: AOS | J762: 16961041 | K762: TJ4SU-SV | L762: SS T-SHIRT PRINT THEME SUMMER - SURF VIBES TJ4SU-SV:TEAL:L:GRAPHIC:SS T-SHIRT | M762: 109900 | N762: =$N$2 -> 0.8 | O762: =$O$2 -> 21980 | P762: =$P$2 -> PERCENTAGE
A763: =$A$2 -> 2024 ALL T-SHIRT EXC KI & RAGLAN D80 | B763: ='2019 ALL N OLDER D95'!$B$2 -> 46121 | C763: ='2019 ALL N OLDER D95'!$C$2 -> 46127 | D763: 3260 | E763: 333 | F763: 3 | G763: 1 | H763: JAVA DESIGN SENTOSA CV. | I763: AOS | J763: 16961050 | K763: TJ4SU-SV | L763: SS T-SHIRT PRINT THEME SUMMER - SURF VIBES TJ4SU-SV:TEAL:XL:GRAPHIC:SS T-SHIRT | M763: 109900 | N763: =$N$2 -> 0.8 | O763: =$O$2 -> 21980 | P763: =$P$2 -> PERCENTAGE
A764: =$A$2 -> 2024 ALL T-SHIRT EXC KI & RAGLAN D80 | B764: ='2019 ALL N OLDER D95'!$B$2 -> 46121 | C764: ='2019 ALL N OLDER D95'!$C$2 -> 46127 | D764: 3260 | E764: 333 | F764: 3 | G764: 1 | H764: JAVA DESIGN SENTOSA CV. | I764: AOS | J764: 16961112 | K764: TJ4SU-BC | L764: SS T-SHIRT PRINT THEME SUMMER - BEACH CLUB TJ4SU-BC:BLACK:S:GRAPHIC:SS T-SHIRT | M764: 109900 | N764: =$N$2 -> 0.8 | O764: =$O$2 -> 21980 | P764: =$P$2 -> PERCENTAGE
A765: =$A$2 -> 2024 ALL T-SHIRT EXC KI & RAGLAN D80 | B765: ='2019 ALL N OLDER D95'!$B$2 -> 46121 | C765: ='2019 ALL N OLDER D95'!$C$2 -> 46127 | D765: 3260 | E765: 333 | F765: 3 | G765: 1 | H765: JAVA DESIGN SENTOSA CV. | I765: AOS | J765: 16961121 | K765: TJ4SU-BC | L765: SS T-SHIRT PRINT THEME SUMMER - BEACH CLUB TJ4SU-BC:BLACK:M:GRAPHIC:SS T-SHIRT | M765: 109900 | N765: =$N$2 -> 0.8 | O765: =$O$2 -> 21980 | P765: =$P$2 -> PERCENTAGE
A766: =$A$2 -> 2024 ALL T-SHIRT EXC KI & RAGLAN D80 | B766: ='2019 ALL N OLDER D95'!$B$2 -> 46121 | C766: ='2019 ALL N OLDER D95'!$C$2 -> 46127 | D766: 3260 | E766: 333 | F766: 3 | G766: 1 | H766: JAVA DESIGN SENTOSA CV. | I766: AOS | J766: 16961130 | K766: TJ4SU-BC | L766: SS T-SHIRT PRINT THEME SUMMER - BEACH CLUB TJ4SU-BC:BLACK:L:GRAPHIC:SS T-SHIRT | M766: 109900 | N766: =$N$2 -> 0.8 | O766: =$O$2 -> 21980 | P766: =$P$2 -> PERCENTAGE
A767: =$A$2 -> 2024 ALL T-SHIRT EXC KI & RAGLAN D80 | B767: ='2019 ALL N OLDER D95'!$B$2 -> 46121 | C767: ='2019 ALL N OLDER D95'!$C$2 -> 46127 | D767: 3260 | E767: 333 | F767: 3 | G767: 1 | H767: JAVA DESIGN SENTOSA CV. | I767: AOS | J767: 16961149 | K767: TJ4SU-BC | L767: SS T-SHIRT PRINT THEME SUMMER - BEACH CLUB TJ4SU-BC:BLACK:XL:GRAPHIC:SS T-SHIRT | M767: 109900 | N767: =$N$2 -> 0.8 | O767: =$O$2 -> 21980 | P767: =$P$2 -> PERCENTAGE
A768: =$A$2 -> 2024 ALL T-SHIRT EXC KI & RAGLAN D80 | B768: ='2019 ALL N OLDER D95'!$B$2 -> 46121 | C768: ='2019 ALL N OLDER D95'!$C$2 -> 46127 | D768: 3260 | E768: 333 | F768: 3 | G768: 1 | H768: JAVA DESIGN SENTOSA CV. | I768: AOS | J768: 16961158 | K768: TJ4SU-AH | L768: SS T-SHIRT PRINT THEME SUMMER - BETTER DAYS AHEAD TJ4SU-AH:DARK JADE:S:GRAPHIC:SS T-SHIRT | M768: 109900 | N768: =$N$2 -> 0.8 | O768: =$O$2 -> 21980 | P768: =$P$2 -> PERCENTAGE
A769: =$A$2 -> 2024 ALL T-SHIRT EXC KI & RAGLAN D80 | B769: ='2019 ALL N OLDER D95'!$B$2 -> 46121 | C769: ='2019 ALL N OLDER D95'!$C$2 -> 46127 | D769: 3260 | E769: 333 | F769: 3 | G769: 1 | H769: JAVA DESIGN SENTOSA CV. | I769: AOS | J769: 16961167 | K769: TJ4SU-AH | L769: SS T-SHIRT PRINT THEME SUMMER - BETTER DAYS AHEAD TJ4SU-AH:DARK JADE:M:GRAPHIC:SS T-SHIRT | M769: 109900 | N769: =$N$2 -> 0.8 | O769: =$O$2 -> 21980 | P769: =$P$2 -> PERCENTAGE
A770: =$A$2 -> 2024 ALL T-SHIRT EXC KI & RAGLAN D80 | B770: ='2019 ALL N OLDER D95'!$B$2 -> 46121 | C770: ='2019 ALL N OLDER D95'!$C$2 -> 46127 | D770: 3260 | E770: 333 | F770: 3 | G770: 1 | H770: JAVA DESIGN SENTOSA CV. | I770: AOS | J770: 16961176 | K770: TJ4SU-AH | L770: SS T-SHIRT PRINT THEME SUMMER - BETTER DAYS AHEAD TJ4SU-AH:DARK JADE:L:GRAPHIC:SS T-SHIRT | M770: 109900 | N770: =$N$2 -> 0.8 | O770: =$O$2 -> 21980 | P770: =$P$2 -> PERCENTAGE
A771: =$A$2 -> 2024 ALL T-SHIRT EXC KI & RAGLAN D80 | B771: ='2019 ALL N OLDER D95'!$B$2 -> 46121 | C771: ='2019 ALL N OLDER D95'!$C$2 -> 46127 | D771: 3260 | E771: 333 | F771: 3 | G771: 1 | H771: JAVA DESIGN SENTOSA CV. | I771: AOS | J771: 16961185 | K771: TJ4SU-AH | L771: SS T-SHIRT PRINT THEME SUMMER - BETTER DAYS AHEAD TJ4SU-AH:DARK JADE:XL:GRAPHIC:SS T-SHIRT | M771: 109900 | N771: =$N$2 -> 0.8 | O771: =$O$2 -> 21980 | P771: =$P$2 -> PERCENTAGE
... A1003: =$A$2 -> 2024 ALL T-SHIRT EXC KI & RAGLAN D80 | B1003: ='2019 ALL N OLDER D95'!$B$2 -> 46121 | C1003: ='2019 ALL N OLDER D95'!$C$2 -> 46127 | D1003: 3260 | E1003: 333 | F1003: 3 | G1003: 4 | H1003: PUTRA KREASINDO GARMENT PT.-8092 | I1003: AOS | J1003: 15392739 | K1003: WBTT-JS6 | L1003: SS T-SHIRT WB TOM AND JERRY - CHILLIN VIBES WBTT-JS6 | M1003: 129900 | N1003: =$N$2 -> 0.8 | O1003: =$O$2 -> 21980 | P1003: =$P$2 -> PERCENTAGE
A1004: =$A$2 -> 2024 ALL T-SHIRT EXC KI & RAGLAN D80 | B1004: ='2019 ALL N OLDER D95'!$B$2 -> 46121 | C1004: ='2019 ALL N OLDER D95'!$C$2 -> 46127 | D1004: 3260 | E1004: 333 | F1004: 3 | G1004: 1 | H1004: SAHABAT GARMINDO PT- 81461 | I1004: AOS | J1004: 15130539 | K1004: LEB24-01 | L1004: SS KOKO MUSLIM 2024 01 - 2 PANELS EMBRO LEB24-01:TAUPE GREY:S:PRINT:SS KOKO | M1004: 179900 | N1004: =$N$2 -> 0.8 | O1004: =$O$2 -> 21980 | P1004: =$P$2 -> PERCENTAGE
A1005: =$A$2 -> 2024 ALL T-SHIRT EXC KI & RAGLAN D80 | B1005: ='2019 ALL N OLDER D95'!$B$2 -> 46121 | C1005: ='2019 ALL N OLDER D95'!$C$2 -> 46127 | D1005: 3260 | E1005: 333 | F1005: 3 | G1005: 1 | H1005: SAHABAT GARMINDO PT- 81462 | I1005: AOS | J1005: 15130548 | K1005: LEB24-01 | L1005: SS KOKO MUSLIM 2024 01 - 2 PANELS EMBRO LEB24-01:TAUPE GREY:M:PRINT:SS KOKO | M1005: 179900 | N1005: =$N$2 -> 0.8 | O1005: =$O$2 -> 21980 | P1005: =$P$2 -> PERCENTAGE
A1006: =$A$2 -> 2024 ALL T-SHIRT EXC KI & RAGLAN D80 | B1006: ='2019 ALL N OLDER D95'!$B$2 -> 46121 | C1006: ='2019 ALL N OLDER D95'!$C$2 -> 46127 | D1006: 3260 | E1006: 333 | F1006: 3 | G1006: 1 | H1006: SAHABAT GARMINDO PT- 81463 | I1006: AOS | J1006: 15130557 | K1006: LEB24-01 | L1006: SS KOKO MUSLIM 2024 01 - 2 PANELS EMBRO LEB24-01:TAUPE GREY:L:PRINT:SS KOKO | M1006: 179900 | N1006: =$N$2 -> 0.8 | O1006: =$O$2 -> 21980 | P1006: =$P$2 -> PERCENTAGE
A1007: =$A$2 -> 2024 ALL T-SHIRT EXC KI & RAGLAN D80 | B1007: ='2019 ALL N OLDER D95'!$B$2 -> 46121 | C1007: ='2019 ALL N OLDER D95'!$C$2 -> 46127 | D1007: 3260 | E1007: 333 | F1007: 3 | G1007: 1 | H1007: SAHABAT GARMINDO PT- 81464 | I1007: AOS | J1007: 15130566 | K1007: LEB24-01 | L1007: SS KOKO MUSLIM 2024 01 - 2 PANELS EMBRO LEB24-01:TAUPE GREY:XL:PRINT:SS KOKO | M1007: 179900 | N1007: =$N$2 -> 0.8 | O1007: =$O$2 -> 21980 | P1007: =$P$2 -> PERCENTAGE
A1008: =$A$2 -> 2024 ALL T-SHIRT EXC KI & RAGLAN D80 | B1008: ='2019 ALL N OLDER D95'!$B$2 -> 46121 | C1008: ='2019 ALL N OLDER D95'!$C$2 -> 46127 | D1008: 3260 | E1008: 333 | F1008: 3 | G1008: 1 | H1008: SAHABAT GARMINDO PT- 81465 | I1008: AOS | J1008: 15130575 | K1008: LEB24-02 | L1008: SS KOKO MUSLIM 2024 02 - CUT AND SEWN PRINTING LEB24-02:NAVY BLUE:S:PRINT:SS KOKO | M1008: 179900 | N1008: =$N$2 -> 0.8 | O1008: =$O$2 -> 21980 | P1008: =$P$2 -> PERCENTAGE
A1009: =$A$2 -> 2024 ALL T-SHIRT EXC KI & RAGLAN D80 | B1009: ='2019 ALL N OLDER D95'!$B$2 -> 46121 | C1009: ='2019 ALL N OLDER D95'!$C$2 -> 46127 | D1009: 3260 | E1009: 333 | F1009: 3 | G1009: 1 | H1009: SAHABAT GARMINDO PT- 81466 | I1009: AOS | J1009: 15130584 | K1009: LEB24-02 | L1009: SS KOKO MUSLIM 2024 02 - CUT AND SEWN PRINTING LEB24-02:NAVY BLUE:M:PRINT:SS KOKO | M1009: 179900 | N1009: =$N$2 -> 0.8 | O1009: =$O$2 -> 21980 | P1009: =$P$2 -> PERCENTAGE
A1010: =$A$2 -> 2024 ALL T-SHIRT EXC KI & RAGLAN D80 | B1010: ='2019 ALL N OLDER D95'!$B$2 -> 46121 | C1010: ='2019 ALL N OLDER D95'!$C$2 -> 46127 | D1010: 3260 | E1010: 333 | F1010: 3 | G1010: 1 | H1010: SAHABAT GARMINDO PT- 81467 | I1010: AOS | J1010: 15130593 | K1010: LEB24-02 | L1010: SS KOKO MUSLIM 2024 02 - CUT AND SEWN PRINTING LEB24-02:NAVY BLUE:L:PRINT:SS KOKO | M1010: 179900 | N1010: =$N$2 -> 0.8 | O1010: =$O$2 -> 21980 | P1010: =$P$2 -> PERCENTAGE
A1011: =$A$2 -> 2024 ALL T-SHIRT EXC KI & RAGLAN D80 | B1011: ='2019 ALL N OLDER D95'!$B$2 -> 46121 | C1011: ='2019 ALL N OLDER D95'!$C$2 -> 46127 | D1011: 3260 | E1011: 333 | F1011: 3 | G1011: 1 | H1011: SAHABAT GARMINDO PT- 81468 | I1011: AOS | J1011: 15130600 | K1011: LEB24-02 | L1011: SS KOKO MUSLIM 2024 02 - CUT AND SEWN PRINTING LEB24-02:NAVY BLUE:XL:PRINT:SS KOKO | M1011: 179900 | N1011: =$N$2 -> 0.8 | O1011: =$O$2 -> 21980 | P1011: =$P$2 -> PERCENTAGE
A1012: =$A$2 -> 2024 ALL T-SHIRT EXC KI & RAGLAN D80 | B1012: ='2019 ALL N OLDER D95'!$B$2 -> 46121 | C1012: ='2019 ALL N OLDER D95'!$C$2 -> 46127 | D1012: 3260 | E1012: 333 | F1012: 3 | G1012: 1 | H1012: SAHABAT GARMINDO PT- 81469 | I1012: AOS | J1012: 15130619 | K1012: LEB24-03 | L1012: SS KOKO MUSLIM 2024 03 - CUT AND SEWN EMBRO LEB24-03:KHAKI:S:PRINT:SS KOKO | M1012: 179900 | N1012: =$N$2 -> 0.8 | O1012: =$O$2 -> 21980 | P1012: =$P$2 -> PERCENTAGE
A1013: =$A$2 -> 2024 ALL T-SHIRT EXC KI & RAGLAN D80 | B1013: ='2019 ALL N OLDER D95'!$B$2 -> 46121 | C1013: ='2019 ALL N OLDER D95'!$C$2 -> 46127 | D1013: 3260 | E1013: 333 | F1013: 3 | G1013: 1 | H1013: SAHABAT GARMINDO PT- 81470 | I1013: AOS | J1013: 15130628 | K1013: LEB24-03 | L1013: SS KOKO MUSLIM 2024 03 - CUT AND SEWN EMBRO LEB24-03:KHAKI:M:PRINT:SS KOKO | M1013: 179900 | N1013: =$N$2 -> 0.8 | O1013: =$O$2 -> 21980 | P1013: =$P$2 -> PERCENTAGE
A1014: =$A$2 -> 2024 ALL T-SHIRT EXC KI & RAGLAN D80 | B1014: ='2019 ALL N OLDER D95'!$B$2 -> 46121 | C1014: ='2019 ALL N OLDER D95'!$C$2 -> 46127 | D1014: 3260 | E1014: 333 | F1014: 3 | G1014: 1 | H1014: SAHABAT GARMINDO PT- 81471 | I1014: AOS | J1014: 15130637 | K1014: LEB24-03 | L1014: SS KOKO MUSLIM 2024 03 - CUT AND SEWN EMBRO LEB24-03:KHAKI:L:PRINT:SS KOKO | M1014: 179900 | N1014: =$N$2 -> 0.8 | O1014: =$O$2 -> 21980 | P1014: =$P$2 -> PERCENTAGE
A1015: =$A$2 -> 2024 ALL T-SHIRT EXC KI & RAGLAN D80 | B1015: ='2019 ALL N OLDER D95'!$B$2 -> 46121 | C1015: ='2019 ALL N OLDER D95'!$C$2 -> 46127 | D1015: 3260 | E1015: 333 | F1015: 3 | G1015: 1 | H1015: SAHABAT GARMINDO PT- 81472 | I1015: AOS | J1015: 15130646 | K1015: LEB24-03 | L1015: SS KOKO MUSLIM 2024 03 - CUT AND SEWN EMBRO LEB24-03:KHAKI:XL:PRINT:SS KOKO | M1015: 179900 | N1015: =$N$2 -> 0.8 | O1015: =$O$2 -> 21980 | P1015: =$P$2 -> PERCENTAGE
... A1115: =$A$2 -> 2024 ALL T-SHIRT EXC KI & RAGLAN D80 | B1115: ='2019 ALL N OLDER D95'!$B$2 -> 46121 | C1115: ='2019 ALL N OLDER D95'!$C$2 -> 46127 | D1115: 3260 | E1115: 333 | F1115: 3 | G1115: 1 | H1115: TRIKENCANA | I1115: AOS | J1115: 14597118 | K1115: CNY24-TT4 | L1115: SS T-SHIRT CNY COLLECTION 2024 - 4 CNY24-TT4:CLASSIC RED:XL:GRAPHIC:SS T-SHIRT | M1115: 109900 | N1115: =$N$2 -> 0.8 | O1115: =$O$2 -> 21980 | P1115: =$P$2 -> PERCENTAGE
A1116: =$A$2 -> 2024 ALL T-SHIRT EXC KI & RAGLAN D80 | B1116: ='2019 ALL N OLDER D95'!$B$2 -> 46121 | C1116: ='2019 ALL N OLDER D95'!$C$2 -> 46127 | D1116: 3260 | E1116: 333 | F1116: 3 | G1116: 1 | H1116: SAHABAT GARMINDO PT- 81461 | I1116: AOS | J1116: 17028923 | K1116: BSS5-MD | L1116: SS T-SHIRT BIG SIZE PRINT THEME CITY - MADRID BSS5-MD:WHITE:2XL:TEXT:SS T-SHIRT | M1116: 129900 | N1116: =$N$2 -> 0.8 | O1116: =$O$2 -> 21980 | P1116: =$P$2 -> PERCENTAGE
A1117: =$A$2 -> 2024 ALL T-SHIRT EXC KI & RAGLAN D80 | B1117: ='2019 ALL N OLDER D95'!$B$2 -> 46121 | C1117: ='2019 ALL N OLDER D95'!$C$2 -> 46127 | D1117: 3260 | E1117: 333 | F1117: 3 | G1117: 1 | H1117: SAHABAT GARMINDO PT- 81461 | I1117: AOS | J1117: 17028932 | K1117: BSS5-MD | L1117: SS T-SHIRT BIG SIZE PRINT THEME CITY - MADRID BSS5-MD:WHITE:3XL:TEXT:SS T-SHIRT | M1117: 129900 | N1117: =$N$2 -> 0.8 | O1117: =$O$2 -> 21980 | P1117: =$P$2 -> PERCENTAGE
A1118: =$A$2 -> 2024 ALL T-SHIRT EXC KI & RAGLAN D80 | B1118: ='2019 ALL N OLDER D95'!$B$2 -> 46121 | C1118: ='2019 ALL N OLDER D95'!$C$2 -> 46127 | D1118: 3260 | E1118: 333 | F1118: 3 | G1118: 1 | H1118: SAHABAT GARMINDO PT- 81461 | I1118: AOS | J1118: 17028941 | K1118: BSS5-MD | L1118: SS T-SHIRT BIG SIZE PRINT THEME CITY - MADRID BSS5-MD:WHITE:4XL:TEXT:SS T-SHIRT | M1118: 129900 | N1118: =$N$2 -> 0.8 | O1118: =$O$2 -> 21980 | P1118: =$P$2 -> PERCENTAGE
A1119: =$A$2 -> 2024 ALL T-SHIRT EXC KI & RAGLAN D80 | B1119: ='2019 ALL N OLDER D95'!$B$2 -> 46121 | C1119: ='2019 ALL N OLDER D95'!$C$2 -> 46127 | D1119: 3260 | E1119: 333 | F1119: 3 | G1119: 1 | H1119: SAHABAT GARMINDO PT- 81461 | I1119: AOS | J1119: 17028950 | K1119: BSS5-MD | L1119: SS T-SHIRT BIG SIZE PRINT THEME CITY - MADRID BSS5-MD:WHITE:5XL:TEXT:SS T-SHIRT | M1119: 129900 | N1119: =$N$2 -> 0.8 | O1119: =$O$2 -> 21980 | P1119: =$P$2 -> PERCENTAGE
A1120: =$A$2 -> 2024 ALL T-SHIRT EXC KI & RAGLAN D80 | B1120: ='2019 ALL N OLDER D95'!$B$2 -> 46121 | C1120: ='2019 ALL N OLDER D95'!$C$2 -> 46127 | D1120: 3260 | E1120: 333 | F1120: 3 | G1120: 1 | H1120: SAHABAT GARMINDO PT- 81461 | I1120: AOS | J1120: 17028969 | K1120: BSS5-LI | L1120: SS T-SHIRT BIG SIZE PRINT THEME CITY - LIVERPOOL BSS5-LI:MAROON:2XL:TEXT:SS T-SHIRT | M1120: 129900 | N1120: =$N$2 -> 0.8 | O1120: =$O$2 -> 21980 | P1120: =$P$2 -> PERCENTAGE
A1121: =$A$2 -> 2024 ALL T-SHIRT EXC KI & RAGLAN D80 | B1121: ='2019 ALL N OLDER D95'!$B$2 -> 46121 | C1121: ='2019 ALL N OLDER D95'!$C$2 -> 46127 | D1121: 3260 | E1121: 333 | F1121: 3 | G1121: 1 | H1121: SAHABAT GARMINDO PT- 81461 | I1121: AOS | J1121: 17028978 | K1121: BSS5-LI | L1121: SS T-SHIRT BIG SIZE PRINT THEME CITY - LIVERPOOL BSS5-LI:MAROON:3XL:TEXT:SS T-SHIRT | M1121: 129900 | N1121: =$N$2 -> 0.8 | O1121: =$O$2 -> 21980 | P1121: =$P$2 -> PERCENTAGE
A1122: =$A$2 -> 2024 ALL T-SHIRT EXC KI & RAGLAN D80 | B1122: ='2019 ALL N OLDER D95'!$B$2 -> 46121 | C1122: ='2019 ALL N OLDER D95'!$C$2 -> 46127 | D1122: 3260 | E1122: 333 | F1122: 3 | G1122: 1 | H1122: SAHABAT GARMINDO PT- 81461 | I1122: AOS | J1122: 17028987 | K1122: BSS5-LI | L1122: SS T-SHIRT BIG SIZE PRINT THEME CITY - LIVERPOOL BSS5-LI:MAROON:4XL:TEXT:SS T-SHIRT | M1122: 129900 | N1122: =$N$2 -> 0.8 | O1122: =$O$2 -> 21980 | P1122: =$P$2 -> PERCENTAGE
A1123: =$A$2 -> 2024 ALL T-SHIRT EXC KI & RAGLAN D80 | B1123: ='2019 ALL N OLDER D95'!$B$2 -> 46121 | C1123: ='2019 ALL N OLDER D95'!$C$2 -> 46127 | D1123: 3260 | E1123: 333 | F1123: 3 | G1123: 1 | H1123: SAHABAT GARMINDO PT- 81461 | I1123: AOS | J1123: 17028996 | K1123: BSS5-LI | L1123: SS T-SHIRT BIG SIZE PRINT THEME CITY - LIVERPOOL BSS5-LI:MAROON:5XL:TEXT:SS T-SHIRT | M1123: 129900 | N1123: =$N$2 -> 0.8 | O1123: =$O$2 -> 21980 | P1123: =$P$2 -> PERCENTAGE
A1124: =$A$2 -> 2024 ALL T-SHIRT EXC KI & RAGLAN D80 | B1124: ='2019 ALL N OLDER D95'!$B$2 -> 46121 | C1124: ='2019 ALL N OLDER D95'!$C$2 -> 46127 | D1124: 3260 | E1124: 333 | F1124: 3 | G1124: 1 | H1124: SAHABAT GARMINDO PT- 81461 | I1124: AOS | J1124: 17029002 | K1124: BSS5-PA | L1124: SS T-SHIRT BIG SIZE PRINT THEME CITY - PARIS BSS5-PA:KHAKI:2XL:TEXT:SS T-SHIRT | M1124: 129900 | N1124: =$N$2 -> 0.8 | O1124: =$O$2 -> 21980 | P1124: =$P$2 -> PERCENTAGE
A1125: =$A$2 -> 2024 ALL T-SHIRT EXC KI & RAGLAN D80 | B1125: ='2019 ALL N OLDER D95'!$B$2 -> 46121 | C1125: ='2019 ALL N OLDER D95'!$C$2 -> 46127 | D1125: 3260 | E1125: 333 | F1125: 3 | G1125: 1 | H1125: SAHABAT GARMINDO PT- 81461 | I1125: AOS | J1125: 17029011 | K1125: BSS5-PA | L1125: SS T-SHIRT BIG SIZE PRINT THEME CITY - PARIS BSS5-PA:KHAKI:3XL:TEXT:SS T-SHIRT | M1125: 129900 | N1125: =$N$2 -> 0.8 | O1125: =$O$2 -> 21980 | P1125: =$P$2 -> PERCENTAGE
A1126: =$A$2 -> 2024 ALL T-SHIRT EXC KI & RAGLAN D80 | B1126: ='2019 ALL N OLDER D95'!$B$2 -> 46121 | C1126: ='2019 ALL N OLDER D95'!$C$2 -> 46127 | D1126: 3260 | E1126: 333 | F1126: 3 | G1126: 1 | H1126: SAHABAT GARMINDO PT- 81461 | I1126: AOS | J1126: 17029020 | K1126: BSS5-PA | L1126: SS T-SHIRT BIG SIZE PRINT THEME CITY - PARIS BSS5-PA:KHAKI:4XL:TEXT:SS T-SHIRT | M1126: 129900 | N1126: =$N$2 -> 0.8 | O1126: =$O$2 -> 21980 | P1126: =$P$2 -> PERCENTAGE
A1127: =$A$2 -> 2024 ALL T-SHIRT EXC KI & RAGLAN D80 | B1127: ='2019 ALL N OLDER D95'!$B$2 -> 46121 | C1127: ='2019 ALL N OLDER D95'!$C$2 -> 46127 | D1127: 3260 | E1127: 333 | F1127: 3 | G1127: 1 | H1127: SAHABAT GARMINDO PT- 81461 | I1127: AOS | J1127: 17029039 | K1127: BSS5-PA | L1127: SS T-SHIRT BIG SIZE PRINT THEME CITY - PARIS BSS5-PA:KHAKI:5XL:TEXT:SS T-SHIRT | M1127: 129900 | N1127: =$N$2 -> 0.8 | O1127: =$O$2 -> 21980 | P1127: =$P$2 -> PERCENTAGE
... A1188: =$A$2 -> 2024 ALL T-SHIRT EXC KI & RAGLAN D80 | B1188: ='2019 ALL N OLDER D95'!$B$2 -> 46121 | C1188: ='2019 ALL N OLDER D95'!$C$2 -> 46127 | D1188: 3260 | E1188: 333 | F1188: 3 | G1188: 1 | H1188: SAHABAT GARMINDO PT- 81461 | I1188: AOS | J1188: 20636402 | K1188: TS08-SP04 | L1188: SS T-SHIRT PRINT THEME SPORT SHBT - 4 TS08-SP04:GOLDEN BROWN:XL:GRAPHIC:SS T-SHIRT | M1188: 109900 | N1188: =$N$2 -> 0.8 | O1188: =$O$2 -> 21980 | P1188: =$P$2 -> PERCENTAGE
A1189: =$A$2 -> 2024 ALL T-SHIRT EXC KI & RAGLAN D80 | B1189: ='2019 ALL N OLDER D95'!$B$2 -> 46121 | C1189: ='2019 ALL N OLDER D95'!$C$2 -> 46127 | D1189: 3260 | E1189: 333 | F1189: 3 | G1189: 4 | H1189: JAVA DESIGN SENTOSA CV. | I1189: AOS | J1189: 20637223 | K1189: WB-FLINS1 | L1189: SS T-SHIRT WB PRINT FLINSTONE - 1 WB-FLINS1 | M1189: 129900 | N1189: =$N$2 -> 0.8 | O1189: =$O$2 -> 21980 | P1189: =$P$2 -> PERCENTAGE
A1190: =$A$2 -> 2024 ALL T-SHIRT EXC KI & RAGLAN D80 | B1190: ='2019 ALL N OLDER D95'!$B$2 -> 46121 | C1190: ='2019 ALL N OLDER D95'!$C$2 -> 46127 | D1190: 3260 | E1190: 333 | F1190: 3 | G1190: 4 | H1190: JAVA DESIGN SENTOSA CV. | I1190: AOS | J1190: 20637269 | K1190: WB-FLINS1 | L1190: SS T-SHIRT WB PRINT FLINSTONE - 1 WB-FLINS1 | M1190: 129900 | N1190: =$N$2 -> 0.8 | O1190: =$O$2 -> 21980 | P1190: =$P$2 -> PERCENTAGE
A1191: =$A$2 -> 2024 ALL T-SHIRT EXC KI & RAGLAN D80 | B1191: ='2019 ALL N OLDER D95'!$B$2 -> 46121 | C1191: ='2019 ALL N OLDER D95'!$C$2 -> 46127 | D1191: 3260 | E1191: 333 | F1191: 3 | G1191: 4 | H1191: JAVA DESIGN SENTOSA CV. | I1191: AOS | J1191: 20637312 | K1191: WB-FLINS1 | L1191: SS T-SHIRT WB PRINT FLINSTONE - 1 WB-FLINS1 | M1191: 129900 | N1191: =$N$2 -> 0.8 | O1191: =$O$2 -> 21980 | P1191: =$P$2 -> PERCENTAGE
A1192: =$A$2 -> 2024 ALL T-SHIRT EXC KI & RAGLAN D80 | B1192: ='2019 ALL N OLDER D95'!$B$2 -> 46121 | C1192: ='2019 ALL N OLDER D95'!$C$2 -> 46127 | D1192: 3260 | E1192: 333 | F1192: 3 | G1192: 4 | H1192: JAVA DESIGN SENTOSA CV. | I1192: AOS | J1192: 20637349 | K1192: WB-FLINS1 | L1192: SS T-SHIRT WB PRINT FLINSTONE - 1 WB-FLINS1 | M1192: 129900 | N1192: =$N$2 -> 0.8 | O1192: =$O$2 -> 21980 | P1192: =$P$2 -> PERCENTAGE
A1193: =$A$2 -> 2024 ALL T-SHIRT EXC KI & RAGLAN D80 | B1193: ='2019 ALL N OLDER D95'!$B$2 -> 46121 | C1193: ='2019 ALL N OLDER D95'!$C$2 -> 46127 | D1193: 3260 | E1193: 333 | F1193: 3 | G1193: 4 | H1193: JAVA DESIGN SENTOSA CV. | I1193: AOS | J1193: 20637401 | K1193: WB-FLINS2 | L1193: SS T-SHIRT WB PRINT FLINSTONE - 2 BACKPRINT WB-FLINS2 | M1193: 129900 | N1193: =$N$2 -> 0.8 | O1193: =$O$2 -> 21980 | P1193: =$P$2 -> PERCENTAGE
A1194: =$A$2 -> 2024 ALL T-SHIRT EXC KI & RAGLAN D80 | B1194: ='2019 ALL N OLDER D95'!$B$2 -> 46121 | C1194: ='2019 ALL N OLDER D95'!$C$2 -> 46127 | D1194: 3260 | E1194: 333 | F1194: 3 | G1194: 4 | H1194: JAVA DESIGN SENTOSA CV. | I1194: AOS | J1194: 20637410 | K1194: WB-FLINS2 | L1194: SS T-SHIRT WB PRINT FLINSTONE - 2 BACKPRINT WB-FLINS2 | M1194: 129900 | N1194: =$N$2 -> 0.8 | O1194: =$O$2 -> 21980 | P1194: =$P$2 -> PERCENTAGE
A1195: =$A$2 -> 2024 ALL T-SHIRT EXC KI & RAGLAN D80 | B1195: ='2019 ALL N OLDER D95'!$B$2 -> 46121 | C1195: ='2019 ALL N OLDER D95'!$C$2 -> 46127 | D1195: 3260 | E1195: 333 | F1195: 3 | G1195: 4 | H1195: JAVA DESIGN SENTOSA CV. | I1195: AOS | J1195: 20637429 | K1195: WB-FLINS2 | L1195: SS T-SHIRT WB PRINT FLINSTONE - 2 BACKPRINT WB-FLINS2 | M1195: 129900 | N1195: =$N$2 -> 0.8 | O1195: =$O$2 -> 21980 | P1195: =$P$2 -> PERCENTAGE
A1196: =$A$2 -> 2024 ALL T-SHIRT EXC KI & RAGLAN D80 | B1196: ='2019 ALL N OLDER D95'!$B$2 -> 46121 | C1196: ='2019 ALL N OLDER D95'!$C$2 -> 46127 | D1196: 3260 | E1196: 333 | F1196: 3 | G1196: 4 | H1196: JAVA DESIGN SENTOSA CV. | I1196: AOS | J1196: 20637447 | K1196: WB-FLINS2 | L1196: SS T-SHIRT WB PRINT FLINSTONE - 2 BACKPRINT WB-FLINS2 | M1196: 129900 | N1196: =$N$2 -> 0.8 | O1196: =$O$2 -> 21980 | P1196: =$P$2 -> PERCENTAGE
A1197: =$A$2 -> 2024 ALL T-SHIRT EXC KI & RAGLAN D80 | B1197: ='2019 ALL N OLDER D95'!$B$2 -> 46121 | C1197: ='2019 ALL N OLDER D95'!$C$2 -> 46127 | D1197: 3260 | E1197: 333 | F1197: 3 | G1197: 4 | H1197: JAVA DESIGN SENTOSA CV. | I1197: AOS | J1197: 20637465 | K1197: WB-FLINS3 | L1197: SS T-SHIRT WB PRINT FLINSTONE - 3 BACKPRINT WB-FLINS3 | M1197: 129900 | N1197: =$N$2 -> 0.8 | O1197: =$O$2 -> 21980 | P1197: =$P$2 -> PERCENTAGE
A1198: =$A$2 -> 2024 ALL T-SHIRT EXC KI & RAGLAN D80 | B1198: ='2019 ALL N OLDER D95'!$B$2 -> 46121 | C1198: ='2019 ALL N OLDER D95'!$C$2 -> 46127 | D1198: 3260 | E1198: 333 | F1198: 3 | G1198: 4 | H1198: JAVA DESIGN SENTOSA CV. | I1198: AOS | J1198: 20637518 | K1198: WB-FLINS3 | L1198: SS T-SHIRT WB PRINT FLINSTONE - 3 BACKPRINT WB-FLINS3 | M1198: 129900 | N1198: =$N$2 -> 0.8 | O1198: =$O$2 -> 21980 | P1198: =$P$2 -> PERCENTAGE
A1199: =$A$2 -> 2024 ALL T-SHIRT EXC KI & RAGLAN D80 | B1199: ='2019 ALL N OLDER D95'!$B$2 -> 46121 | C1199: ='2019 ALL N OLDER D95'!$C$2 -> 46127 | D1199: 3260 | E1199: 333 | F1199: 3 | G1199: 4 | H1199: JAVA DESIGN SENTOSA CV. | I1199: AOS | J1199: 20637527 | K1199: WB-FLINS3 | L1199: SS T-SHIRT WB PRINT FLINSTONE - 3 BACKPRINT WB-FLINS3 | M1199: 129900 | N1199: =$N$2 -> 0.8 | O1199: =$O$2 -> 21980 | P1199: =$P$2 -> PERCENTAGE
A1200: =$A$2 -> 2024 ALL T-SHIRT EXC KI & RAGLAN D80 | B1200: ='2019 ALL N OLDER D95'!$B$2 -> 46121 | C1200: ='2019 ALL N OLDER D95'!$C$2 -> 46127 | D1200: 3260 | E1200: 333 | F1200: 3 | G1200: 4 | H1200: JAVA DESIGN SENTOSA CV. | I1200: AOS | J1200: 20637545 | K1200: WB-FLINS3 | L1200: SS T-SHIRT WB PRINT FLINSTONE - 3 BACKPRINT WB-FLINS3 | M1200: 129900 | N1200: =$N$2 -> 0.8 | O1200: =$O$2 -> 21980 | P1200: =$P$2 -> PERCENTAGE
... A1344: =$A$2 -> 2024 ALL T-SHIRT EXC KI & RAGLAN D80 | B1344: ='2019 ALL N OLDER D95'!$B$2 -> 46121 | C1344: ='2019 ALL N OLDER D95'!$C$2 -> 46127 | D1344: 3260 | E1344: 333 | F1344: 3 | G1344: 1 | H1344: JAVA DESIGN SENTOSA CV. | I1344: AOS | J1344: 22737666 | K1344: TJ8SPO3-5 | L1344: SS T-SHIRT PRINT THEME SPORT 3 - 5 TJ8SPO3-5 | M1344: 109900 | N1344: =$N$2 -> 0.8 | O1344: =$O$2 -> 21980 | P1344: =$P$2 -> PERCENTAGE
A1345: =$A$2 -> 2024 ALL T-SHIRT EXC KI & RAGLAN D80 | B1345: ='2019 ALL N OLDER D95'!$B$2 -> 46121 | C1345: ='2019 ALL N OLDER D95'!$C$2 -> 46127 | D1345: 3260 | E1345: 333 | F1345: 3 | G1345: 1 | H1345: JAVA DESIGN SENTOSA CV. | I1345: AOS | J1345: 22736112 | K1345: TJ9RF-1 | L1345: SS T-SHIRT PRINT THEME ROCK FESTIVAL - 1 TJ9RF-1 | M1345: 109900 | N1345: =$N$2 -> 0.8 | O1345: =$O$2 -> 21980 | P1345: =$P$2 -> PERCENTAGE
A1346: =$A$2 -> 2024 ALL T-SHIRT EXC KI & RAGLAN D80 | B1346: ='2019 ALL N OLDER D95'!$B$2 -> 46121 | C1346: ='2019 ALL N OLDER D95'!$C$2 -> 46127 | D1346: 3260 | E1346: 333 | F1346: 3 | G1346: 1 | H1346: JAVA DESIGN SENTOSA CV. | I1346: AOS | J1346: 22736121 | K1346: TJ9RF-1 | L1346: SS T-SHIRT PRINT THEME ROCK FESTIVAL - 1 TJ9RF-1 | M1346: 109900 | N1346: =$N$2 -> 0.8 | O1346: =$O$2 -> 21980 | P1346: =$P$2 -> PERCENTAGE
A1347: =$A$2 -> 2024 ALL T-SHIRT EXC KI & RAGLAN D80 | B1347: ='2019 ALL N OLDER D95'!$B$2 -> 46121 | C1347: ='2019 ALL N OLDER D95'!$C$2 -> 46127 | D1347: 3260 | E1347: 333 | F1347: 3 | G1347: 1 | H1347: JAVA DESIGN SENTOSA CV. | I1347: AOS | J1347: 22736130 | K1347: TJ9RF-1 | L1347: SS T-SHIRT PRINT THEME ROCK FESTIVAL - 1 TJ9RF-1 | M1347: 109900 | N1347: =$N$2 -> 0.8 | O1347: =$O$2 -> 21980 | P1347: =$P$2 -> PERCENTAGE
A1348: =$A$2 -> 2024 ALL T-SHIRT EXC KI & RAGLAN D80 | B1348: ='2019 ALL N OLDER D95'!$B$2 -> 46121 | C1348: ='2019 ALL N OLDER D95'!$C$2 -> 46127 | D1348: 3260 | E1348: 333 | F1348: 3 | G1348: 1 | H1348: JAVA DESIGN SENTOSA CV. | I1348: AOS | J1348: 22736149 | K1348: TJ9RF-1 | L1348: SS T-SHIRT PRINT THEME ROCK FESTIVAL - 1 TJ9RF-1 | M1348: 109900 | N1348: =$N$2 -> 0.8 | O1348: =$O$2 -> 21980 | P1348: =$P$2 -> PERCENTAGE
A1349: =$A$2 -> 2024 ALL T-SHIRT EXC KI & RAGLAN D80 | B1349: ='2019 ALL N OLDER D95'!$B$2 -> 46121 | C1349: ='2019 ALL N OLDER D95'!$C$2 -> 46127 | D1349: 3260 | E1349: 333 | F1349: 3 | G1349: 1 | H1349: JAVA DESIGN SENTOSA CV. | I1349: AOS | J1349: 22736630 | K1349: TJ9RF-3 | L1349: SS T-SHIRT PRINT THEME ROCK FESTIVAL - 3 TJ9RF-3 | M1349: 109900 | N1349: =$N$2 -> 0.8 | O1349: =$O$2 -> 21980 | P1349: =$P$2 -> PERCENTAGE
A1350: =$A$2 -> 2024 ALL T-SHIRT EXC KI & RAGLAN D80 | B1350: ='2019 ALL N OLDER D95'!$B$2 -> 46121 | C1350: ='2019 ALL N OLDER D95'!$C$2 -> 46127 | D1350: 3260 | E1350: 333 | F1350: 3 | G1350: 1 | H1350: JAVA DESIGN SENTOSA CV. | I1350: AOS | J1350: 22736649 | K1350: TJ9RF-3 | L1350: SS T-SHIRT PRINT THEME ROCK FESTIVAL - 3 TJ9RF-3 | M1350: 109900 | N1350: =$N$2 -> 0.8 | O1350: =$O$2 -> 21980 | P1350: =$P$2 -> PERCENTAGE
A1351: =$A$2 -> 2024 ALL T-SHIRT EXC KI & RAGLAN D80 | B1351: ='2019 ALL N OLDER D95'!$B$2 -> 46121 | C1351: ='2019 ALL N OLDER D95'!$C$2 -> 46127 | D1351: 3260 | E1351: 333 | F1351: 3 | G1351: 1 | H1351: JAVA DESIGN SENTOSA CV. | I1351: AOS | J1351: 22736658 | K1351: TJ9RF-3 | L1351: SS T-SHIRT PRINT THEME ROCK FESTIVAL - 3 TJ9RF-3 | M1351: 109900 | N1351: =$N$2 -> 0.8 | O1351: =$O$2 -> 21980 | P1351: =$P$2 -> PERCENTAGE
A1352: =$A$2 -> 2024 ALL T-SHIRT EXC KI & RAGLAN D80 | B1352: ='2019 ALL N OLDER D95'!$B$2 -> 46121 | C1352: ='2019 ALL N OLDER D95'!$C$2 -> 46127 | D1352: 3260 | E1352: 333 | F1352: 3 | G1352: 1 | H1352: JAVA DESIGN SENTOSA CV. | I1352: AOS | J1352: 22736667 | K1352: TJ9RF-3 | L1352: SS T-SHIRT PRINT THEME ROCK FESTIVAL - 3 TJ9RF-3 | M1352: 109900 | N1352: =$N$2 -> 0.8 | O1352: =$O$2 -> 21980 | P1352: =$P$2 -> PERCENTAGE
A1353: =$A$2 -> 2024 ALL T-SHIRT EXC KI & RAGLAN D80 | B1353: ='2019 ALL N OLDER D95'!$B$2 -> 46121 | C1353: ='2019 ALL N OLDER D95'!$C$2 -> 46127 | D1353: 3260 | E1353: 333 | F1353: 3 | G1353: 4 | H1353: JAVA DESIGN SENTOSA CV. | I1353: AOS | J1353: 22739164 | K1353: WBJ&B-1 | L1353: SS T-SHIRT WB JOKER AND BATMAN - 1 WBJ&B-1 | M1353: 129900 | N1353: =$N$2 -> 0.8 | O1353: =$O$2 -> 21980 | P1353: =$P$2 -> PERCENTAGE
A1354: =$A$2 -> 2024 ALL T-SHIRT EXC KI & RAGLAN D80 | B1354: ='2019 ALL N OLDER D95'!$B$2 -> 46121 | C1354: ='2019 ALL N OLDER D95'!$C$2 -> 46127 | D1354: 3260 | E1354: 333 | F1354: 3 | G1354: 4 | H1354: JAVA DESIGN SENTOSA CV. | I1354: AOS | J1354: 22739173 | K1354: WBJ&B-1 | L1354: SS T-SHIRT WB JOKER AND BATMAN - 1 WBJ&B-1 | M1354: 129900 | N1354: =$N$2 -> 0.8 | O1354: =$O$2 -> 21980 | P1354: =$P$2 -> PERCENTAGE
A1355: =$A$2 -> 2024 ALL T-SHIRT EXC KI & RAGLAN D80 | B1355: ='2019 ALL N OLDER D95'!$B$2 -> 46121 | C1355: ='2019 ALL N OLDER D95'!$C$2 -> 46127 | D1355: 3260 | E1355: 333 | F1355: 3 | G1355: 4 | H1355: JAVA DESIGN SENTOSA CV. | I1355: AOS | J1355: 22739182 | K1355: WBJ&B-1 | L1355: SS T-SHIRT WB JOKER AND BATMAN - 1 WBJ&B-1 | M1355: 129900 | N1355: =$N$2 -> 0.8 | O1355: =$O$2 -> 21980 | P1355: =$P$2 -> PERCENTAGE
A1356: =$A$2 -> 2024 ALL T-SHIRT EXC KI & RAGLAN D80 | B1356: ='2019 ALL N OLDER D95'!$B$2 -> 46121 | C1356: ='2019 ALL N OLDER D95'!$C$2 -> 46127 | D1356: 3260 | E1356: 333 | F1356: 3 | G1356: 4 | H1356: JAVA DESIGN SENTOSA CV. | I1356: AOS | J1356: 22739191 | K1356: WBJ&B-1 | L1356: SS T-SHIRT WB JOKER AND BATMAN - 1 WBJ&B-1 | M1356: 129900 | N1356: =$N$2 -> 0.8 | O1356: =$O$2 -> 21980 | P1356: =$P$2 -> PERCENTAGE
... A1372: =$A$2 -> 2024 ALL T-SHIRT EXC KI & RAGLAN D80 | B1372: ='2019 ALL N OLDER D95'!$B$2 -> 46121 | C1372: ='2019 ALL N OLDER D95'!$C$2 -> 46127 | D1372: 3260 | E1372: 333 | F1372: 3 | G1372: 4 | H1372: JAVA DESIGN SENTOSA CV. | I1372: AOS | J1372: 22739904 | K1372: WBJ&B-5 | L1372: SS T-SHIRT WB JOKER AND BATMAN - 5 WBJ&B-5 | M1372: 129900 | N1372: =$N$2 -> 0.8 | O1372: =$O$2 -> 21980 | P1372: =$P$2 -> PERCENTAGE
A1373: =$A$2 -> 2024 ALL T-SHIRT EXC KI & RAGLAN D80 | B1373: ='2019 ALL N OLDER D95'!$B$2 -> 46121 | C1373: ='2019 ALL N OLDER D95'!$C$2 -> 46127 | D1373: 3260 | E1373: 333 | F1373: 3 | G1373: 1 | H1373: FECEKRAN SANDANG JAYA PT.-81235 | I1373: AOS | J1373: 17029137 | K1373: TFUF6-WC1 | L1373: SS T-SHIRT FULLPRINT AOP THEME WASTELAND CAMOU - 1 GOOD VIBES TFUF6-WC1:DARK JADE:S:PRINT:SS T-SHIRT | M1373: 109900 | N1373: =$N$2 -> 0.8 | O1373: =$O$2 -> 21980 | P1373: =$P$2 -> PERCENTAGE
A1374: =$A$2 -> 2024 ALL T-SHIRT EXC KI & RAGLAN D80 | B1374: ='2019 ALL N OLDER D95'!$B$2 -> 46121 | C1374: ='2019 ALL N OLDER D95'!$C$2 -> 46127 | D1374: 3260 | E1374: 333 | F1374: 3 | G1374: 1 | H1374: FECEKRAN SANDANG JAYA PT.-81235 | I1374: AOS | J1374: 17029146 | K1374: TFUF6-WC1 | L1374: SS T-SHIRT FULLPRINT AOP THEME WASTELAND CAMOU - 1 GOOD VIBES TFUF6-WC1:DARK JADE:M:PRINT:SS T-SHIRT | M1374: 109900 | N1374: =$N$2 -> 0.8 | O1374: =$O$2 -> 21980 | P1374: =$P$2 -> PERCENTAGE
A1375: =$A$2 -> 2024 ALL T-SHIRT EXC KI & RAGLAN D80 | B1375: ='2019 ALL N OLDER D95'!$B$2 -> 46121 | C1375: ='2019 ALL N OLDER D95'!$C$2 -> 46127 | D1375: 3260 | E1375: 333 | F1375: 3 | G1375: 1 | H1375: FECEKRAN SANDANG JAYA PT.-81235 | I1375: AOS | J1375: 17029155 | K1375: TFUF6-WC1 | L1375: SS T-SHIRT FULLPRINT AOP THEME WASTELAND CAMOU - 1 GOOD VIBES TFUF6-WC1:DARK JADE:L:PRINT:SS T-SHIRT | M1375: 109900 | N1375: =$N$2 -> 0.8 | O1375: =$O$2 -> 21980 | P1375: =$P$2 -> PERCENTAGE
A1376: =$A$2 -> 2024 ALL T-SHIRT EXC KI & RAGLAN D80 | B1376: ='2019 ALL N OLDER D95'!$B$2 -> 46121 | C1376: ='2019 ALL N OLDER D95'!$C$2 -> 46127 | D1376: 3260 | E1376: 333 | F1376: 3 | G1376: 1 | H1376: FECEKRAN SANDANG JAYA PT.-81235 | I1376: AOS | J1376: 17029164 | K1376: TFUF6-WC1 | L1376: SS T-SHIRT FULLPRINT AOP THEME WASTELAND CAMOU - 1 GOOD VIBES TFUF6-WC1:DARK JADE:XL:PRINT:SS T-SHIR | M1376: 109900 | N1376: =$N$2 -> 0.8 | O1376: =$O$2 -> 21980 | P1376: =$P$2 -> PERCENTAGE
A1377: =$A$2 -> 2024 ALL T-SHIRT EXC KI & RAGLAN D80 | B1377: ='2019 ALL N OLDER D95'!$B$2 -> 46121 | C1377: ='2019 ALL N OLDER D95'!$C$2 -> 46127 | D1377: 3260 | E1377: 333 | F1377: 3 | G1377: 1 | H1377: FECEKRAN SANDANG JAYA PT.-81235 | I1377: AOS | J1377: 17029173 | K1377: TFUF6-WC2 | L1377: SS T-SHIRT FULLPRINT AOP THEME WASTELAND CAMOU - 2 TRUST THE PROCESS TFUF6-WC2:NAVY BLUE:S:PRINT:SS | M1377: 109900 | N1377: =$N$2 -> 0.8 | O1377: =$O$2 -> 21980 | P1377: =$P$2 -> PERCENTAGE
A1378: =$A$2 -> 2024 ALL T-SHIRT EXC KI & RAGLAN D80 | B1378: ='2019 ALL N OLDER D95'!$B$2 -> 46121 | C1378: ='2019 ALL N OLDER D95'!$C$2 -> 46127 | D1378: 3260 | E1378: 333 | F1378: 3 | G1378: 1 | H1378: FECEKRAN SANDANG JAYA PT.-81235 | I1378: AOS | J1378: 17029182 | K1378: TFUF6-WC2 | L1378: SS T-SHIRT FULLPRINT AOP THEME WASTELAND CAMOU - 2 TRUST THE PROCESS TFUF6-WC2:NAVY BLUE:M:PRINT:SS | M1378: 109900 | N1378: =$N$2 -> 0.8 | O1378: =$O$2 -> 21980 | P1378: =$P$2 -> PERCENTAGE
A1379: =$A$2 -> 2024 ALL T-SHIRT EXC KI & RAGLAN D80 | B1379: ='2019 ALL N OLDER D95'!$B$2 -> 46121 | C1379: ='2019 ALL N OLDER D95'!$C$2 -> 46127 | D1379: 3260 | E1379: 333 | F1379: 3 | G1379: 1 | H1379: FECEKRAN SANDANG JAYA PT.-81235 | I1379: AOS | J1379: 17029191 | K1379: TFUF6-WC2 | L1379: SS T-SHIRT FULLPRINT AOP THEME WASTELAND CAMOU - 2 TRUST THE PROCESS TFUF6-WC2:NAVY BLUE:L:PRINT:SS | M1379: 109900 | N1379: =$N$2 -> 0.8 | O1379: =$O$2 -> 21980 | P1379: =$P$2 -> PERCENTAGE
A1380: =$A$2 -> 2024 ALL T-SHIRT EXC KI & RAGLAN D80 | B1380: ='2019 ALL N OLDER D95'!$B$2 -> 46121 | C1380: ='2019 ALL N OLDER D95'!$C$2 -> 46127 | D1380: 3260 | E1380: 333 | F1380: 3 | G1380: 1 | H1380: FECEKRAN SANDANG JAYA PT.-81235 | I1380: AOS | J1380: 17029208 | K1380: TFUF6-WC2 | L1380: SS T-SHIRT FULLPRINT AOP THEME WASTELAND CAMOU - 2 TRUST THE PROCESS TFUF6-WC2:NAVY BLUE:XL:PRINT:SS | M1380: 109900 | N1380: =$N$2 -> 0.8 | O1380: =$O$2 -> 21980 | P1380: =$P$2 -> PERCENTAGE
A1381: =$A$2 -> 2024 ALL T-SHIRT EXC KI & RAGLAN D80 | B1381: ='2019 ALL N OLDER D95'!$B$2 -> 46121 | C1381: ='2019 ALL N OLDER D95'!$C$2 -> 46127 | D1381: 3260 | E1381: 333 | F1381: 3 | G1381: 1 | H1381: FECEKRAN SANDANG JAYA PT.-81235 | I1381: AOS | J1381: 17029217 | K1381: TFUF6-WC3 | L1381: SS T-SHIRT FULLPRINT AOP THEME WASTELAND CAMOU - 3 GOOD THINGS TFUF6-WC3:BLACK:S:PRINT:SS T-SHIRT | M1381: 109900 | N1381: =$N$2 -> 0.8 | O1381: =$O$2 -> 21980 | P1381: =$P$2 -> PERCENTAGE
A1382: =$A$2 -> 2024 ALL T-SHIRT EXC KI & RAGLAN D80 | B1382: ='2019 ALL N OLDER D95'!$B$2 -> 46121 | C1382: ='2019 ALL N OLDER D95'!$C$2 -> 46127 | D1382: 3260 | E1382: 333 | F1382: 3 | G1382: 1 | H1382: FECEKRAN SANDANG JAYA PT.-81235 | I1382: AOS | J1382: 17029226 | K1382: TFUF6-WC3 | L1382: SS T-SHIRT FULLPRINT AOP THEME WASTELAND CAMOU - 3 GOOD THINGS TFUF6-WC3:BLACK:M:PRINT:SS T-SHIRT | M1382: 109900 | N1382: =$N$2 -> 0.8 | O1382: =$O$2 -> 21980 | P1382: =$P$2 -> PERCENTAGE
A1383: =$A$2 -> 2024 ALL T-SHIRT EXC KI & RAGLAN D80 | B1383: ='2019 ALL N OLDER D95'!$B$2 -> 46121 | C1383: ='2019 ALL N OLDER D95'!$C$2 -> 46127 | D1383: 3260 | E1383: 333 | F1383: 3 | G1383: 1 | H1383: FECEKRAN SANDANG JAYA PT.-81235 | I1383: AOS | J1383: 17029235 | K1383: TFUF6-WC3 | L1383: SS T-SHIRT FULLPRINT AOP THEME WASTELAND CAMOU - 3 GOOD THINGS TFUF6-WC3:BLACK:L:PRINT:SS T-SHIRT | M1383: 109900 | N1383: =$N$2 -> 0.8 | O1383: =$O$2 -> 21980 | P1383: =$P$2 -> PERCENTAGE
A1384: =$A$2 -> 2024 ALL T-SHIRT EXC KI & RAGLAN D80 | B1384: ='2019 ALL N OLDER D95'!$B$2 -> 46121 | C1384: ='2019 ALL N OLDER D95'!$C$2 -> 46127 | D1384: 3260 | E1384: 333 | F1384: 3 | G1384: 1 | H1384: FECEKRAN SANDANG JAYA PT.-81235 | I1384: AOS | J1384: 17029244 | K1384: TFUF6-WC3 | L1384: SS T-SHIRT FULLPRINT AOP THEME WASTELAND CAMOU - 3 GOOD THINGS TFUF6-WC3:BLACK:XL:PRINT:SS T-SHIRT | M1384: 109900 | N1384: =$N$2 -> 0.8 | O1384: =$O$2 -> 21980 | P1384: =$P$2 -> PERCENTAGE
... A1451: =$A$2 -> 2024 ALL T-SHIRT EXC KI & RAGLAN D80 | B1451: ='2019 ALL N OLDER D95'!$B$2 -> 46121 | C1451: ='2019 ALL N OLDER D95'!$C$2 -> 46127 | D1451: 3260 | E1451: 333 | F1451: 3 | G1451: 4 | H1451: JAVA DESIGN | I1451: AOS | J1451: 19116735 | K1451: WBTSJK7-6 | L1451: SS T-SHIRT WB SAMURAI JACK - 6 FULLPRINT WBTSJK7-6:BLACK:XL:GRAPHIC:SS T-SHIRT | M1451: 129900 | N1451: =$N$2 -> 0.8 | O1451: =$O$2 -> 21980 | P1451: =$P$2 -> PERCENTAGE
A1452: =$A$2 -> 2024 ALL T-SHIRT EXC KI & RAGLAN D80 | B1452: ='2019 ALL N OLDER D95'!$B$2 -> 46121 | C1452: ='2019 ALL N OLDER D95'!$C$2 -> 46127 | D1452: 3260 | E1452: 333 | F1452: 3 | G1452: 1 | H1452: SAHABAT GARMINDO PT- 81461 | I1452: AOS | J1452: 24394292 | K1452: BSS10-W1 | L1452: SS T-SHIRT BIG SIZE PRINT THEME MINIMALIST WORDING - 1 BSS10-W1:BLACK:2XL:TEXT:SS T-SHIRT | M1452: 129900 | N1452: =$N$2 -> 0.8 | O1452: =$O$2 -> 21980 | P1452: =$P$2 -> PERCENTAGE
A1453: =$A$2 -> 2024 ALL T-SHIRT EXC KI & RAGLAN D80 | B1453: ='2019 ALL N OLDER D95'!$B$2 -> 46121 | C1453: ='2019 ALL N OLDER D95'!$C$2 -> 46127 | D1453: 3260 | E1453: 333 | F1453: 3 | G1453: 1 | H1453: SAHABAT GARMINDO PT- 81461 | I1453: AOS | J1453: 24394309 | K1453: BSS10-W1 | L1453: SS T-SHIRT BIG SIZE PRINT THEME MINIMALIST WORDING - 1 BSS10-W1:BLACK:3XL:TEXT:SS T-SHIRT | M1453: 129900 | N1453: =$N$2 -> 0.8 | O1453: =$O$2 -> 21980 | P1453: =$P$2 -> PERCENTAGE
A1454: =$A$2 -> 2024 ALL T-SHIRT EXC KI & RAGLAN D80 | B1454: ='2019 ALL N OLDER D95'!$B$2 -> 46121 | C1454: ='2019 ALL N OLDER D95'!$C$2 -> 46127 | D1454: 3260 | E1454: 333 | F1454: 3 | G1454: 1 | H1454: SAHABAT GARMINDO PT- 81461 | I1454: AOS | J1454: 24394327 | K1454: BSS10-W1 | L1454: SS T-SHIRT BIG SIZE PRINT THEME MINIMALIST WORDING - 1 BSS10-W1:BLACK:4XL:TEXT:SS T-SHIRT | M1454: 129900 | N1454: =$N$2 -> 0.8 | O1454: =$O$2 -> 21980 | P1454: =$P$2 -> PERCENTAGE
A1455: =$A$2 -> 2024 ALL T-SHIRT EXC KI & RAGLAN D80 | B1455: ='2019 ALL N OLDER D95'!$B$2 -> 46121 | C1455: ='2019 ALL N OLDER D95'!$C$2 -> 46127 | D1455: 3260 | E1455: 333 | F1455: 3 | G1455: 1 | H1455: SAHABAT GARMINDO PT- 81461 | I1455: AOS | J1455: 24394489 | K1455: BSS10-W1 | L1455: SS T-SHIRT BIG SIZE PRINT THEME MINIMALIST WORDING - 1 BSS10-W1:BLACK:5XL:TEXT:SS T-SHIRT | M1455: 129900 | N1455: =$N$2 -> 0.8 | O1455: =$O$2 -> 21980 | P1455: =$P$2 -> PERCENTAGE
A1456: =$A$2 -> 2024 ALL T-SHIRT EXC KI & RAGLAN D80 | B1456: ='2019 ALL N OLDER D95'!$B$2 -> 46121 | C1456: ='2019 ALL N OLDER D95'!$C$2 -> 46127 | D1456: 3260 | E1456: 333 | F1456: 3 | G1456: 1 | H1456: SAHABAT GARMINDO PT- 81461 | I1456: AOS | J1456: 24394498 | K1456: BSS10-W2 | L1456: SS T-SHIRT BIG SIZE PRINT THEME MINIMALIST WORDING - 2 BSS10-W2:BLACK:2XL:TEXT:SS T-SHIRT | M1456: 129900 | N1456: =$N$2 -> 0.8 | O1456: =$O$2 -> 21980 | P1456: =$P$2 -> PERCENTAGE
A1457: =$A$2 -> 2024 ALL T-SHIRT EXC KI & RAGLAN D80 | B1457: ='2019 ALL N OLDER D95'!$B$2 -> 46121 | C1457: ='2019 ALL N OLDER D95'!$C$2 -> 46127 | D1457: 3260 | E1457: 333 | F1457: 3 | G1457: 1 | H1457: SAHABAT GARMINDO PT- 81461 | I1457: AOS | J1457: 24394505 | K1457: BSS10-W2 | L1457: SS T-SHIRT BIG SIZE PRINT THEME MINIMALIST WORDING - 2 BSS10-W2:BLACK:3XL:TEXT:SS T-SHIRT | M1457: 129900 | N1457: =$N$2 -> 0.8 | O1457: =$O$2 -> 21980 | P1457: =$P$2 -> PERCENTAGE
A1458: =$A$2 -> 2024 ALL T-SHIRT EXC KI & RAGLAN D80 | B1458: ='2019 ALL N OLDER D95'!$B$2 -> 46121 | C1458: ='2019 ALL N OLDER D95'!$C$2 -> 46127 | D1458: 3260 | E1458: 333 | F1458: 3 | G1458: 1 | H1458: SAHABAT GARMINDO PT- 81461 | I1458: AOS | J1458: 24394514 | K1458: BSS10-W2 | L1458: SS T-SHIRT BIG SIZE PRINT THEME MINIMALIST WORDING - 2 BSS10-W2:BLACK:4XL:TEXT:SS T-SHIRT | M1458: 129900 | N1458: =$N$2 -> 0.8 | O1458: =$O$2 -> 21980 | P1458: =$P$2 -> PERCENTAGE
...

Sheet 2025 CNY D75
A1: ACARA | B1: FROM DATE | C1: TO DATE | D1: DEPT | E1: WORLD | F1: DIVISION | G1: CLASS | H1: SUPPLIER | I1: BRAND | J1: SKU | K1: ARTICLE | L1: DESCRIPTION | M1: HARGA NORMAL | N1: DISKON | O1: HARGA PROMO | P1: DISCOUNT TYPE
A2: 2025 CNY D75 | B2: ='2019 ALL N OLDER D95'!$B$2 -> 46121 | C2: ='2019 ALL N OLDER D95'!$C$2 -> 46127 | D2: 3260 | E2: 333 | F2: 3 | G2: 1 | H2: UOMO DONNA INDONESIA PT.-81679 | I2: AOS | J2: 50218414 | K2: WBTJCY12-1 | L2: SS T-SHIRT WB TOM AND JERRY CNY - 1 WBTJCY12-1:KHAKI:XS:GRAPHIC:SS T-SHIRT | M2: 129900 | N2: 0.75 | O2: =M2*(1-N2) -> 32475 | P2: PERCENTAGE
A3: =$A2 -> 2025 CNY D75 | B3: ='2019 ALL N OLDER D95'!$B$2 -> 46121 | C3: ='2019 ALL N OLDER D95'!$C$2 -> 46127 | D3: 3260 | E3: 333 | F3: 3 | G3: 1 | H3: UOMO DONNA INDONESIA PT.-81679 | I3: AOS | J3: 50218423 | K3: WBTJCY12-1 | L3: SS T-SHIRT WB TOM AND JERRY CNY - 1 WBTJCY12-1:KHAKI:S:GRAPHIC:SS T-SHIRT | M3: 129900 | N3: =$N2 -> 0.75 | O3: =M3*(1-N3) -> 32475 | P3: =$P2 -> PERCENTAGE
A4: =$A3 -> 2025 CNY D75 | B4: ='2019 ALL N OLDER D95'!$B$2 -> 46121 | C4: ='2019 ALL N OLDER D95'!$C$2 -> 46127 | D4: 3260 | E4: 333 | F4: 3 | G4: 1 | H4: UOMO DONNA INDONESIA PT.-81679 | I4: AOS | J4: 50218432 | K4: WBTJCY12-1 | L4: SS T-SHIRT WB TOM AND JERRY CNY - 1 WBTJCY12-1:KHAKI:M:GRAPHIC:SS T-SHIRT | M4: 129900 | N4: =$N3 -> 0.75 | O4: =M4*(1-N4) -> 32475 | P4: =$P3 -> PERCENTAGE
A5: =$A4 -> 2025 CNY D75 | B5: ='2019 ALL N OLDER D95'!$B$2 -> 46121 | C5: ='2019 ALL N OLDER D95'!$C$2 -> 46127 | D5: 3260 | E5: 333 | F5: 3 | G5: 1 | H5: UOMO DONNA INDONESIA PT.-81679 | I5: AOS | J5: 50218441 | K5: WBTJCY12-1 | L5: SS T-SHIRT WB TOM AND JERRY CNY - 1 WBTJCY12-1:KHAKI:L:GRAPHIC:SS T-SHIRT | M5: 129900 | N5: =$N4 -> 0.75 | O5: =M5*(1-N5) -> 32475 | P5: =$P4 -> PERCENTAGE
A6: =$A5 -> 2025 CNY D75 | B6: ='2019 ALL N OLDER D95'!$B$2 -> 46121 | C6: ='2019 ALL N OLDER D95'!$C$2 -> 46127 | D6: 3260 | E6: 333 | F6: 3 | G6: 1 | H6: UOMO DONNA INDONESIA PT.-81679 | I6: AOS | J6: 50218450 | K6: WBTJCY12-1 | L6: SS T-SHIRT WB TOM AND JERRY CNY - 1 WBTJCY12-1:KHAKI:XL:GRAPHIC:SS T-SHIRT | M6: 129900 | N6: =$N5 -> 0.75 | O6: =M6*(1-N6) -> 32475 | P6: =$P5 -> PERCENTAGE
A7: =$A6 -> 2025 CNY D75 | B7: ='2019 ALL N OLDER D95'!$B$2 -> 46121 | C7: ='2019 ALL N OLDER D95'!$C$2 -> 46127 | D7: 3260 | E7: 333 | F7: 3 | G7: 1 | H7: UOMO DONNA INDONESIA PT.-81679 | I7: AOS | J7: 50218469 | K7: WBTJCY12-2 | L7: SS T-SHIRT WB TOM AND JERRY CNY - 2 WBTJCY12-2:CLASSIC RED:XS:GRAPHIC:SS T-SHIRT | M7: 129900 | N7: =$N6 -> 0.75 | O7: =M7*(1-N7) -> 32475 | P7: =$P6 -> PERCENTAGE
A8: =$A7 -> 2025 CNY D75 | B8: ='2019 ALL N OLDER D95'!$B$2 -> 46121 | C8: ='2019 ALL N OLDER D95'!$C$2 -> 46127 | D8: 3260 | E8: 333 | F8: 3 | G8: 1 | H8: UOMO DONNA INDONESIA PT.-81679 | I8: AOS | J8: 50218478 | K8: WBTJCY12-2 | L8: SS T-SHIRT WB TOM AND JERRY CNY - 2 WBTJCY12-2:CLASSIC RED:S:GRAPHIC:SS T-SHIRT | M8: 129900 | N8: =$N7 -> 0.75 | O8: =M8*(1-N8) -> 32475 | P8: =$P7 -> PERCENTAGE
A9: =$A8 -> 2025 CNY D75 | B9: ='2019 ALL N OLDER D95'!$B$2 -> 46121 | C9: ='2019 ALL N OLDER D95'!$C$2 -> 46127 | D9: 3260 | E9: 333 | F9: 3 | G9: 1 | H9: UOMO DONNA INDONESIA PT.-81679 | I9: AOS | J9: 50218487 | K9: WBTJCY12-2 | L9: SS T-SHIRT WB TOM AND JERRY CNY - 2 WBTJCY12-2:CLASSIC RED:M:GRAPHIC:SS T-SHIRT | M9: 129900 | N9: =$N8 -> 0.75 | O9: =M9*(1-N9) -> 32475 | P9: =$P8 -> PERCENTAGE
A10: =$A9 -> 2025 CNY D75 | B10: ='2019 ALL N OLDER D95'!$B$2 -> 46121 | C10: ='2019 ALL N OLDER D95'!$C$2 -> 46127 | D10: 3260 | E10: 333 | F10: 3 | G10: 1 | H10: UOMO DONNA INDONESIA PT.-81679 | I10: AOS | J10: 50218496 | K10: WBTJCY12-2 | L10: SS T-SHIRT WB TOM AND JERRY CNY - 2 WBTJCY12-2:CLASSIC RED:L:GRAPHIC:SS T-SHIRT | M10: 129900 | N10: =$N9 -> 0.75 | O10: =M10*(1-N10) -> 32475 | P10: =$P9 -> PERCENTAGE
A11: =$A10 -> 2025 CNY D75 | B11: ='2019 ALL N OLDER D95'!$B$2 -> 46121 | C11: ='2019 ALL N OLDER D95'!$C$2 -> 46127 | D11: 3260 | E11: 333 | F11: 3 | G11: 1 | H11: UOMO DONNA INDONESIA PT.-81679 | I11: AOS | J11: 50218503 | K11: WBTJCY12-2 | L11: SS T-SHIRT WB TOM AND JERRY CNY - 2 WBTJCY12-2:CLASSIC RED:XL:GRAPHIC:SS T-SHIRT | M11: 129900 | N11: =$N10 -> 0.75 | O11: =M11*(1-N11) -> 32475 | P11: =$P10 -> PERCENTAGE
A12: =$A11 -> 2025 CNY D75 | B12: ='2019 ALL N OLDER D95'!$B$2 -> 46121 | C12: ='2019 ALL N OLDER D95'!$C$2 -> 46127 | D12: 3260 | E12: 333 | F12: 3 | G12: 1 | H12: UOMO DONNA INDONESIA PT.-81679 | I12: AOS | J12: 50218512 | K12: WBTJCY12-3 | L12: SS T-SHIRT WB TOM AND JERRY CNY - 3 WBTJCY12-3:CLASSIC RED:XS:GRAPHIC:SS T-SHIRT | M12: 129900 | N12: =$N11 -> 0.75 | O12: =M12*(1-N12) -> 32475 | P12: =$P11 -> PERCENTAGE
A13: =$A12 -> 2025 CNY D75 | B13: ='2019 ALL N OLDER D95'!$B$2 -> 46121 | C13: ='2019 ALL N OLDER D95'!$C$2 -> 46127 | D13: 3260 | E13: 333 | F13: 3 | G13: 1 | H13: UOMO DONNA INDONESIA PT.-81679 | I13: AOS | J13: 50218521 | K13: WBTJCY12-3 | L13: SS T-SHIRT WB TOM AND JERRY CNY - 3 WBTJCY12-3:CLASSIC RED:S:GRAPHIC:SS T-SHIRT | M13: 129900 | N13: =$N12 -> 0.75 | O13: =M13*(1-N13) -> 32475 | P13: =$P12 -> PERCENTAGE
A14: =$A13 -> 2025 CNY D75 | B14: ='2019 ALL N OLDER D95'!$B$2 -> 46121 | C14: ='2019 ALL N OLDER D95'!$C$2 -> 46127 | D14: 3260 | E14: 333 | F14: 3 | G14: 1 | H14: UOMO DONNA INDONESIA PT.-81679 | I14: AOS | J14: 50218530 | K14: WBTJCY12-3 | L14: SS T-SHIRT WB TOM AND JERRY CNY - 3 WBTJCY12-3:CLASSIC RED:M:GRAPHIC:SS T-SHIRT | M14: 129900 | N14: =$N13 -> 0.75 | O14: =M14*(1-N14) -> 32475 | P14: =$P13 -> PERCENTAGE
... A62: =$A61 -> 2025 CNY D75 | B62: ='2019 ALL N OLDER D95'!$B$2 -> 46121 | C62: ='2019 ALL N OLDER D95'!$C$2 -> 46127 | D62: 3260 | E62: 333 | F62: 3 | G62: 1 | H62: UOMO DONNA INDONESIA PT.-81679 | I62: AOS | J62: 50218656 | K62: WBTJCY12-5 | L62: SS T-SHIRT WB TOM AND JERRY CNY - 5 WBTJCY12-5:BLACK:XL:GRAPHIC:SS T-SHIRT | M62: 129900 | N62: =$N61 -> 0.75 | O62: =M62*(1-N62) -> 32475 | P62: =$P61 -> PERCENTAGE

Sheet 2025 BAMUS D75
A1: ACARA | B1: FROM DATE | C1: TO DATE | D1: DEPT | E1: WORLD | F1: DIVISION | G1: CLASS | H1: SUPPLIER | I1: BRAND | J1: SKU | K1: ARTICLE | L1: DESCRIPTION | M1: HARGA NORMAL | N1: DISKON | O1: HARGA PROMO | P1: DISCOUNT TYPE
A2: 2025 BAMUS D75 | B2: ='2019 ALL N OLDER D95'!$B$2 -> 46121 | C2: ='2019 ALL N OLDER D95'!$C$2 -> 46127 | D2: 3260 | E2: 333 | F2: 3 | G2: 1 | H2: SAHABAT GARMINDO | I2: AOS | J2: 51418170 | K2: LEB25-03 | L2: SS KOKO PRINT MUSLIM 2025 - 3 LEB25-03:FOREST GREEN:S:GRAPHIC:SS KOKO | M2: 179900 | N2: 0.75 | O2: =M2*(1-N2) -> 44975 | P2: PERCENTAGE
A3: =$A2 -> 2025 BAMUS D75 | B3: ='2019 ALL N OLDER D95'!$B$2 -> 46121 | C3: ='2019 ALL N OLDER D95'!$C$2 -> 46127 | D3: 3260 | E3: 333 | F3: 3 | G3: 1 | H3: SAHABAT GARMINDO | I3: AOS | J3: 51418189 | K3: LEB25-03 | L3: SS KOKO PRINT MUSLIM 2025 - 3 LEB25-03:FOREST GREEN:M:GRAPHIC:SS KOKO | M3: 179900 | N3: =$N2 -> 0.75 | O3: =$O$2 -> 44975 | P3: =$P2 -> PERCENTAGE
A4: =$A3 -> 2025 BAMUS D75 | B4: ='2019 ALL N OLDER D95'!$B$2 -> 46121 | C4: ='2019 ALL N OLDER D95'!$C$2 -> 46127 | D4: 3260 | E4: 333 | F4: 3 | G4: 1 | H4: SAHABAT GARMINDO | I4: AOS | J4: 51418198 | K4: LEB25-03 | L4: SS KOKO PRINT MUSLIM 2025 - 3 LEB25-03:FOREST GREEN:L:GRAPHIC:SS KOKO | M4: 179900 | N4: =$N3 -> 0.75 | O4: =$O$2 -> 44975 | P4: =$P3 -> PERCENTAGE
A5: =$A4 -> 2025 BAMUS D75 | B5: ='2019 ALL N OLDER D95'!$B$2 -> 46121 | C5: ='2019 ALL N OLDER D95'!$C$2 -> 46127 | D5: 3260 | E5: 333 | F5: 3 | G5: 1 | H5: SAHABAT GARMINDO | I5: AOS | J5: 51418205 | K5: LEB25-03 | L5: SS KOKO PRINT MUSLIM 2025 - 3 LEB25-03:FOREST GREEN:XL:GRAPHIC:SS KOKO | M5: 179900 | N5: =$N4 -> 0.75 | O5: =$O$2 -> 44975 | P5: =$P4 -> PERCENTAGE
A6: =$A5 -> 2025 BAMUS D75 | B6: ='2019 ALL N OLDER D95'!$B$2 -> 46121 | C6: ='2019 ALL N OLDER D95'!$C$2 -> 46127 | D6: 3260 | E6: 333 | F6: 3 | G6: 1 | H6: SAHABAT GARMINDO | I6: AOS | J6: 51418214 | K6: LEB25-04 | L6: SS KOKO PRINT MUSLIM 2025 - 4 LEB25-04:WHITE:S:GRAPHIC:SS KOKO | M6: 179900 | N6: =$N5 -> 0.75 | O6: =$O$2 -> 44975 | P6: =$P5 -> PERCENTAGE
A7: =$A6 -> 2025 BAMUS D75 | B7: ='2019 ALL N OLDER D95'!$B$2 -> 46121 | C7: ='2019 ALL N OLDER D95'!$C$2 -> 46127 | D7: 3260 | E7: 333 | F7: 3 | G7: 1 | H7: SAHABAT GARMINDO | I7: AOS | J7: 51418223 | K7: LEB25-04 | L7: SS KOKO PRINT MUSLIM 2025 - 4 LEB25-04:WHITE:M:GRAPHIC:SS KOKO | M7: 179900 | N7: =$N6 -> 0.75 | O7: =$O$2 -> 44975 | P7: =$P6 -> PERCENTAGE
A8: =$A7 -> 2025 BAMUS D75 | B8: ='2019 ALL N OLDER D95'!$B$2 -> 46121 | C8: ='2019 ALL N OLDER D95'!$C$2 -> 46127 | D8: 3260 | E8: 333 | F8: 3 | G8: 1 | H8: SAHABAT GARMINDO | I8: AOS | J8: 51418232 | K8: LEB25-04 | L8: SS KOKO PRINT MUSLIM 2025 - 4 LEB25-04:WHITE:L:GRAPHIC:SS KOKO | M8: 179900 | N8: =$N7 -> 0.75 | O8: =$O$2 -> 44975 | P8: =$P7 -> PERCENTAGE
A9: =$A8 -> 2025 BAMUS D75 | B9: ='2019 ALL N OLDER D95'!$B$2 -> 46121 | C9: ='2019 ALL N OLDER D95'!$C$2 -> 46127 | D9: 3260 | E9: 333 | F9: 3 | G9: 1 | H9: SAHABAT GARMINDO | I9: AOS | J9: 51418241 | K9: LEB25-04 | L9: SS KOKO PRINT MUSLIM 2025 - 4 LEB25-04:WHITE:XL:GRAPHIC:SS KOKO | M9: 179900 | N9: =$N8 -> 0.75 | O9: =$O$2 -> 44975 | P9: =$P8 -> PERCENTAGE
A10: =$A9 -> 2025 BAMUS D75 | B10: ='2019 ALL N OLDER D95'!$B$2 -> 46121 | C10: ='2019 ALL N OLDER D95'!$C$2 -> 46127 | D10: 3260 | E10: 333 | F10: 3 | G10: 1 | H10: SAHABAT GARMINDO | I10: AOS | J10: 51418250 | K10: LEB25-05 | L10: SS KOKO PRINT MUSLIM 2025 - 5 LEB25-05:PASTEL GREY:S:GRAPHIC:SS KOKO | M10: 179900 | N10: =$N9 -> 0.75 | O10: =$O$2 -> 44975 | P10: =$P9 -> PERCENTAGE
A11: =$A10 -> 2025 BAMUS D75 | B11: ='2019 ALL N OLDER D95'!$B$2 -> 46121 | C11: ='2019 ALL N OLDER D95'!$C$2 -> 46127 | D11: 3260 | E11: 333 | F11: 3 | G11: 1 | H11: SAHABAT GARMINDO | I11: AOS | J11: 51418269 | K11: LEB25-05 | L11: SS KOKO PRINT MUSLIM 2025 - 5 LEB25-05:PASTEL GREY:M:GRAPHIC:SS KOKO | M11: 179900 | N11: =$N10 -> 0.75 | O11: =$O$2 -> 44975 | P11: =$P10 -> PERCENTAGE
A12: =$A11 -> 2025 BAMUS D75 | B12: ='2019 ALL N OLDER D95'!$B$2 -> 46121 | C12: ='2019 ALL N OLDER D95'!$C$2 -> 46127 | D12: 3260 | E12: 333 | F12: 3 | G12: 1 | H12: SAHABAT GARMINDO | I12: AOS | J12: 51418278 | K12: LEB25-05 | L12: SS KOKO PRINT MUSLIM 2025 - 5 LEB25-05:PASTEL GREY:L:GRAPHIC:SS KOKO | M12: 179900 | N12: =$N11 -> 0.75 | O12: =$O$2 -> 44975 | P12: =$P11 -> PERCENTAGE
